Workbook

Sheet Leia-me
A1: Esmaltes Cone 6 — Planilha de formulação, custos e testes
A2: Linha inicial de 17 cores · oxidação · 1220–1240 °C · Fase 1 pincel → Fase 2 pó para mergulho
A5: Como usar
A6: 1. Matérias-Primas | B6: Substitua as análises químicas (%) e os preços pelos dados dos SEUS fornecedores. Os valores atuais são teóricos/típicos e os preços são estimativas ilustrativas.
A7: 2. Base A … Base E | B7: Cada aba é uma base. Edite materiais e quantidades (azul). A UMF é calculada sozinha e comparada com as faixas-alvo (verde = dentro, vermelho = ajustar).
A8: 3. Cores | B8: As 17 cores: base + colorantes (% sobre 100 da base). Custo de matéria-prima por kg calculado automaticamente.
A9: 4. Pincel | B9: FASE 1: receita do líquido para pincel — densidade-alvo e aditivos (CMC, bentonita, glicerina, defloculante, conservante) com custo.
A10: 5. Custos e Preço | B10: Fase 1 (potes para pincel) e Fase 2 (pó 500 g / 1 kg). Premissas em amarelo → preço mínimo e margem real com o preço praticado.
A11: 6. Testes | B11: Matriz de 136 placas (17 cores × 2 argilas × 2 e 3 demãos × 2 curvas). A 1ª linha é um exemplo.
A12: 7. Estabilidade | B12: Validade do líquido no pote: sedimento, mofo e densidade aos 7, 30 e 90 dias.
A13: 8. Curva de Queima | B13: Curva padrão e curva com resfriamento lento para indicar no rótulo.
A15: Legenda de cores
A16: Texto azul | B16: Dado de entrada que você pode editar
A17: Texto preto | B17: Fórmula — não editar
A18: Texto verde | B18: Vínculo com outra aba
A19: Fundo amarelo | B19: Premissa-chave para revisar
A21: Avisos importantes
A22: Receitas | B22: As receitas e % de colorantes são PONTOS DE PARTIDA para teste, não fórmulas prontas para venda. Valide tudo em placas de teste.
A23: Segurança alimentar | B23: Só rotule como "própria para alimentos" após ensaio de lixiviação (Pb/Cd e metais como Cu, Co) em laboratório acreditado (ref. ISO 6486).
A24: Saúde | B24: Sílica, cobalto, cobre e pigmentos: use exaustão e máscara PFF2/P3 ao pesar e misturar pós.
A25: Estratégia | B25: Fase 1 = líquido para pincel (produto pronto, maior valor por grama). Fase 2 = mesmo esmalte em pó para o ceramista preparar banho. As bases e cores são as mesmas nas duas fases.

Sheet Matérias-Primas
A1: Matérias-primas e colorantes
A2: Análise química em % (base queimada = sem PPC). Substitua pelos laudos dos fornecedores.
E3: Massa molar → | F3: 60.08 | G3: 101.96 | H3: 69.62 | I3: 61.98 | J3: 94.2 | K3: 29.88 | L3: 56.08 | M3: 40.3 | N3: 103.62 | O3: 81.38 | P3: 123.22 | Q3: 159.69 | R3: 79.87
A4: Material | B4: Tipo | C4: Fornecedor | D4: Preço (R$/kg) | E4: PPC (%) | F4: SiO2 (%) | G4: Al2O3 (%) | H4: B2O3 (%) | I4: Na2O (%) | J4: K2O (%) | K4: Li2O (%) | L4: CaO (%) | M4: MgO (%) | N4: SrO (%) | O4: ZnO (%) | P4: ZrO2 (%) | Q4: Fe2O3 (%) | R4: TiO2 (%) | S4: Fonte / observação
A5: Feldspato potássico | B5: Base | D5: 3.5 | E5: 0.3 | F5: 67 | G5: 18.5 | H5: 0 | I5: 3 | J5: 11 | K5: 0 | L5: 0.2 | M5: 0 | N5: 0 | O5: 0 | P5: 0 | Q5: 0.1 | R5: 0 | S5: Valor típico de feldspato potássico nacional
A6: Caulim | B6: Base | D6: 2.5 | E6: 13.9 | F6: 46.5 | G6: 39.5 | H6: 0 | I6: 0 | J6: 0 | K6: 0 | L6: 0 | M6: 0 | N6: 0 | O6: 0 | P6: 0 | Q6: 0.1 | R6: 0 | S6: Caulinita teórica
A7: Quartzo (sílica 325#) | B7: Base | D7: 2 | E7: 0 | F7: 100 | G7: 0 | H7: 0 | I7: 0 | J7: 0 | K7: 0 | L7: 0 | M7: 0 | N7: 0 | O7: 0 | P7: 0 | Q7: 0 | R7: 0 | S7: Teórico
A8: Wollastonita | B8: Base | D8: 8 | E8: 0 | F8: 51.7 | G8: 0 | H8: 0 | I8: 0 | J8: 0 | K8: 0 | L8: 48.3 | M8: 0 | N8: 0 | O8: 0 | P8: 0 | Q8: 0 | R8: 0 | S8: Teórico
A9: Carbonato de cálcio | B9: Base | D9: 2 | E9: 44 | F9: 0 | G9: 0 | H9: 0 | I9: 0 | J9: 0 | K9: 0 | L9: 56 | M9: 0 | N9: 0 | O9: 0 | P9: 0 | Q9: 0 | R9: 0 | S9: Teórico
A10: Dolomita | B10: Base | D10: 2 | E10: 47.7 | F10: 0 | G10: 0 | H10: 0 | I10: 0 | J10: 0 | K10: 0 | L10: 30.4 | M10: 21.9 | N10: 0 | O10: 0 | P10: 0 | Q10: 0 | R10: 0 | S10: Teórico
A11: Talco | B11: Base | D11: 4 | E11: 4.8 | F11: 63.5 | G11: 0 | H11: 0 | I11: 0 | J11: 0 | K11: 0 | L11: 0 | M11: 31.9 | N11: 0 | O11: 0 | P11: 0 | Q11: 0 | R11: 0 | S11: Teórico
A12: Carbonato de estrôncio | B12: Base | D12: 35 | E12: 29.8 | F12: 0 | G12: 0 | H12: 0 | I12: 0 | J12: 0 | K12: 0 | L12: 0 | M12: 0 | N12: 70.2 | O12: 0 | P12: 0 | Q12: 0 | R12: 0 | S12: Teórico
A13: Óxido de zinco | B13: Base | D13: 40 | E13: 0 | F13: 0 | G13: 0 | H13: 0 | I13: 0 | J13: 0 | K13: 0 | L13: 0 | M13: 0 | N13: 0 | O13: 100 | P13: 0 | Q13: 0 | R13: 0 | S13: Teórico
A14: Frita borácica | B14: Base | D14: 15 | E14: 0 | F14: 46.5 | G14: 0 | H14: 23.1 | I14: 10.3 | J14: 0 | K14: 0 | L14: 20.1 | M14: 0 | N14: 0 | O14: 0 | P14: 0 | Q14: 0 | R14: 0 | S14: Aproximação tipo Ferro 3134 — trocar pela ficha da frita nacional
A15: Carbonato de lítio | B15: Base | D15: 300 | E15: 59.6 | F15: 0 | G15: 0 | H15: 0 | I15: 0 | J15: 0 | K15: 40.4 | L15: 0 | M15: 0 | N15: 0 | O15: 0 | P15: 0 | Q15: 0 | R15: 0 | S15: Teórico
A16: Silicato de zircônio | B16: Colorante | D16: 25 | E16: 0 | F16: 32.8 | G16: 0 | H16: 0 | I16: 0 | J16: 0 | K16: 0 | L16: 0 | M16: 0 | N16: 0 | O16: 0 | P16: 67.2 | Q16: 0 | R16: 0 | S16: Opacificante — teórico
... A29: Conservante (isotiazolinona) | B29: Aditivo | D29: 80 | E29: 0 | F29: 0 | G29: 0 | H29: 0 | I29: 0 | J29: 0 | K29: 0 | L29: 0 | M29: 0 | N29: 0 | O29: 0 | P29: 0 | Q29: 0 | R29: 0 | S29: Aditivo pincel — biocida
A31: Linhas livres abaixo para novos materiais (mantenha o mesmo formato). Preços: estimativas ilustrativas de 2026 — substitua por cotações reais.

Sheet Base A
A1: Base A — Brilhante transparente
A2: Ponto de partida: base "20x5" adaptada a materiais nacionais.
E3: Contribuição em massa de cada óxido (g por 100 g de esmalte queimado não normalizado) →
A4: Material | B4: Quantidade (g) | C4: % normalizado | D4: Preço (R$/kg) | E4: SiO2 | F4: Al2O3 | G4: B2O3 | H4: Na2O | I4: K2O | J4: Li2O | K4: CaO | L4: MgO | M4: SrO | N4: ZnO | O4: ZrO2 | P4: Fe2O3 | Q4: TiO2
A5: Wollastonita | B5: 20 | C5: =IF(B5="","",B5/SUM($B$5:$B$14)) -> 0.2 | D5: =IF(A5="","",IFERROR(INDEX('Matérias-Primas'!$D$5:$D$45,MATCH(A5,'Matérias-Primas'!$A$5:$A$45,0)),0)) -> 8 | E5: =IF(A5="",0,C5*IFERROR(INDEX('Matérias-Primas'!$F$5:$F$45,MATCH(A5,'Matérias-Primas'!$A$5:$A$45,0)),0)) -> 10.34 | F5: =IF(A5="",0,C5*IFERROR(INDEX('Matérias-Primas'!$G$5:$G$45,MATCH(A5,'Matérias-Primas'!$A$5:$A$45,0)),0)) -> 0 | G5: =IF(A5="",0,C5*IFERROR(INDEX('Matérias-Primas'!$H$5:$H$45,MATCH(A5,'Matérias-Primas'!$A$5:$A$45,0)),0)) -> 0 | H5: =IF(A5="",0,C5*IFERROR(INDEX('Matérias-Primas'!$I$5:$I$45,MATCH(A5,'Matérias-Primas'!$A$5:$A$45,0)),0)) -> 0 | I5: =IF(A5="",0,C5*IFERROR(INDEX('Matérias-Primas'!$J$5:$J$45,MATCH(A5,'Matérias-Primas'!$A$5:$A$45,0)),0)) -> 0 | J5: =IF(A5="",0,C5*IFERROR(INDEX('Matérias-Primas'!$K$5:$K$45,MATCH(A5,'Matérias-Primas'!$A$5:$A$45,0)),0)) -> 0 | K5: =IF(A5="",0,C5*IFERROR(INDEX('Matérias-Primas'!$L$5:$L$45,MATCH(A5,'Matérias-Primas'!$A$5:$A$45,0)),0)) -> 9.66 | L5: =IF(A5="",0,C5*IFERROR(INDEX('Matérias-Primas'!$M$5:$M$45,MATCH(A5,'Matérias-Primas'!$A$5:$A$45,0)),0)) -> 0 | M5: =IF(A5="",0,C5*IFERROR(INDEX('Matérias-Primas'!$N$5:$N$45,MATCH(A5,'Matérias-Primas'!$A$5:$A$45,0)),0)) -> 0 | N5: =IF(A5="",0,C5*IFERROR(INDEX('Matérias-Primas'!$O$5:$O$45,MATCH(A5,'Matérias-Primas'!$A$5:$A$45,0)),0)) -> 0 | O5: =IF(A5="",0,C5*IFERROR(INDEX('Matérias-Primas'!$P$5:$P$45,MATCH(A5,'Matérias-Primas'!$A$5:$A$45,0)),0)) -> 0 | P5: =IF(A5="",0,C5*IFERROR(INDEX('Matérias-Primas'!$Q$5:$Q$45,MATCH(A5,'Matérias-Primas'!$A$5:$A$45,0)),0)) -> 0 | Q5: =IF(A5="",0,C5*IFERROR(INDEX('Matérias-Primas'!$R$5:$R$45,MATCH(A5,'Matérias-Primas'!$A$5:$A$45,0)),0)) -> 0
A6: Frita borácica | B6: 20 | C6: =IF(B6="","",B6/SUM($B$5:$B$14)) -> 0.2 | D6: =IF(A6="","",IFERROR(INDEX('Matérias-Primas'!$D$5:$D$45,MATCH(A6,'Matérias-Primas'!$A$5:$A$45,0)),0)) -> 15 | E6: =IF(A6="",0,C6*IFERROR(INDEX('Matérias-Primas'!$F$5:$F$45,MATCH(A6,'Matérias-Primas'!$A$5:$A$45,0)),0)) -> 9.3 | F6: =IF(A6="",0,C6*IFERROR(INDEX('Matérias-Primas'!$G$5:$G$45,MATCH(A6,'Matérias-Primas'!$A$5:$A$45,0)),0)) -> 0 | G6: =IF(A6="",0,C6*IFERROR(INDEX('Matérias-Primas'!$H$5:$H$45,MATCH(A6,'Matérias-Primas'!$A$5:$A$45,0)),0)) -> 4.62 | H6: =IF(A6="",0,C6*IFERROR(INDEX('Matérias-Primas'!$I$5:$I$45,MATCH(A6,'Matérias-Primas'!$A$5:$A$45,0)),0)) -> 2.06 | I6: =IF(A6="",0,C6*IFERROR(INDEX('Matérias-Primas'!$J$5:$J$45,MATCH(A6,'Matérias-Primas'!$A$5:$A$45,0)),0)) -> 0 | J6: =IF(A6="",0,C6*IFERROR(INDEX('Matérias-Primas'!$K$5:$K$45,MATCH(A6,'Matérias-Primas'!$A$5:$A$45,0)),0)) -> 0 | K6: =IF(A6="",0,C6*IFERROR(INDEX('Matérias-Primas'!$L$5:$L$45,MATCH(A6,'Matérias-Primas'!$A$5:$A$45,0)),0)) -> 4.02 | L6: =IF(A6="",0,C6*IFERROR(INDEX('Matérias-Primas'!$M$5:$M$45,MATCH(A6,'Matérias-Primas'!$A$5:$A$45,0)),0)) -> 0 | M6: =IF(A6="",0,C6*IFERROR(INDEX('Matérias-Primas'!$N$5:$N$45,MATCH(A6,'Matérias-Primas'!$A$5:$A$45,0)),0)) -> 0 | N6: =IF(A6="",0,C6*IFERROR(INDEX('Matérias-Primas'!$O$5:$O$45,MATCH(A6,'Matérias-Primas'!$A$5:$A$45,0)),0)) -> 0 | O6: =IF(A6="",0,C6*IFERROR(INDEX('Matérias-Primas'!$P$5:$P$45,MATCH(A6,'Matérias-Primas'!$A$5:$A$45,0)),0)) -> 0 | P6: =IF(A6="",0,C6*IFERROR(INDEX('Matérias-Primas'!$Q$5:$Q$45,MATCH(A6,'Matérias-Primas'!$A$5:$A$45,0)),0)) -> 0 | Q6: =IF(A6="",0,C6*IFERROR(INDEX('Matérias-Primas'!$R$5:$R$45,MATCH(A6,'Matérias-Primas'!$A$5:$A$45,0)),0)) -> 0
A7: Feldspato potássico | B7: 20 | C7: =IF(B7="","",B7/SUM($B$5:$B$14)) -> 0.2 | D7: =IF(A7="","",IFERROR(INDEX('Matérias-Primas'!$D$5:$D$45,MATCH(A7,'Matérias-Primas'!$A$5:$A$45,0)),0)) -> 3.5 | E7: =IF(A7="",0,C7*IFERROR(INDEX('Matérias-Primas'!$F$5:$F$45,MATCH(A7,'Matérias-Primas'!$A$5:$A$45,0)),0)) -> 13.4 | F7: =IF(A7="",0,C7*IFERROR(INDEX('Matérias-Primas'!$G$5:$G$45,MATCH(A7,'Matérias-Primas'!$A$5:$A$45,0)),0)) -> 3.7 | G7: =IF(A7="",0,C7*IFERROR(INDEX('Matérias-Primas'!$H$5:$H$45,MATCH(A7,'Matérias-Primas'!$A$5:$A$45,0)),0)) -> 0 | H7: =IF(A7="",0,C7*IFERROR(INDEX('Matérias-Primas'!$I$5:$I$45,MATCH(A7,'Matérias-Primas'!$A$5:$A$45,0)),0)) -> 0.6 | I7: =IF(A7="",0,C7*IFERROR(INDEX('Matérias-Primas'!$J$5:$J$45,MATCH(A7,'Matérias-Primas'!$A$5:$A$45,0)),0)) -> 2.2 | J7: =IF(A7="",0,C7*IFERROR(INDEX('Matérias-Primas'!$K$5:$K$45,MATCH(A7,'Matérias-Primas'!$A$5:$A$45,0)),0)) -> 0 | K7: =IF(A7="",0,C7*IFERROR(INDEX('Matérias-Primas'!$L$5:$L$45,MATCH(A7,'Matérias-Primas'!$A$5:$A$45,0)),0)) -> 0.04 | L7: =IF(A7="",0,C7*IFERROR(INDEX('Matérias-Primas'!$M$5:$M$45,MATCH(A7,'Matérias-Primas'!$A$5:$A$45,0)),0)) -> 0 | M7: =IF(A7="",0,C7*IFERROR(INDEX('Matérias-Primas'!$N$5:$N$45,MATCH(A7,'Matérias-Primas'!$A$5:$A$45,0)),0)) -> 0 | N7: =IF(A7="",0,C7*IFERROR(INDEX('Matérias-Primas'!$O$5:$O$45,MATCH(A7,'Matérias-Primas'!$A$5:$A$45,0)),0)) -> 0 | O7: =IF(A7="",0,C7*IFERROR(INDEX('Matérias-Primas'!$P$5:$P$45,MATCH(A7,'Matérias-Primas'!$A$5:$A$45,0)),0)) -> 0 | P7: =IF(A7="",0,C7*IFERROR(INDEX('Matérias-Primas'!$Q$5:$Q$45,MATCH(A7,'Matérias-Primas'!$A$5:$A$45,0)),0)) -> 0.02 | Q7: =IF(A7="",0,C7*IFERROR(INDEX('Matérias-Primas'!$R$5:$R$45,MATCH(A7,'Matérias-Primas'!$A$5:$A$45,0)),0)) -> 0
A8: Caulim | B8: 20 | C8: =IF(B8="","",B8/SUM($B$5:$B$14)) -> 0.2 | D8: =IF(A8="","",IFERROR(INDEX('Matérias-Primas'!$D$5:$D$45,MATCH(A8,'Matérias-Primas'!$A$5:$A$45,0)),0)) -> 2.5 | E8: =IF(A8="",0,C8*IFERROR(INDEX('Matérias-Primas'!$F$5:$F$45,MATCH(A8,'Matérias-Primas'!$A$5:$A$45,0)),0)) -> 9.3 | F8: =IF(A8="",0,C8*IFERROR(INDEX('Matérias-Primas'!$G$5:$G$45,MATCH(A8,'Matérias-Primas'!$A$5:$A$45,0)),0)) -> 7.9 | G8: =IF(A8="",0,C8*IFERROR(INDEX('Matérias-Primas'!$H$5:$H$45,MATCH(A8,'Matérias-Primas'!$A$5:$A$45,0)),0)) -> 0 | H8: =IF(A8="",0,C8*IFERROR(INDEX('Matérias-Primas'!$I$5:$I$45,MATCH(A8,'Matérias-Primas'!$A$5:$A$45,0)),0)) -> 0 | I8: =IF(A8="",0,C8*IFERROR(INDEX('Matérias-Primas'!$J$5:$J$45,MATCH(A8,'Matérias-Primas'!$A$5:$A$45,0)),0)) -> 0 | J8: =IF(A8="",0,C8*IFERROR(INDEX('Matérias-Primas'!$K$5:$K$45,MATCH(A8,'Matérias-Primas'!$A$5:$A$45,0)),0)) -> 0 | K8: =IF(A8="",0,C8*IFERROR(INDEX('Matérias-Primas'!$L$5:$L$45,MATCH(A8,'Matérias-Primas'!$A$5:$A$45,0)),0)) -> 0 | L8: =IF(A8="",0,C8*IFERROR(INDEX('Matérias-Primas'!$M$5:$M$45,MATCH(A8,'Matérias-Primas'!$A$5:$A$45,0)),0)) -> 0 | M8: =IF(A8="",0,C8*IFERROR(INDEX('Matérias-Primas'!$N$5:$N$45,MATCH(A8,'Matérias-Primas'!$A$5:$A$45,0)),0)) -> 0 | N8: =IF(A8="",0,C8*IFERROR(INDEX('Matérias-Primas'!$O$5:$O$45,MATCH(A8,'Matérias-Primas'!$A$5:$A$45,0)),0)) -> 0 | O8: =IF(A8="",0,C8*IFERROR(INDEX('Matérias-Primas'!$P$5:$P$45,MATCH(A8,'Matérias-Primas'!$A$5:$A$45,0)),0)) -> 0 | P8: =IF(A8="",0,C8*IFERROR(INDEX('Matérias-Primas'!$Q$5:$Q$45,MATCH(A8,'Matérias-Primas'!$A$5:$A$45,0)),0)) -> 0.02 | Q8: =IF(A8="",0,C8*IFERROR(INDEX('Matérias-Primas'!$R$5:$R$45,MATCH(A8,'Matérias-Primas'!$A$5:$A$45,0)),0)) -> 0
A9: Quartzo (sílica 325#) | B9: 20 | C9: =IF(B9="","",B9/SUM($B$5:$B$14)) -> 0.2 | D9: =IF(A9="","",IFERROR(INDEX('Matérias-Primas'!$D$5:$D$45,MATCH(A9,'Matérias-Primas'!$A$5:$A$45,0)),0)) -> 2 | E9: =IF(A9="",0,C9*IFERROR(INDEX('Matérias-Primas'!$F$5:$F$45,MATCH(A9,'Matérias-Primas'!$A$5:$A$45,0)),0)) -> 20 | F9: =IF(A9="",0,C9*IFERROR(INDEX('Matérias-Primas'!$G$5:$G$45,MATCH(A9,'Matérias-Primas'!$A$5:$A$45,0)),0)) -> 0 | G9: =IF(A9="",0,C9*IFERROR(INDEX('Matérias-Primas'!$H$5:$H$45,MATCH(A9,'Matérias-Primas'!$A$5:$A$45,0)),0)) -> 0 | H9: =IF(A9="",0,C9*IFERROR(INDEX('Matérias-Primas'!$I$5:$I$45,MATCH(A9,'Matérias-Primas'!$A$5:$A$45,0)),0)) -> 0 | I9: =IF(A9="",0,C9*IFERROR(INDEX('Matérias-Primas'!$J$5:$J$45,MATCH(A9,'Matérias-Primas'!$A$5:$A$45,0)),0)) -> 0 | J9: =IF(A9="",0,C9*IFERROR(INDEX('Matérias-Primas'!$K$5:$K$45,MATCH(A9,'Matérias-Primas'!$A$5:$A$45,0)),0)) -> 0 | K9: =IF(A9="",0,C9*IFERROR(INDEX('Matérias-Primas'!$L$5:$L$45,MATCH(A9,'Matérias-Primas'!$A$5:$A$45,0)),0)) -> 0 | L9: =IF(A9="",0,C9*IFERROR(INDEX('Matérias-Primas'!$M$5:$M$45,MATCH(A9,'Matérias-Primas'!$A$5:$A$45,0)),0)) -> 0 | M9: =IF(A9="",0,C9*IFERROR(INDEX('Matérias-Primas'!$N$5:$N$45,MATCH(A9,'Matérias-Primas'!$A$5:$A$45,0)),0)) -> 0 | N9: =IF(A9="",0,C9*IFERROR(INDEX('Matérias-Primas'!$O$5:$O$45,MATCH(A9,'Matérias-Primas'!$A$5:$A$45,0)),0)) -> 0 | O9: =IF(A9="",0,C9*IFERROR(INDEX('Matérias-Primas'!$P$5:$P$45,MATCH(A9,'Matérias-Primas'!$A$5:$A$45,0)),0)) -> 0 | P9: =IF(A9="",0,C9*IFERROR(INDEX('Matérias-Primas'!$Q$5:$Q$45,MATCH(A9,'Matérias-Primas'!$A$5:$A$45,0)),0)) -> 0 | Q9: =IF(A9="",0,C9*IFERROR(INDEX('Matérias-Primas'!$R$5:$R$45,MATCH(A9,'Matérias-Primas'!$A$5:$A$45,0)),0)) -> 0
C10: =IF(B10="","",B10/SUM($B$5:$B$14)) | D10: =IF(A10="","",IFERROR(INDEX('Matérias-Primas'!$D$5:$D$45,MATCH(A10,'Matérias-Primas'!$A$5:$A$45,0)),0)) | E10: =IF(A10="",0,C10*IFERROR(INDEX('Matérias-Primas'!$F$5:$F$45,MATCH(A10,'Matérias-Primas'!$A$5:$A$45,0)),0)) -> 0 | F10: =IF(A10="",0,C10*IFERROR(INDEX('Matérias-Primas'!$G$5:$G$45,MATCH(A10,'Matérias-Primas'!$A$5:$A$45,0)),0)) -> 0 | G10: =IF(A10="",0,C10*IFERROR(INDEX('Matérias-Primas'!$H$5:$H$45,MATCH(A10,'Matérias-Primas'!$A$5:$A$45,0)),0)) -> 0 | H10: =IF(A10="",0,C10*IFERROR(INDEX('Matérias-Primas'!$I$5:$I$45,MATCH(A10,'Matérias-Primas'!$A$5:$A$45,0)),0)) -> 0 | I10: =IF(A10="",0,C10*IFERROR(INDEX('Matérias-Primas'!$J$5:$J$45,MATCH(A10,'Matérias-Primas'!$A$5:$A$45,0)),0)) -> 0 | J10: =IF(A10="",0,C10*IFERROR(INDEX('Matérias-Primas'!$K$5:$K$45,MATCH(A10,'Matérias-Primas'!$A$5:$A$45,0)),0)) -> 0 | K10: =IF(A10="",0,C10*IFERROR(INDEX('Matérias-Primas'!$L$5:$L$45,MATCH(A10,'Matérias-Primas'!$A$5:$A$45,0)),0)) -> 0 | L10: =IF(A10="",0,C10*IFERROR(INDEX('Matérias-Primas'!$M$5:$M$45,MATCH(A10,'Matérias-Primas'!$A$5:$A$45,0)),0)) -> 0 | M10: =IF(A10="",0,C10*IFERROR(INDEX('Matérias-Primas'!$N$5:$N$45,MATCH(A10,'Matérias-Primas'!$A$5:$A$45,0)),0)) -> 0 | N10: =IF(A10="",0,C10*IFERROR(INDEX('Matérias-Primas'!$O$5:$O$45,MATCH(A10,'Matérias-Primas'!$A$5:$A$45,0)),0)) -> 0 | O10: =IF(A10="",0,C10*IFERROR(INDEX('Matérias-Primas'!$P$5:$P$45,MATCH(A10,'Matérias-Primas'!$A$5:$A$45,0)),0)) -> 0 | P10: =IF(A10="",0,C10*IFERROR(INDEX('Matérias-Primas'!$Q$5:$Q$45,MATCH(A10,'Matérias-Primas'!$A$5:$A$45,0)),0)) -> 0 | Q10: =IF(A10="",0,C10*IFERROR(INDEX('Matérias-Primas'!$R$5:$R$45,MATCH(A10,'Matérias-Primas'!$A$5:$A$45,0)),0)) -> 0
C11: =IF(B11="","",B11/SUM($B$5:$B$14)) | D11: =IF(A11="","",IFERROR(INDEX('Matérias-Primas'!$D$5:$D$45,MATCH(A11,'Matérias-Primas'!$A$5:$A$45,0)),0)) | E11: =IF(A11="",0,C11*IFERROR(INDEX('Matérias-Primas'!$F$5:$F$45,MATCH(A11,'Matérias-Primas'!$A$5:$A$45,0)),0)) -> 0 | F11: =IF(A11="",0,C11*IFERROR(INDEX('Matérias-Primas'!$G$5:$G$45,MATCH(A11,'Matérias-Primas'!$A$5:$A$45,0)),0)) -> 0 | G11: =IF(A11="",0,C11*IFERROR(INDEX('Matérias-Primas'!$H$5:$H$45,MATCH(A11,'Matérias-Primas'!$A$5:$A$45,0)),0)) -> 0 | H11: =IF(A11="",0,C11*IFERROR(INDEX('Matérias-Primas'!$I$5:$I$45,MATCH(A11,'Matérias-Primas'!$A$5:$A$45,0)),0)) -> 0 | I11: =IF(A11="",0,C11*IFERROR(INDEX('Matérias-Primas'!$J$5:$J$45,MATCH(A11,'Matérias-Primas'!$A$5:$A$45,0)),0)) -> 0 | J11: =IF(A11="",0,C11*IFERROR(INDEX('Matérias-Primas'!$K$5:$K$45,MATCH(A11,'Matérias-Primas'!$A$5:$A$45,0)),0)) -> 0 | K11: =IF(A11="",0,C11*IFERROR(INDEX('Matérias-Primas'!$L$5:$L$45,MATCH(A11,'Matérias-Primas'!$A$5:$A$45,0)),0)) -> 0 | L11: =IF(A11="",0,C11*IFERROR(INDEX('Matérias-Primas'!$M$5:$M$45,MATCH(A11,'Matérias-Primas'!$A$5:$A$45,0)),0)) -> 0 | M11: =IF(A11="",0,C11*IFERROR(INDEX('Matérias-Primas'!$N$5:$N$45,MATCH(A11,'Matérias-Primas'!$A$5:$A$45,0)),0)) -> 0 | N11: =IF(A11="",0,C11*IFERROR(INDEX('Matérias-Primas'!$O$5:$O$45,MATCH(A11,'Matérias-Primas'!$A$5:$A$45,0)),0)) -> 0 | O11: =IF(A11="",0,C11*IFERROR(INDEX('Matérias-Primas'!$P$5:$P$45,MATCH(A11,'Matérias-Primas'!$A$5:$A$45,0)),0)) -> 0 | P11: =IF(A11="",0,C11*IFERROR(INDEX('Matérias-Primas'!$Q$5:$Q$45,MATCH(A11,'Matérias-Primas'!$A$5:$A$45,0)),0)) -> 0 | Q11: =IF(A11="",0,C11*IFERROR(INDEX('Matérias-Primas'!$R$5:$R$45,MATCH(A11,'Matérias-Primas'!$A$5:$A$45,0)),0)) -> 0
C12: =IF(B12="","",B12/SUM($B$5:$B$14)) | D12: =IF(A12="","",IFERROR(INDEX('Matérias-Primas'!$D$5:$D$45,MATCH(A12,'Matérias-Primas'!$A$5:$A$45,0)),0)) | E12: =IF(A12="",0,C12*IFERROR(INDEX('Matérias-Primas'!$F$5:$F$45,MATCH(A12,'Matérias-Primas'!$A$5:$A$45,0)),0)) -> 0 | F12: =IF(A12="",0,C12*IFERROR(INDEX('Matérias-Primas'!$G$5:$G$45,MATCH(A12,'Matérias-Primas'!$A$5:$A$45,0)),0)) -> 0 | G12: =IF(A12="",0,C12*IFERROR(INDEX('Matérias-Primas'!$H$5:$H$45,MATCH(A12,'Matérias-Primas'!$A$5:$A$45,0)),0)) -> 0 | H12: =IF(A12="",0,C12*IFERROR(INDEX('Matérias-Primas'!$I$5:$I$45,MATCH(A12,'Matérias-Primas'!$A$5:$A$45,0)),0)) -> 0 | I12: =IF(A12="",0,C12*IFERROR(INDEX('Matérias-Primas'!$J$5:$J$45,MATCH(A12,'Matérias-Primas'!$A$5:$A$45,0)),0)) -> 0 | J12: =IF(A12="",0,C12*IFERROR(INDEX('Matérias-Primas'!$K$5:$K$45,MATCH(A12,'Matérias-Primas'!$A$5:$A$45,0)),0)) -> 0 | K12: =IF(A12="",0,C12*IFERROR(INDEX('Matérias-Primas'!$L$5:$L$45,MATCH(A12,'Matérias-Primas'!$A$5:$A$45,0)),0)) -> 0 | L12: =IF(A12="",0,C12*IFERROR(INDEX('Matérias-Primas'!$M$5:$M$45,MATCH(A12,'Matérias-Primas'!$A$5:$A$45,0)),0)) -> 0 | M12: =IF(A12="",0,C12*IFERROR(INDEX('Matérias-Primas'!$N$5:$N$45,MATCH(A12,'Matérias-Primas'!$A$5:$A$45,0)),0)) -> 0 | N12: =IF(A12="",0,C12*IFERROR(INDEX('Matérias-Primas'!$O$5:$O$45,MATCH(A12,'Matérias-Primas'!$A$5:$A$45,0)),0)) -> 0 | O12: =IF(A12="",0,C12*IFERROR(INDEX('Matérias-Primas'!$P$5:$P$45,MATCH(A12,'Matérias-Primas'!$A$5:$A$45,0)),0)) -> 0 | P12: =IF(A12="",0,C12*IFERROR(INDEX('Matérias-Primas'!$Q$5:$Q$45,MATCH(A12,'Matérias-Primas'!$A$5:$A$45,0)),0)) -> 0 | Q12: =IF(A12="",0,C12*IFERROR(INDEX('Matérias-Primas'!$R$5:$R$45,MATCH(A12,'Matérias-Primas'!$A$5:$A$45,0)),0)) -> 0
C13: =IF(B13="","",B13/SUM($B$5:$B$14)) | D13: =IF(A13="","",IFERROR(INDEX('Matérias-Primas'!$D$5:$D$45,MATCH(A13,'Matérias-Primas'!$A$5:$A$45,0)),0)) | E13: =IF(A13="",0,C13*IFERROR(INDEX('Matérias-Primas'!$F$5:$F$45,MATCH(A13,'Matérias-Primas'!$A$5:$A$45,0)),0)) -> 0 | F13: =IF(A13="",0,C13*IFERROR(INDEX('Matérias-Primas'!$G$5:$G$45,MATCH(A13,'Matérias-Primas'!$A$5:$A$45,0)),0)) -> 0 | G13: =IF(A13="",0,C13*IFERROR(INDEX('Matérias-Primas'!$H$5:$H$45,MATCH(A13,'Matérias-Primas'!$A$5:$A$45,0)),0)) -> 0 | H13: =IF(A13="",0,C13*IFERROR(INDEX('Matérias-Primas'!$I$5:$I$45,MATCH(A13,'Matérias-Primas'!$A$5:$A$45,0)),0)) -> 0 | I13: =IF(A13="",0,C13*IFERROR(INDEX('Matérias-Primas'!$J$5:$J$45,MATCH(A13,'Matérias-Primas'!$A$5:$A$45,0)),0)) -> 0 | J13: =IF(A13="",0,C13*IFERROR(INDEX('Matérias-Primas'!$K$5:$K$45,MATCH(A13,'Matérias-Primas'!$A$5:$A$45,0)),0)) -> 0 | K13: =IF(A13="",0,C13*IFERROR(INDEX('Matérias-Primas'!$L$5:$L$45,MATCH(A13,'Matérias-Primas'!$A$5:$A$45,0)),0)) -> 0 | L13: =IF(A13="",0,C13*IFERROR(INDEX('Matérias-Primas'!$M$5:$M$45,MATCH(A13,'Matérias-Primas'!$A$5:$A$45,0)),0)) -> 0 | M13: =IF(A13="",0,C13*IFERROR(INDEX('Matérias-Primas'!$N$5:$N$45,MATCH(A13,'Matérias-Primas'!$A$5:$A$45,0)),0)) -> 0 | N13: =IF(A13="",0,C13*IFERROR(INDEX('Matérias-Primas'!$O$5:$O$45,MATCH(A13,'Matérias-Primas'!$A$5:$A$45,0)),0)) -> 0 | O13: =IF(A13="",0,C13*IFERROR(INDEX('Matérias-Primas'!$P$5:$P$45,MATCH(A13,'Matérias-Primas'!$A$5:$A$45,0)),0)) -> 0 | P13: =IF(A13="",0,C13*IFERROR(INDEX('Matérias-Primas'!$Q$5:$Q$45,MATCH(A13,'Matérias-Primas'!$A$5:$A$45,0)),0)) -> 0 | Q13: =IF(A13="",0,C13*IFERROR(INDEX('Matérias-Primas'!$R$5:$R$45,MATCH(A13,'Matérias-Primas'!$A$5:$A$45,0)),0)) -> 0
C14: =IF(B14="","",B14/SUM($B$5:$B$14)) | D14: =IF(A14="","",IFERROR(INDEX('Matérias-Primas'!$D$5:$D$45,MATCH(A14,'Matérias-Primas'!$A$5:$A$45,0)),0)) | E14: =IF(A14="",0,C14*IFERROR(INDEX('Matérias-Primas'!$F$5:$F$45,MATCH(A14,'Matérias-Primas'!$A$5:$A$45,0)),0)) -> 0 | F14: =IF(A14="",0,C14*IFERROR(INDEX('Matérias-Primas'!$G$5:$G$45,MATCH(A14,'Matérias-Primas'!$A$5:$A$45,0)),0)) -> 0 | G14: =IF(A14="",0,C14*IFERROR(INDEX('Matérias-Primas'!$H$5:$H$45,MATCH(A14,'Matérias-Primas'!$A$5:$A$45,0)),0)) -> 0 | H14: =IF(A14="",0,C14*IFERROR(INDEX('Matérias-Primas'!$I$5:$I$45,MATCH(A14,'Matérias-Primas'!$A$5:$A$45,0)),0)) -> 0 | I14: =IF(A14="",0,C14*IFERROR(INDEX('Matérias-Primas'!$J$5:$J$45,MATCH(A14,'Matérias-Primas'!$A$5:$A$45,0)),0)) -> 0 | J14: =IF(A14="",0,C14*IFERROR(INDEX('Matérias-Primas'!$K$5:$K$45,MATCH(A14,'Matérias-Primas'!$A$5:$A$45,0)),0)) -> 0 | K14: =IF(A14="",0,C14*IFERROR(INDEX('Matérias-Primas'!$L$5:$L$45,MATCH(A14,'Matérias-Primas'!$A$5:$A$45,0)),0)) -> 0 | L14: =IF(A14="",0,C14*IFERROR(INDEX('Matérias-Primas'!$M$5:$M$45,MATCH(A14,'Matérias-Primas'!$A$5:$A$45,0)),0)) -> 0 | M14: =IF(A14="",0,C14*IFERROR(INDEX('Matérias-Primas'!$N$5:$N$45,MATCH(A14,'Matérias-Primas'!$A$5:$A$45,0)),0)) -> 0 | N14: =IF(A14="",0,C14*IFERROR(INDEX('Matérias-Primas'!$O$5:$O$45,MATCH(A14,'Matérias-Primas'!$A$5:$A$45,0)),0)) -> 0 | O14: =IF(A14="",0,C14*IFERROR(INDEX('Matérias-Primas'!$P$5:$P$45,MATCH(A14,'Matérias-Primas'!$A$5:$A$45,0)),0)) -> 0 | P14: =IF(A14="",0,C14*IFERROR(INDEX('Matérias-Primas'!$Q$5:$Q$45,MATCH(A14,'Matérias-Primas'!$A$5:$A$45,0)),0)) -> 0 | Q14: =IF(A14="",0,C14*IFERROR(INDEX('Matérias-Primas'!$R$5:$R$45,MATCH(A14,'Matérias-Primas'!$A$5:$A$45,0)),0)) -> 0
A15: Total | B15: =SUM(B5:B14) -> 100 | C15: =SUM(C5:C14) -> 1 | E15: =SUM(E5:E14) -> 62.34 | F15: =SUM(F5:F14) -> 11.6 | G15: =SUM(G5:G14) -> 4.62 | H15: =SUM(H5:H14) -> 2.66 | I15: =SUM(I5:I14) -> 2.2 | J15: =SUM(J5:J14) -> 0 | K15: =SUM(K5:K14) -> 13.72 | L15: =SUM(L5:L14) -> 0 | ... Q15: =SUM(Q5:Q14) -> 0
A16: Massa molar | E16: ='Matérias-Primas'!F3 -> 60.08 | F16: ='Matérias-Primas'!G3 -> 101.96 | G16: ='Matérias-Primas'!H3 -> 69.62 | H16: ='Matérias-Primas'!I3 -> 61.98 | I16: ='Matérias-Primas'!J3 -> 94.2 | J16: ='Matérias-Primas'!K3 -> 29.88 | K16: ='Matérias-Primas'!L3 -> 56.08 | L16: ='Matérias-Primas'!M3 -> 40.3 | ... Q16: ='Matérias-Primas'!R3 -> 79.87
A17: Mols | C17: Soma fundentes: | D17: =H17+I17+J17+K17+L17+M17+N17 -> 0.31092213 | E17: =E15/E16 -> 1.0376165 | F17: =F15/F16 -> 0.11377011 | G17: =G15/G16 -> 0.066360241 | H17: =H15/H16 -> 0.04291707 | I17: =I15/I16 -> 0.023354565 | J17: =J15/J16 -> 0 | K17: =K15/K16 -> 0.2446505 | L17: =L15/L16 -> 0 | ... Q17: =Q15/Q16 -> 0
A18: UMF (fundentes = 1) | E18: =IF($D$17=0,0,E17/$D$17) -> 3.337223 | F18: =IF($D$17=0,0,F17/$D$17) -> 0.36591189 | G18: =IF($D$17=0,0,G17/$D$17) -> 0.21343042 | H18: =IF($D$17=0,0,H17/$D$17) -> 0.13803157 | I18: =IF($D$17=0,0,I17/$D$17) -> 0.07511387 | J18: =IF($D$17=0,0,J17/$D$17) -> 0 | K18: =IF($D$17=0,0,K17/$D$17) -> 0.78685456 | L18: =IF($D$17=0,0,L17/$D$17) -> 0 | ... Q18: =IF($D$17=0,0,Q17/$D$17) -> 0
A20: Checagem contra faixas-alvo
A21: Indicador | B21: Valor | C21: Mín | D21: Máx | E21: Status
A22: SiO₂ (UMF) | B22: =E18 -> 3.337223 | C22: 3 | D22: 4 | E22: =IF(AND(B22>=C22,B22<=D22),"OK","Ajustar") -> OK
A23: Al₂O₃ (UMF) | B23: =F18 -> 0.36591189 | C23: 0.3 | D23: 0.4 | E23: =IF(AND(B23>=C23,B23<=D23),"OK","Ajustar") -> OK
A24: B₂O₃ (UMF) | B24: =G18 -> 0.21343042 | C24: 0.1 | D24: 0.3 | E24: =IF(AND(B24>=C24,B24<=D24),"OK","Ajustar") -> OK
A25: Razão SiO₂:Al₂O₃ | B25: =IF(F18=0,0,E18/F18) -> 9.1202913 | C25: 8 | D25: 10 | E25: =IF(AND(B25>=C25,B25<=D25),"OK","Ajustar") -> OK
A27: Custo matéria-prima da base (R$/kg) | B27: =SUMPRODUCT(C5:C14,D5:D14) -> 6.2
A28: Faixas-alvo são referências de literatura para cone 6 estável; ajuste-as conforme seus testes. Fórmula-alvo calculada sobre óxidos; colorantes entram na aba Cores.

Sheet Base B
A1: Base B — Mate/acetinada cálcica (sem zinco)
A2: Mate por alumina alta + cálcio. Sem zinco para permitir o rosa cromo-estanho.
E3: Contribuição em massa de cada óxido (g por 100 g de esmalte queimado não normalizado) →
A4: Material | B4: Quantidade (g) | C4: % normalizado | D4: Preço (R$/kg) | E4: SiO2 | F4: Al2O3 | G4: B2O3 | H4: Na2O | I4: K2O | J4: Li2O | K4: CaO | L4: MgO | M4: SrO | N4: ZnO | O4: ZrO2 | P4: Fe2O3 | Q4: TiO2
A5: Feldspato potássico | B5: 30 | C5: =IF(B5="","",B5/SUM($B$5:$B$14)) -> 0.3 | D5: =IF(A5="","",IFERROR(INDEX('Matérias-Primas'!$D$5:$D$45,MATCH(A5,'Matérias-Primas'!$A$5:$A$45,0)),0)) -> 3.5 | E5: =IF(A5="",0,C5*IFERROR(INDEX('Matérias-Primas'!$F$5:$F$45,MATCH(A5,'Matérias-Primas'!$A$5:$A$45,0)),0)) -> 20.1 | F5: =IF(A5="",0,C5*IFERROR(INDEX('Matérias-Primas'!$G$5:$G$45,MATCH(A5,'Matérias-Primas'!$A$5:$A$45,0)),0)) -> 5.55 | G5: =IF(A5="",0,C5*IFERROR(INDEX('Matérias-Primas'!$H$5:$H$45,MATCH(A5,'Matérias-Primas'!$A$5:$A$45,0)),0)) -> 0 | H5: =IF(A5="",0,C5*IFERROR(INDEX('Matérias-Primas'!$I$5:$I$45,MATCH(A5,'Matérias-Primas'!$A$5:$A$45,0)),0)) -> 0.9 | I5: =IF(A5="",0,C5*IFERROR(INDEX('Matérias-Primas'!$J$5:$J$45,MATCH(A5,'Matérias-Primas'!$A$5:$A$45,0)),0)) -> 3.3 | J5: =IF(A5="",0,C5*IFERROR(INDEX('Matérias-Primas'!$K$5:$K$45,MATCH(A5,'Matérias-Primas'!$A$5:$A$45,0)),0)) -> 0 | K5: =IF(A5="",0,C5*IFERROR(INDEX('Matérias-Primas'!$L$5:$L$45,MATCH(A5,'Matérias-Primas'!$A$5:$A$45,0)),0)) -> 0.06 | L5: =IF(A5="",0,C5*IFERROR(INDEX('Matérias-Primas'!$M$5:$M$45,MATCH(A5,'Matérias-Primas'!$A$5:$A$45,0)),0)) -> 0 | M5: =IF(A5="",0,C5*IFERROR(INDEX('Matérias-Primas'!$N$5:$N$45,MATCH(A5,'Matérias-Primas'!$A$5:$A$45,0)),0)) -> 0 | N5: =IF(A5="",0,C5*IFERROR(INDEX('Matérias-Primas'!$O$5:$O$45,MATCH(A5,'Matérias-Primas'!$A$5:$A$45,0)),0)) -> 0 | O5: =IF(A5="",0,C5*IFERROR(INDEX('Matérias-Primas'!$P$5:$P$45,MATCH(A5,'Matérias-Primas'!$A$5:$A$45,0)),0)) -> 0 | P5: =IF(A5="",0,C5*IFERROR(INDEX('Matérias-Primas'!$Q$5:$Q$45,MATCH(A5,'Matérias-Primas'!$A$5:$A$45,0)),0)) -> 0.03 | Q5: =IF(A5="",0,C5*IFERROR(INDEX('Matérias-Primas'!$R$5:$R$45,MATCH(A5,'Matérias-Primas'!$A$5:$A$45,0)),0)) -> 0
A6: Frita borácica | B6: 12 | C6: =IF(B6="","",B6/SUM($B$5:$B$14)) -> 0.12 | D6: =IF(A6="","",IFERROR(INDEX('Matérias-Primas'!$D$5:$D$45,MATCH(A6,'Matérias-Primas'!$A$5:$A$45,0)),0)) -> 15 | E6: =IF(A6="",0,C6*IFERROR(INDEX('Matérias-Primas'!$F$5:$F$45,MATCH(A6,'Matérias-Primas'!$A$5:$A$45,0)),0)) -> 5.58 | F6: =IF(A6="",0,C6*IFERROR(INDEX('Matérias-Primas'!$G$5:$G$45,MATCH(A6,'Matérias-Primas'!$A$5:$A$45,0)),0)) -> 0 | G6: =IF(A6="",0,C6*IFERROR(INDEX('Matérias-Primas'!$H$5:$H$45,MATCH(A6,'Matérias-Primas'!$A$5:$A$45,0)),0)) -> 2.772 | H6: =IF(A6="",0,C6*IFERROR(INDEX('Matérias-Primas'!$I$5:$I$45,MATCH(A6,'Matérias-Primas'!$A$5:$A$45,0)),0)) -> 1.236 | I6: =IF(A6="",0,C6*IFERROR(INDEX('Matérias-Primas'!$J$5:$J$45,MATCH(A6,'Matérias-Primas'!$A$5:$A$45,0)),0)) -> 0 | J6: =IF(A6="",0,C6*IFERROR(INDEX('Matérias-Primas'!$K$5:$K$45,MATCH(A6,'Matérias-Primas'!$A$5:$A$45,0)),0)) -> 0 | K6: =IF(A6="",0,C6*IFERROR(INDEX('Matérias-Primas'!$L$5:$L$45,MATCH(A6,'Matérias-Primas'!$A$5:$A$45,0)),0)) -> 2.412 | L6: =IF(A6="",0,C6*IFERROR(INDEX('Matérias-Primas'!$M$5:$M$45,MATCH(A6,'Matérias-Primas'!$A$5:$A$45,0)),0)) -> 0 | M6: =IF(A6="",0,C6*IFERROR(INDEX('Matérias-Primas'!$N$5:$N$45,MATCH(A6,'Matérias-Primas'!$A$5:$A$45,0)),0)) -> 0 | N6: =IF(A6="",0,C6*IFERROR(INDEX('Matérias-Primas'!$O$5:$O$45,MATCH(A6,'Matérias-Primas'!$A$5:$A$45,0)),0)) -> 0 | O6: =IF(A6="",0,C6*IFERROR(INDEX('Matérias-Primas'!$P$5:$P$45,MATCH(A6,'Matérias-Primas'!$A$5:$A$45,0)),0)) -> 0 | P6: =IF(A6="",0,C6*IFERROR(INDEX('Matérias-Primas'!$Q$5:$Q$45,MATCH(A6,'Matérias-Primas'!$A$5:$A$45,0)),0)) -> 0 | Q6: =IF(A6="",0,C6*IFERROR(INDEX('Matérias-Primas'!$R$5:$R$45,MATCH(A6,'Matérias-Primas'!$A$5:$A$45,0)),0)) -> 0
A7: Wollastonita | B7: 22 | C7: =IF(B7="","",B7/SUM($B$5:$B$14)) -> 0.22 | D7: =IF(A7="","",IFERROR(INDEX('Matérias-Primas'!$D$5:$D$45,MATCH(A7,'Matérias-Primas'!$A$5:$A$45,0)),0)) -> 8 | E7: =IF(A7="",0,C7*IFERROR(INDEX('Matérias-Primas'!$F$5:$F$45,MATCH(A7,'Matérias-Primas'!$A$5:$A$45,0)),0)) -> 11.374 | F7: =IF(A7="",0,C7*IFERROR(INDEX('Matérias-Primas'!$G$5:$G$45,MATCH(A7,'Matérias-Primas'!$A$5:$A$45,0)),0)) -> 0 | G7: =IF(A7="",0,C7*IFERROR(INDEX('Matérias-Primas'!$H$5:$H$45,MATCH(A7,'Matérias-Primas'!$A$5:$A$45,0)),0)) -> 0 | H7: =IF(A7="",0,C7*IFERROR(INDEX('Matérias-Primas'!$I$5:$I$45,MATCH(A7,'Matérias-Primas'!$A$5:$A$45,0)),0)) -> 0 | I7: =IF(A7="",0,C7*IFERROR(INDEX('Matérias-Primas'!$J$5:$J$45,MATCH(A7,'Matérias-Primas'!$A$5:$A$45,0)),0)) -> 0 | J7: =IF(A7="",0,C7*IFERROR(INDEX('Matérias-Primas'!$K$5:$K$45,MATCH(A7,'Matérias-Primas'!$A$5:$A$45,0)),0)) -> 0 | K7: =IF(A7="",0,C7*IFERROR(INDEX('Matérias-Primas'!$L$5:$L$45,MATCH(A7,'Matérias-Primas'!$A$5:$A$45,0)),0)) -> 10.626 | L7: =IF(A7="",0,C7*IFERROR(INDEX('Matérias-Primas'!$M$5:$M$45,MATCH(A7,'Matérias-Primas'!$A$5:$A$45,0)),0)) -> 0 | M7: =IF(A7="",0,C7*IFERROR(INDEX('Matérias-Primas'!$N$5:$N$45,MATCH(A7,'Matérias-Primas'!$A$5:$A$45,0)),0)) -> 0 | N7: =IF(A7="",0,C7*IFERROR(INDEX('Matérias-Primas'!$O$5:$O$45,MATCH(A7,'Matérias-Primas'!$A$5:$A$45,0)),0)) -> 0 | O7: =IF(A7="",0,C7*IFERROR(INDEX('Matérias-Primas'!$P$5:$P$45,MATCH(A7,'Matérias-Primas'!$A$5:$A$45,0)),0)) -> 0 | P7: =IF(A7="",0,C7*IFERROR(INDEX('Matérias-Primas'!$Q$5:$Q$45,MATCH(A7,'Matérias-Primas'!$A$5:$A$45,0)),0)) -> 0 | Q7: =IF(A7="",0,C7*IFERROR(INDEX('Matérias-Primas'!$R$5:$R$45,MATCH(A7,'Matérias-Primas'!$A$5:$A$45,0)),0)) -> 0
A8: Carbonato de cálcio | B8: 6 | C8: =IF(B8="","",B8/SUM($B$5:$B$14)) -> 0.06 | D8: =IF(A8="","",IFERROR(INDEX('Matérias-Primas'!$D$5:$D$45,MATCH(A8,'Matérias-Primas'!$A$5:$A$45,0)),0)) -> 2 | E8: =IF(A8="",0,C8*IFERROR(INDEX('Matérias-Primas'!$F$5:$F$45,MATCH(A8,'Matérias-Primas'!$A$5:$A$45,0)),0)) -> 0 | F8: =IF(A8="",0,C8*IFERROR(INDEX('Matérias-Primas'!$G$5:$G$45,MATCH(A8,'Matérias-Primas'!$A$5:$A$45,0)),0)) -> 0 | G8: =IF(A8="",0,C8*IFERROR(INDEX('Matérias-Primas'!$H$5:$H$45,MATCH(A8,'Matérias-Primas'!$A$5:$A$45,0)),0)) -> 0 | H8: =IF(A8="",0,C8*IFERROR(INDEX('Matérias-Primas'!$I$5:$I$45,MATCH(A8,'Matérias-Primas'!$A$5:$A$45,0)),0)) -> 0 | I8: =IF(A8="",0,C8*IFERROR(INDEX('Matérias-Primas'!$J$5:$J$45,MATCH(A8,'Matérias-Primas'!$A$5:$A$45,0)),0)) -> 0 | J8: =IF(A8="",0,C8*IFERROR(INDEX('Matérias-Primas'!$K$5:$K$45,MATCH(A8,'Matérias-Primas'!$A$5:$A$45,0)),0)) -> 0 | K8: =IF(A8="",0,C8*IFERROR(INDEX('Matérias-Primas'!$L$5:$L$45,MATCH(A8,'Matérias-Primas'!$A$5:$A$45,0)),0)) -> 3.36 | L8: =IF(A8="",0,C8*IFERROR(INDEX('Matérias-Primas'!$M$5:$M$45,MATCH(A8,'Matérias-Primas'!$A$5:$A$45,0)),0)) -> 0 | M8: =IF(A8="",0,C8*IFERROR(INDEX('Matérias-Primas'!$N$5:$N$45,MATCH(A8,'Matérias-Primas'!$A$5:$A$45,0)),0)) -> 0 | N8: =IF(A8="",0,C8*IFERROR(INDEX('Matérias-Primas'!$O$5:$O$45,MATCH(A8,'Matérias-Primas'!$A$5:$A$45,0)),0)) -> 0 | O8: =IF(A8="",0,C8*IFERROR(INDEX('Matérias-Primas'!$P$5:$P$45,MATCH(A8,'Matérias-Primas'!$A$5:$A$45,0)),0)) -> 0 | P8: =IF(A8="",0,C8*IFERROR(INDEX('Matérias-Primas'!$Q$5:$Q$45,MATCH(A8,'Matérias-Primas'!$A$5:$A$45,0)),0)) -> 0 | Q8: =IF(A8="",0,C8*IFERROR(INDEX('Matérias-Primas'!$R$5:$R$45,MATCH(A8,'Matérias-Primas'!$A$5:$A$45,0)),0)) -> 0
A9: Caulim | B9: 25 | C9: =IF(B9="","",B9/SUM($B$5:$B$14)) -> 0.25 | D9: =IF(A9="","",IFERROR(INDEX('Matérias-Primas'!$D$5:$D$45,MATCH(A9,'Matérias-Primas'!$A$5:$A$45,0)),0)) -> 2.5 | E9: =IF(A9="",0,C9*IFERROR(INDEX('Matérias-Primas'!$F$5:$F$45,MATCH(A9,'Matérias-Primas'!$A$5:$A$45,0)),0)) -> 11.625 | F9: =IF(A9="",0,C9*IFERROR(INDEX('Matérias-Primas'!$G$5:$G$45,MATCH(A9,'Matérias-Primas'!$A$5:$A$45,0)),0)) -> 9.875 | G9: =IF(A9="",0,C9*IFERROR(INDEX('Matérias-Primas'!$H$5:$H$45,MATCH(A9,'Matérias-Primas'!$A$5:$A$45,0)),0)) -> 0 | H9: =IF(A9="",0,C9*IFERROR(INDEX('Matérias-Primas'!$I$5:$I$45,MATCH(A9,'Matérias-Primas'!$A$5:$A$45,0)),0)) -> 0 | I9: =IF(A9="",0,C9*IFERROR(INDEX('Matérias-Primas'!$J$5:$J$45,MATCH(A9,'Matérias-Primas'!$A$5:$A$45,0)),0)) -> 0 | J9: =IF(A9="",0,C9*IFERROR(INDEX('Matérias-Primas'!$K$5:$K$45,MATCH(A9,'Matérias-Primas'!$A$5:$A$45,0)),0)) -> 0 | K9: =IF(A9="",0,C9*IFERROR(INDEX('Matérias-Primas'!$L$5:$L$45,MATCH(A9,'Matérias-Primas'!$A$5:$A$45,0)),0)) -> 0 | L9: =IF(A9="",0,C9*IFERROR(INDEX('Matérias-Primas'!$M$5:$M$45,MATCH(A9,'Matérias-Primas'!$A$5:$A$45,0)),0)) -> 0 | M9: =IF(A9="",0,C9*IFERROR(INDEX('Matérias-Primas'!$N$5:$N$45,MATCH(A9,'Matérias-Primas'!$A$5:$A$45,0)),0)) -> 0 | N9: =IF(A9="",0,C9*IFERROR(INDEX('Matérias-Primas'!$O$5:$O$45,MATCH(A9,'Matérias-Primas'!$A$5:$A$45,0)),0)) -> 0 | O9: =IF(A9="",0,C9*IFERROR(INDEX('Matérias-Primas'!$P$5:$P$45,MATCH(A9,'Matérias-Primas'!$A$5:$A$45,0)),0)) -> 0 | P9: =IF(A9="",0,C9*IFERROR(INDEX('Matérias-Primas'!$Q$5:$Q$45,MATCH(A9,'Matérias-Primas'!$A$5:$A$45,0)),0)) -> 0.025 | Q9: =IF(A9="",0,C9*IFERROR(INDEX('Matérias-Primas'!$R$5:$R$45,MATCH(A9,'Matérias-Primas'!$A$5:$A$45,0)),0)) -> 0
A10: Quartzo (sílica 325#) | B10: 5 | C10: =IF(B10="","",B10/SUM($B$5:$B$14)) -> 0.05 | D10: =IF(A10="","",IFERROR(INDEX('Matérias-Primas'!$D$5:$D$45,MATCH(A10,'Matérias-Primas'!$A$5:$A$45,0)),0)) -> 2 | E10: =IF(A10="",0,C10*IFERROR(INDEX('Matérias-Primas'!$F$5:$F$45,MATCH(A10,'Matérias-Primas'!$A$5:$A$45,0)),0)) -> 5 | F10: =IF(A10="",0,C10*IFERROR(INDEX('Matérias-Primas'!$G$5:$G$45,MATCH(A10,'Matérias-Primas'!$A$5:$A$45,0)),0)) -> 0 | G10: =IF(A10="",0,C10*IFERROR(INDEX('Matérias-Primas'!$H$5:$H$45,MATCH(A10,'Matérias-Primas'!$A$5:$A$45,0)),0)) -> 0 | H10: =IF(A10="",0,C10*IFERROR(INDEX('Matérias-Primas'!$I$5:$I$45,MATCH(A10,'Matérias-Primas'!$A$5:$A$45,0)),0)) -> 0 | I10: =IF(A10="",0,C10*IFERROR(INDEX('Matérias-Primas'!$J$5:$J$45,MATCH(A10,'Matérias-Primas'!$A$5:$A$45,0)),0)) -> 0 | J10: =IF(A10="",0,C10*IFERROR(INDEX('Matérias-Primas'!$K$5:$K$45,MATCH(A10,'Matérias-Primas'!$A$5:$A$45,0)),0)) -> 0 | K10: =IF(A10="",0,C10*IFERROR(INDEX('Matérias-Primas'!$L$5:$L$45,MATCH(A10,'Matérias-Primas'!$A$5:$A$45,0)),0)) -> 0 | L10: =IF(A10="",0,C10*IFERROR(INDEX('Matérias-Primas'!$M$5:$M$45,MATCH(A10,'Matérias-Primas'!$A$5:$A$45,0)),0)) -> 0 | M10: =IF(A10="",0,C10*IFERROR(INDEX('Matérias-Primas'!$N$5:$N$45,MATCH(A10,'Matérias-Primas'!$A$5:$A$45,0)),0)) -> 0 | N10: =IF(A10="",0,C10*IFERROR(INDEX('Matérias-Primas'!$O$5:$O$45,MATCH(A10,'Matérias-Primas'!$A$5:$A$45,0)),0)) -> 0 | O10: =IF(A10="",0,C10*IFERROR(INDEX('Matérias-Primas'!$P$5:$P$45,MATCH(A10,'Matérias-Primas'!$A$5:$A$45,0)),0)) -> 0 | P10: =IF(A10="",0,C10*IFERROR(INDEX('Matérias-Primas'!$Q$5:$Q$45,MATCH(A10,'Matérias-Primas'!$A$5:$A$45,0)),0)) -> 0 | Q10: =IF(A10="",0,C10*IFERROR(INDEX('Matérias-Primas'!$R$5:$R$45,MATCH(A10,'Matérias-Primas'!$A$5:$A$45,0)),0)) -> 0
C11: =IF(B11="","",B11/SUM($B$5:$B$14)) | D11: =IF(A11="","",IFERROR(INDEX('Matérias-Primas'!$D$5:$D$45,MATCH(A11,'Matérias-Primas'!$A$5:$A$45,0)),0)) | E11: =IF(A11="",0,C11*IFERROR(INDEX('Matérias-Primas'!$F$5:$F$45,MATCH(A11,'Matérias-Primas'!$A$5:$A$45,0)),0)) -> 0 | F11: =IF(A11="",0,C11*IFERROR(INDEX('Matérias-Primas'!$G$5:$G$45,MATCH(A11,'Matérias-Primas'!$A$5:$A$45,0)),0)) -> 0 | G11: =IF(A11="",0,C11*IFERROR(INDEX('Matérias-Primas'!$H$5:$H$45,MATCH(A11,'Matérias-Primas'!$A$5:$A$45,0)),0)) -> 0 | H11: =IF(A11="",0,C11*IFERROR(INDEX('Matérias-Primas'!$I$5:$I$45,MATCH(A11,'Matérias-Primas'!$A$5:$A$45,0)),0)) -> 0 | I11: =IF(A11="",0,C11*IFERROR(INDEX('Matérias-Primas'!$J$5:$J$45,MATCH(A11,'Matérias-Primas'!$A$5:$A$45,0)),0)) -> 0 | J11: =IF(A11="",0,C11*IFERROR(INDEX('Matérias-Primas'!$K$5:$K$45,MATCH(A11,'Matérias-Primas'!$A$5:$A$45,0)),0)) -> 0 | K11: =IF(A11="",0,C11*IFERROR(INDEX('Matérias-Primas'!$L$5:$L$45,MATCH(A11,'Matérias-Primas'!$A$5:$A$45,0)),0)) -> 0 | L11: =IF(A11="",0,C11*IFERROR(INDEX('Matérias-Primas'!$M$5:$M$45,MATCH(A11,'Matérias-Primas'!$A$5:$A$45,0)),0)) -> 0 | M11: =IF(A11="",0,C11*IFERROR(INDEX('Matérias-Primas'!$N$5:$N$45,MATCH(A11,'Matérias-Primas'!$A$5:$A$45,0)),0)) -> 0 | N11: =IF(A11="",0,C11*IFERROR(INDEX('Matérias-Primas'!$O$5:$O$45,MATCH(A11,'Matérias-Primas'!$A$5:$A$45,0)),0)) -> 0 | O11: =IF(A11="",0,C11*IFERROR(INDEX('Matérias-Primas'!$P$5:$P$45,MATCH(A11,'Matérias-Primas'!$A$5:$A$45,0)),0)) -> 0 | P11: =IF(A11="",0,C11*IFERROR(INDEX('Matérias-Primas'!$Q$5:$Q$45,MATCH(A11,'Matérias-Primas'!$A$5:$A$45,0)),0)) -> 0 | Q11: =IF(A11="",0,C11*IFERROR(INDEX('Matérias-Primas'!$R$5:$R$45,MATCH(A11,'Matérias-Primas'!$A$5:$A$45,0)),0)) -> 0
C12: =IF(B12="","",B12/SUM($B$5:$B$14)) | D12: =IF(A12="","",IFERROR(INDEX('Matérias-Primas'!$D$5:$D$45,MATCH(A12,'Matérias-Primas'!$A$5:$A$45,0)),0)) | E12: =IF(A12="",0,C12*IFERROR(INDEX('Matérias-Primas'!$F$5:$F$45,MATCH(A12,'Matérias-Primas'!$A$5:$A$45,0)),0)) -> 0 | F12: =IF(A12="",0,C12*IFERROR(INDEX('Matérias-Primas'!$G$5:$G$45,MATCH(A12,'Matérias-Primas'!$A$5:$A$45,0)),0)) -> 0 | G12: =IF(A12="",0,C12*IFERROR(INDEX('Matérias-Primas'!$H$5:$H$45,MATCH(A12,'Matérias-Primas'!$A$5:$A$45,0)),0)) -> 0 | H12: =IF(A12="",0,C12*IFERROR(INDEX('Matérias-Primas'!$I$5:$I$45,MATCH(A12,'Matérias-Primas'!$A$5:$A$45,0)),0)) -> 0 | I12: =IF(A12="",0,C12*IFERROR(INDEX('Matérias-Primas'!$J$5:$J$45,MATCH(A12,'Matérias-Primas'!$A$5:$A$45,0)),0)) -> 0 | J12: =IF(A12="",0,C12*IFERROR(INDEX('Matérias-Primas'!$K$5:$K$45,MATCH(A12,'Matérias-Primas'!$A$5:$A$45,0)),0)) -> 0 | K12: =IF(A12="",0,C12*IFERROR(INDEX('Matérias-Primas'!$L$5:$L$45,MATCH(A12,'Matérias-Primas'!$A$5:$A$45,0)),0)) -> 0 | L12: =IF(A12="",0,C12*IFERROR(INDEX('Matérias-Primas'!$M$5:$M$45,MATCH(A12,'Matérias-Primas'!$A$5:$A$45,0)),0)) -> 0 | M12: =IF(A12="",0,C12*IFERROR(INDEX('Matérias-Primas'!$N$5:$N$45,MATCH(A12,'Matérias-Primas'!$A$5:$A$45,0)),0)) -> 0 | N12: =IF(A12="",0,C12*IFERROR(INDEX('Matérias-Primas'!$O$5:$O$45,MATCH(A12,'Matérias-Primas'!$A$5:$A$45,0)),0)) -> 0 | O12: =IF(A12="",0,C12*IFERROR(INDEX('Matérias-Primas'!$P$5:$P$45,MATCH(A12,'Matérias-Primas'!$A$5:$A$45,0)),0)) -> 0 | P12: =IF(A12="",0,C12*IFERROR(INDEX('Matérias-Primas'!$Q$5:$Q$45,MATCH(A12,'Matérias-Primas'!$A$5:$A$45,0)),0)) -> 0 | Q12: =IF(A12="",0,C12*IFERROR(INDEX('Matérias-Primas'!$R$5:$R$45,MATCH(A12,'Matérias-Primas'!$A$5:$A$45,0)),0)) -> 0
C13: =IF(B13="","",B13/SUM($B$5:$B$14)) | D13: =IF(A13="","",IFERROR(INDEX('Matérias-Primas'!$D$5:$D$45,MATCH(A13,'Matérias-Primas'!$A$5:$A$45,0)),0)) | E13: =IF(A13="",0,C13*IFERROR(INDEX('Matérias-Primas'!$F$5:$F$45,MATCH(A13,'Matérias-Primas'!$A$5:$A$45,0)),0)) -> 0 | F13: =IF(A13="",0,C13*IFERROR(INDEX('Matérias-Primas'!$G$5:$G$45,MATCH(A13,'Matérias-Primas'!$A$5:$A$45,0)),0)) -> 0 | G13: =IF(A13="",0,C13*IFERROR(INDEX('Matérias-Primas'!$H$5:$H$45,MATCH(A13,'Matérias-Primas'!$A$5:$A$45,0)),0)) -> 0 | H13: =IF(A13="",0,C13*IFERROR(INDEX('Matérias-Primas'!$I$5:$I$45,MATCH(A13,'Matérias-Primas'!$A$5:$A$45,0)),0)) -> 0 | I13: =IF(A13="",0,C13*IFERROR(INDEX('Matérias-Primas'!$J$5:$J$45,MATCH(A13,'Matérias-Primas'!$A$5:$A$45,0)),0)) -> 0 | J13: =IF(A13="",0,C13*IFERROR(INDEX('Matérias-Primas'!$K$5:$K$45,MATCH(A13,'Matérias-Primas'!$A$5:$A$45,0)),0)) -> 0 | K13: =IF(A13="",0,C13*IFERROR(INDEX('Matérias-Primas'!$L$5:$L$45,MATCH(A13,'Matérias-Primas'!$A$5:$A$45,0)),0)) -> 0 | L13: =IF(A13="",0,C13*IFERROR(INDEX('Matérias-Primas'!$M$5:$M$45,MATCH(A13,'Matérias-Primas'!$A$5:$A$45,0)),0)) -> 0 | M13: =IF(A13="",0,C13*IFERROR(INDEX('Matérias-Primas'!$N$5:$N$45,MATCH(A13,'Matérias-Primas'!$A$5:$A$45,0)),0)) -> 0 | N13: =IF(A13="",0,C13*IFERROR(INDEX('Matérias-Primas'!$O$5:$O$45,MATCH(A13,'Matérias-Primas'!$A$5:$A$45,0)),0)) -> 0 | O13: =IF(A13="",0,C13*IFERROR(INDEX('Matérias-Primas'!$P$5:$P$45,MATCH(A13,'Matérias-Primas'!$A$5:$A$45,0)),0)) -> 0 | P13: =IF(A13="",0,C13*IFERROR(INDEX('Matérias-Primas'!$Q$5:$Q$45,MATCH(A13,'Matérias-Primas'!$A$5:$A$45,0)),0)) -> 0 | Q13: =IF(A13="",0,C13*IFERROR(INDEX('Matérias-Primas'!$R$5:$R$45,MATCH(A13,'Matérias-Primas'!$A$5:$A$45,0)),0)) -> 0
C14: =IF(B14="","",B14/SUM($B$5:$B$14)) | D14: =IF(A14="","",IFERROR(INDEX('Matérias-Primas'!$D$5:$D$45,MATCH(A14,'Matérias-Primas'!$A$5:$A$45,0)),0)) | E14: =IF(A14="",0,C14*IFERROR(INDEX('Matérias-Primas'!$F$5:$F$45,MATCH(A14,'Matérias-Primas'!$A$5:$A$45,0)),0)) -> 0 | F14: =IF(A14="",0,C14*IFERROR(INDEX('Matérias-Primas'!$G$5:$G$45,MATCH(A14,'Matérias-Primas'!$A$5:$A$45,0)),0)) -> 0 | G14: =IF(A14="",0,C14*IFERROR(INDEX('Matérias-Primas'!$H$5:$H$45,MATCH(A14,'Matérias-Primas'!$A$5:$A$45,0)),0)) -> 0 | H14: =IF(A14="",0,C14*IFERROR(INDEX('Matérias-Primas'!$I$5:$I$45,MATCH(A14,'Matérias-Primas'!$A$5:$A$45,0)),0)) -> 0 | I14: =IF(A14="",0,C14*IFERROR(INDEX('Matérias-Primas'!$J$5:$J$45,MATCH(A14,'Matérias-Primas'!$A$5:$A$45,0)),0)) -> 0 | J14: =IF(A14="",0,C14*IFERROR(INDEX('Matérias-Primas'!$K$5:$K$45,MATCH(A14,'Matérias-Primas'!$A$5:$A$45,0)),0)) -> 0 | K14: =IF(A14="",0,C14*IFERROR(INDEX('Matérias-Primas'!$L$5:$L$45,MATCH(A14,'Matérias-Primas'!$A$5:$A$45,0)),0)) -> 0 | L14: =IF(A14="",0,C14*IFERROR(INDEX('Matérias-Primas'!$M$5:$M$45,MATCH(A14,'Matérias-Primas'!$A$5:$A$45,0)),0)) -> 0 | M14: =IF(A14="",0,C14*IFERROR(INDEX('Matérias-Primas'!$N$5:$N$45,MATCH(A14,'Matérias-Primas'!$A$5:$A$45,0)),0)) -> 0 | N14: =IF(A14="",0,C14*IFERROR(INDEX('Matérias-Primas'!$O$5:$O$45,MATCH(A14,'Matérias-Primas'!$A$5:$A$45,0)),0)) -> 0 | O14: =IF(A14="",0,C14*IFERROR(INDEX('Matérias-Primas'!$P$5:$P$45,MATCH(A14,'Matérias-Primas'!$A$5:$A$45,0)),0)) -> 0 | P14: =IF(A14="",0,C14*IFERROR(INDEX('Matérias-Primas'!$Q$5:$Q$45,MATCH(A14,'Matérias-Primas'!$A$5:$A$45,0)),0)) -> 0 | Q14: =IF(A14="",0,C14*IFERROR(INDEX('Matérias-Primas'!$R$5:$R$45,MATCH(A14,'Matérias-Primas'!$A$5:$A$45,0)),0)) -> 0
A15: Total | B15: =SUM(B5:B14) -> 100 | C15: =SUM(C5:C14) -> 1 | E15: =SUM(E5:E14) -> 53.679 | F15: =SUM(F5:F14) -> 15.425 | G15: =SUM(G5:G14) -> 2.772 | H15: =SUM(H5:H14) -> 2.136 | I15: =SUM(I5:I14) -> 3.3 | J15: =SUM(J5:J14) -> 0 | K15: =SUM(K5:K14) -> 16.458 | L15: =SUM(L5:L14) -> 0 | ... Q15: =SUM(Q5:Q14) -> 0
A16: Massa molar | E16: ='Matérias-Primas'!F3 -> 60.08 | F16: ='Matérias-Primas'!G3 -> 101.96 | G16: ='Matérias-Primas'!H3 -> 69.62 | H16: ='Matérias-Primas'!I3 -> 61.98 | I16: ='Matérias-Primas'!J3 -> 94.2 | J16: ='Matérias-Primas'!K3 -> 29.88 | K16: ='Matérias-Primas'!L3 -> 56.08 | L16: ='Matérias-Primas'!M3 -> 40.3 | ... Q16: ='Matérias-Primas'!R3 -> 79.87
A17: Mols | C17: Soma fundentes: | D17: =H17+I17+J17+K17+L17+M17+N17 -> 0.36296819 | E17: =E15/E16 -> 0.89345872 | F17: =F15/F16 -> 0.15128482 | G17: =G15/G16 -> 0.039816145 | H17: =H15/H16 -> 0.03446273 | I17: =I15/I16 -> 0.035031847 | J17: =J15/J16 -> 0 | K17: =K15/K16 -> 0.29347361 | L17: =L15/L16 -> 0 | ... Q17: =Q15/Q16 -> 0
A18: UMF (fundentes = 1) | E18: =IF($D$17=0,0,E17/$D$17) -> 2.4615345 | F18: =IF($D$17=0,0,F17/$D$17) -> 0.41679911 | G18: =IF($D$17=0,0,G17/$D$17) -> 0.10969596 | H18: =IF($D$17=0,0,H17/$D$17) -> 0.094946971 | I18: =IF($D$17=0,0,I17/$D$17) -> 0.096514925 | J18: =IF($D$17=0,0,J17/$D$17) -> 0 | K18: =IF($D$17=0,0,K17/$D$17) -> 0.8085381 | L18: =IF($D$17=0,0,L17/$D$17) -> 0 | ... Q18: =IF($D$17=0,0,Q17/$D$17) -> 0
A20: Checagem contra faixas-alvo
A21: Indicador | B21: Valor | C21: Mín | D21: Máx | E21: Status
A22: SiO₂ (UMF) | B22: =E18 -> 2.4615345 | C22: 2 | D22: 3 | E22: =IF(AND(B22>=C22,B22<=D22),"OK","Ajustar") -> OK
A23: Al₂O₃ (UMF) | B23: =F18 -> 0.41679911 | C23: 0.35 | D23: 0.5 | E23: =IF(AND(B23>=C23,B23<=D23),"OK","Ajustar") -> OK
A24: B₂O₃ (UMF) | B24: =G18 -> 0.10969596 | C24: 0.1 | D24: 0.25 | E24: =IF(AND(B24>=C24,B24<=D24),"OK","Ajustar") -> OK
A25: Razão SiO₂:Al₂O₃ | B25: =IF(F18=0,0,E18/F18) -> 5.9058056 | C25: 5 | D25: 7 | E25: =IF(AND(B25>=C25,B25<=D25),"OK","Ajustar") -> OK
A27: Custo matéria-prima da base (R$/kg) | B27: =SUMPRODUCT(C5:C14,D5:D14) -> 5.455
A28: Faixas-alvo são referências de literatura para cone 6 estável; ajuste-as conforme seus testes. Fórmula-alvo calculada sobre óxidos; colorantes entram na aba Cores.

Sheet Base C
A1: Base C — Brilhante de estrôncio (para branco opaco e turquesa)
A2: Estrôncio no lugar de bário: favorece turquesa com cobre.
E3: Contribuição em massa de cada óxido (g por 100 g de esmalte queimado não normalizado) →
A4: Material | B4: Quantidade (g) | C4: % normalizado | D4: Preço (R$/kg) | E4: SiO2 | F4: Al2O3 | G4: B2O3 | H4: Na2O | I4: K2O | J4: Li2O | K4: CaO | L4: MgO | M4: SrO | N4: ZnO | O4: ZrO2 | P4: Fe2O3 | Q4: TiO2
A5: Feldspato potássico | B5: 25 | C5: =IF(B5="","",B5/SUM($B$5:$B$14)) -> 0.25 | D5: =IF(A5="","",IFERROR(INDEX('Matérias-Primas'!$D$5:$D$45,MATCH(A5,'Matérias-Primas'!$A$5:$A$45,0)),0)) -> 3.5 | E5: =IF(A5="",0,C5*IFERROR(INDEX('Matérias-Primas'!$F$5:$F$45,MATCH(A5,'Matérias-Primas'!$A$5:$A$45,0)),0)) -> 16.75 | F5: =IF(A5="",0,C5*IFERROR(INDEX('Matérias-Primas'!$G$5:$G$45,MATCH(A5,'Matérias-Primas'!$A$5:$A$45,0)),0)) -> 4.625 | G5: =IF(A5="",0,C5*IFERROR(INDEX('Matérias-Primas'!$H$5:$H$45,MATCH(A5,'Matérias-Primas'!$A$5:$A$45,0)),0)) -> 0 | H5: =IF(A5="",0,C5*IFERROR(INDEX('Matérias-Primas'!$I$5:$I$45,MATCH(A5,'Matérias-Primas'!$A$5:$A$45,0)),0)) -> 0.75 | I5: =IF(A5="",0,C5*IFERROR(INDEX('Matérias-Primas'!$J$5:$J$45,MATCH(A5,'Matérias-Primas'!$A$5:$A$45,0)),0)) -> 2.75 | J5: =IF(A5="",0,C5*IFERROR(INDEX('Matérias-Primas'!$K$5:$K$45,MATCH(A5,'Matérias-Primas'!$A$5:$A$45,0)),0)) -> 0 | K5: =IF(A5="",0,C5*IFERROR(INDEX('Matérias-Primas'!$L$5:$L$45,MATCH(A5,'Matérias-Primas'!$A$5:$A$45,0)),0)) -> 0.05 | L5: =IF(A5="",0,C5*IFERROR(INDEX('Matérias-Primas'!$M$5:$M$45,MATCH(A5,'Matérias-Primas'!$A$5:$A$45,0)),0)) -> 0 | M5: =IF(A5="",0,C5*IFERROR(INDEX('Matérias-Primas'!$N$5:$N$45,MATCH(A5,'Matérias-Primas'!$A$5:$A$45,0)),0)) -> 0 | N5: =IF(A5="",0,C5*IFERROR(INDEX('Matérias-Primas'!$O$5:$O$45,MATCH(A5,'Matérias-Primas'!$A$5:$A$45,0)),0)) -> 0 | O5: =IF(A5="",0,C5*IFERROR(INDEX('Matérias-Primas'!$P$5:$P$45,MATCH(A5,'Matérias-Primas'!$A$5:$A$45,0)),0)) -> 0 | P5: =IF(A5="",0,C5*IFERROR(INDEX('Matérias-Primas'!$Q$5:$Q$45,MATCH(A5,'Matérias-Primas'!$A$5:$A$45,0)),0)) -> 0.025 | Q5: =IF(A5="",0,C5*IFERROR(INDEX('Matérias-Primas'!$R$5:$R$45,MATCH(A5,'Matérias-Primas'!$A$5:$A$45,0)),0)) -> 0
A6: Frita borácica | B6: 18 | C6: =IF(B6="","",B6/SUM($B$5:$B$14)) -> 0.18 | D6: =IF(A6="","",IFERROR(INDEX('Matérias-Primas'!$D$5:$D$45,MATCH(A6,'Matérias-Primas'!$A$5:$A$45,0)),0)) -> 15 | E6: =IF(A6="",0,C6*IFERROR(INDEX('Matérias-Primas'!$F$5:$F$45,MATCH(A6,'Matérias-Primas'!$A$5:$A$45,0)),0)) -> 8.37 | F6: =IF(A6="",0,C6*IFERROR(INDEX('Matérias-Primas'!$G$5:$G$45,MATCH(A6,'Matérias-Primas'!$A$5:$A$45,0)),0)) -> 0 | G6: =IF(A6="",0,C6*IFERROR(INDEX('Matérias-Primas'!$H$5:$H$45,MATCH(A6,'Matérias-Primas'!$A$5:$A$45,0)),0)) -> 4.158 | H6: =IF(A6="",0,C6*IFERROR(INDEX('Matérias-Primas'!$I$5:$I$45,MATCH(A6,'Matérias-Primas'!$A$5:$A$45,0)),0)) -> 1.854 | I6: =IF(A6="",0,C6*IFERROR(INDEX('Matérias-Primas'!$J$5:$J$45,MATCH(A6,'Matérias-Primas'!$A$5:$A$45,0)),0)) -> 0 | J6: =IF(A6="",0,C6*IFERROR(INDEX('Matérias-Primas'!$K$5:$K$45,MATCH(A6,'Matérias-Primas'!$A$5:$A$45,0)),0)) -> 0 | K6: =IF(A6="",0,C6*IFERROR(INDEX('Matérias-Primas'!$L$5:$L$45,MATCH(A6,'Matérias-Primas'!$A$5:$A$45,0)),0)) -> 3.618 | L6: =IF(A6="",0,C6*IFERROR(INDEX('Matérias-Primas'!$M$5:$M$45,MATCH(A6,'Matérias-Primas'!$A$5:$A$45,0)),0)) -> 0 | M6: =IF(A6="",0,C6*IFERROR(INDEX('Matérias-Primas'!$N$5:$N$45,MATCH(A6,'Matérias-Primas'!$A$5:$A$45,0)),0)) -> 0 | N6: =IF(A6="",0,C6*IFERROR(INDEX('Matérias-Primas'!$O$5:$O$45,MATCH(A6,'Matérias-Primas'!$A$5:$A$45,0)),0)) -> 0 | O6: =IF(A6="",0,C6*IFERROR(INDEX('Matérias-Primas'!$P$5:$P$45,MATCH(A6,'Matérias-Primas'!$A$5:$A$45,0)),0)) -> 0 | P6: =IF(A6="",0,C6*IFERROR(INDEX('Matérias-Primas'!$Q$5:$Q$45,MATCH(A6,'Matérias-Primas'!$A$5:$A$45,0)),0)) -> 0 | Q6: =IF(A6="",0,C6*IFERROR(INDEX('Matérias-Primas'!$R$5:$R$45,MATCH(A6,'Matérias-Primas'!$A$5:$A$45,0)),0)) -> 0
A7: Carbonato de estrôncio | B7: 10 | C7: =IF(B7="","",B7/SUM($B$5:$B$14)) -> 0.1 | D7: =IF(A7="","",IFERROR(INDEX('Matérias-Primas'!$D$5:$D$45,MATCH(A7,'Matérias-Primas'!$A$5:$A$45,0)),0)) -> 35 | E7: =IF(A7="",0,C7*IFERROR(INDEX('Matérias-Primas'!$F$5:$F$45,MATCH(A7,'Matérias-Primas'!$A$5:$A$45,0)),0)) -> 0 | F7: =IF(A7="",0,C7*IFERROR(INDEX('Matérias-Primas'!$G$5:$G$45,MATCH(A7,'Matérias-Primas'!$A$5:$A$45,0)),0)) -> 0 | G7: =IF(A7="",0,C7*IFERROR(INDEX('Matérias-Primas'!$H$5:$H$45,MATCH(A7,'Matérias-Primas'!$A$5:$A$45,0)),0)) -> 0 | H7: =IF(A7="",0,C7*IFERROR(INDEX('Matérias-Primas'!$I$5:$I$45,MATCH(A7,'Matérias-Primas'!$A$5:$A$45,0)),0)) -> 0 | I7: =IF(A7="",0,C7*IFERROR(INDEX('Matérias-Primas'!$J$5:$J$45,MATCH(A7,'Matérias-Primas'!$A$5:$A$45,0)),0)) -> 0 | J7: =IF(A7="",0,C7*IFERROR(INDEX('Matérias-Primas'!$K$5:$K$45,MATCH(A7,'Matérias-Primas'!$A$5:$A$45,0)),0)) -> 0 | K7: =IF(A7="",0,C7*IFERROR(INDEX('Matérias-Primas'!$L$5:$L$45,MATCH(A7,'Matérias-Primas'!$A$5:$A$45,0)),0)) -> 0 | L7: =IF(A7="",0,C7*IFERROR(INDEX('Matérias-Primas'!$M$5:$M$45,MATCH(A7,'Matérias-Primas'!$A$5:$A$45,0)),0)) -> 0 | M7: =IF(A7="",0,C7*IFERROR(INDEX('Matérias-Primas'!$N$5:$N$45,MATCH(A7,'Matérias-Primas'!$A$5:$A$45,0)),0)) -> 7.02 | N7: =IF(A7="",0,C7*IFERROR(INDEX('Matérias-Primas'!$O$5:$O$45,MATCH(A7,'Matérias-Primas'!$A$5:$A$45,0)),0)) -> 0 | O7: =IF(A7="",0,C7*IFERROR(INDEX('Matérias-Primas'!$P$5:$P$45,MATCH(A7,'Matérias-Primas'!$A$5:$A$45,0)),0)) -> 0 | P7: =IF(A7="",0,C7*IFERROR(INDEX('Matérias-Primas'!$Q$5:$Q$45,MATCH(A7,'Matérias-Primas'!$A$5:$A$45,0)),0)) -> 0 | Q7: =IF(A7="",0,C7*IFERROR(INDEX('Matérias-Primas'!$R$5:$R$45,MATCH(A7,'Matérias-Primas'!$A$5:$A$45,0)),0)) -> 0
A8: Wollastonita | B8: 10 | C8: =IF(B8="","",B8/SUM($B$5:$B$14)) -> 0.1 | D8: =IF(A8="","",IFERROR(INDEX('Matérias-Primas'!$D$5:$D$45,MATCH(A8,'Matérias-Primas'!$A$5:$A$45,0)),0)) -> 8 | E8: =IF(A8="",0,C8*IFERROR(INDEX('Matérias-Primas'!$F$5:$F$45,MATCH(A8,'Matérias-Primas'!$A$5:$A$45,0)),0)) -> 5.17 | F8: =IF(A8="",0,C8*IFERROR(INDEX('Matérias-Primas'!$G$5:$G$45,MATCH(A8,'Matérias-Primas'!$A$5:$A$45,0)),0)) -> 0 | G8: =IF(A8="",0,C8*IFERROR(INDEX('Matérias-Primas'!$H$5:$H$45,MATCH(A8,'Matérias-Primas'!$A$5:$A$45,0)),0)) -> 0 | H8: =IF(A8="",0,C8*IFERROR(INDEX('Matérias-Primas'!$I$5:$I$45,MATCH(A8,'Matérias-Primas'!$A$5:$A$45,0)),0)) -> 0 | I8: =IF(A8="",0,C8*IFERROR(INDEX('Matérias-Primas'!$J$5:$J$45,MATCH(A8,'Matérias-Primas'!$A$5:$A$45,0)),0)) -> 0 | J8: =IF(A8="",0,C8*IFERROR(INDEX('Matérias-Primas'!$K$5:$K$45,MATCH(A8,'Matérias-Primas'!$A$5:$A$45,0)),0)) -> 0 | K8: =IF(A8="",0,C8*IFERROR(INDEX('Matérias-Primas'!$L$5:$L$45,MATCH(A8,'Matérias-Primas'!$A$5:$A$45,0)),0)) -> 4.83 | L8: =IF(A8="",0,C8*IFERROR(INDEX('Matérias-Primas'!$M$5:$M$45,MATCH(A8,'Matérias-Primas'!$A$5:$A$45,0)),0)) -> 0 | M8: =IF(A8="",0,C8*IFERROR(INDEX('Matérias-Primas'!$N$5:$N$45,MATCH(A8,'Matérias-Primas'!$A$5:$A$45,0)),0)) -> 0 | N8: =IF(A8="",0,C8*IFERROR(INDEX('Matérias-Primas'!$O$5:$O$45,MATCH(A8,'Matérias-Primas'!$A$5:$A$45,0)),0)) -> 0 | O8: =IF(A8="",0,C8*IFERROR(INDEX('Matérias-Primas'!$P$5:$P$45,MATCH(A8,'Matérias-Primas'!$A$5:$A$45,0)),0)) -> 0 | P8: =IF(A8="",0,C8*IFERROR(INDEX('Matérias-Primas'!$Q$5:$Q$45,MATCH(A8,'Matérias-Primas'!$A$5:$A$45,0)),0)) -> 0 | Q8: =IF(A8="",0,C8*IFERROR(INDEX('Matérias-Primas'!$R$5:$R$45,MATCH(A8,'Matérias-Primas'!$A$5:$A$45,0)),0)) -> 0
A9: Caulim | B9: 15 | C9: =IF(B9="","",B9/SUM($B$5:$B$14)) -> 0.15 | D9: =IF(A9="","",IFERROR(INDEX('Matérias-Primas'!$D$5:$D$45,MATCH(A9,'Matérias-Primas'!$A$5:$A$45,0)),0)) -> 2.5 | E9: =IF(A9="",0,C9*IFERROR(INDEX('Matérias-Primas'!$F$5:$F$45,MATCH(A9,'Matérias-Primas'!$A$5:$A$45,0)),0)) -> 6.975 | F9: =IF(A9="",0,C9*IFERROR(INDEX('Matérias-Primas'!$G$5:$G$45,MATCH(A9,'Matérias-Primas'!$A$5:$A$45,0)),0)) -> 5.925 | G9: =IF(A9="",0,C9*IFERROR(INDEX('Matérias-Primas'!$H$5:$H$45,MATCH(A9,'Matérias-Primas'!$A$5:$A$45,0)),0)) -> 0 | H9: =IF(A9="",0,C9*IFERROR(INDEX('Matérias-Primas'!$I$5:$I$45,MATCH(A9,'Matérias-Primas'!$A$5:$A$45,0)),0)) -> 0 | I9: =IF(A9="",0,C9*IFERROR(INDEX('Matérias-Primas'!$J$5:$J$45,MATCH(A9,'Matérias-Primas'!$A$5:$A$45,0)),0)) -> 0 | J9: =IF(A9="",0,C9*IFERROR(INDEX('Matérias-Primas'!$K$5:$K$45,MATCH(A9,'Matérias-Primas'!$A$5:$A$45,0)),0)) -> 0 | K9: =IF(A9="",0,C9*IFERROR(INDEX('Matérias-Primas'!$L$5:$L$45,MATCH(A9,'Matérias-Primas'!$A$5:$A$45,0)),0)) -> 0 | L9: =IF(A9="",0,C9*IFERROR(INDEX('Matérias-Primas'!$M$5:$M$45,MATCH(A9,'Matérias-Primas'!$A$5:$A$45,0)),0)) -> 0 | M9: =IF(A9="",0,C9*IFERROR(INDEX('Matérias-Primas'!$N$5:$N$45,MATCH(A9,'Matérias-Primas'!$A$5:$A$45,0)),0)) -> 0 | N9: =IF(A9="",0,C9*IFERROR(INDEX('Matérias-Primas'!$O$5:$O$45,MATCH(A9,'Matérias-Primas'!$A$5:$A$45,0)),0)) -> 0 | O9: =IF(A9="",0,C9*IFERROR(INDEX('Matérias-Primas'!$P$5:$P$45,MATCH(A9,'Matérias-Primas'!$A$5:$A$45,0)),0)) -> 0 | P9: =IF(A9="",0,C9*IFERROR(INDEX('Matérias-Primas'!$Q$5:$Q$45,MATCH(A9,'Matérias-Primas'!$A$5:$A$45,0)),0)) -> 0.015 | Q9: =IF(A9="",0,C9*IFERROR(INDEX('Matérias-Primas'!$R$5:$R$45,MATCH(A9,'Matérias-Primas'!$A$5:$A$45,0)),0)) -> 0
A10: Quartzo (sílica 325#) | B10: 22 | C10: =IF(B10="","",B10/SUM($B$5:$B$14)) -> 0.22 | D10: =IF(A10="","",IFERROR(INDEX('Matérias-Primas'!$D$5:$D$45,MATCH(A10,'Matérias-Primas'!$A$5:$A$45,0)),0)) -> 2 | E10: =IF(A10="",0,C10*IFERROR(INDEX('Matérias-Primas'!$F$5:$F$45,MATCH(A10,'Matérias-Primas'!$A$5:$A$45,0)),0)) -> 22 | F10: =IF(A10="",0,C10*IFERROR(INDEX('Matérias-Primas'!$G$5:$G$45,MATCH(A10,'Matérias-Primas'!$A$5:$A$45,0)),0)) -> 0 | G10: =IF(A10="",0,C10*IFERROR(INDEX('Matérias-Primas'!$H$5:$H$45,MATCH(A10,'Matérias-Primas'!$A$5:$A$45,0)),0)) -> 0 | H10: =IF(A10="",0,C10*IFERROR(INDEX('Matérias-Primas'!$I$5:$I$45,MATCH(A10,'Matérias-Primas'!$A$5:$A$45,0)),0)) -> 0 | I10: =IF(A10="",0,C10*IFERROR(INDEX('Matérias-Primas'!$J$5:$J$45,MATCH(A10,'Matérias-Primas'!$A$5:$A$45,0)),0)) -> 0 | J10: =IF(A10="",0,C10*IFERROR(INDEX('Matérias-Primas'!$K$5:$K$45,MATCH(A10,'Matérias-Primas'!$A$5:$A$45,0)),0)) -> 0 | K10: =IF(A10="",0,C10*IFERROR(INDEX('Matérias-Primas'!$L$5:$L$45,MATCH(A10,'Matérias-Primas'!$A$5:$A$45,0)),0)) -> 0 | L10: =IF(A10="",0,C10*IFERROR(INDEX('Matérias-Primas'!$M$5:$M$45,MATCH(A10,'Matérias-Primas'!$A$5:$A$45,0)),0)) -> 0 | M10: =IF(A10="",0,C10*IFERROR(INDEX('Matérias-Primas'!$N$5:$N$45,MATCH(A10,'Matérias-Primas'!$A$5:$A$45,0)),0)) -> 0 | N10: =IF(A10="",0,C10*IFERROR(INDEX('Matérias-Primas'!$O$5:$O$45,MATCH(A10,'Matérias-Primas'!$A$5:$A$45,0)),0)) -> 0 | O10: =IF(A10="",0,C10*IFERROR(INDEX('Matérias-Primas'!$P$5:$P$45,MATCH(A10,'Matérias-Primas'!$A$5:$A$45,0)),0)) -> 0 | P10: =IF(A10="",0,C10*IFERROR(INDEX('Matérias-Primas'!$Q$5:$Q$45,MATCH(A10,'Matérias-Primas'!$A$5:$A$45,0)),0)) -> 0 | Q10: =IF(A10="",0,C10*IFERROR(INDEX('Matérias-Primas'!$R$5:$R$45,MATCH(A10,'Matérias-Primas'!$A$5:$A$45,0)),0)) -> 0
C11: =IF(B11="","",B11/SUM($B$5:$B$14)) | D11: =IF(A11="","",IFERROR(INDEX('Matérias-Primas'!$D$5:$D$45,MATCH(A11,'Matérias-Primas'!$A$5:$A$45,0)),0)) | E11: =IF(A11="",0,C11*IFERROR(INDEX('Matérias-Primas'!$F$5:$F$45,MATCH(A11,'Matérias-Primas'!$A$5:$A$45,0)),0)) -> 0 | F11: =IF(A11="",0,C11*IFERROR(INDEX('Matérias-Primas'!$G$5:$G$45,MATCH(A11,'Matérias-Primas'!$A$5:$A$45,0)),0)) -> 0 | G11: =IF(A11="",0,C11*IFERROR(INDEX('Matérias-Primas'!$H$5:$H$45,MATCH(A11,'Matérias-Primas'!$A$5:$A$45,0)),0)) -> 0 | H11: =IF(A11="",0,C11*IFERROR(INDEX('Matérias-Primas'!$I$5:$I$45,MATCH(A11,'Matérias-Primas'!$A$5:$A$45,0)),0)) -> 0 | I11: =IF(A11="",0,C11*IFERROR(INDEX('Matérias-Primas'!$J$5:$J$45,MATCH(A11,'Matérias-Primas'!$A$5:$A$45,0)),0)) -> 0 | J11: =IF(A11="",0,C11*IFERROR(INDEX('Matérias-Primas'!$K$5:$K$45,MATCH(A11,'Matérias-Primas'!$A$5:$A$45,0)),0)) -> 0 | K11: =IF(A11="",0,C11*IFERROR(INDEX('Matérias-Primas'!$L$5:$L$45,MATCH(A11,'Matérias-Primas'!$A$5:$A$45,0)),0)) -> 0 | L11: =IF(A11="",0,C11*IFERROR(INDEX('Matérias-Primas'!$M$5:$M$45,MATCH(A11,'Matérias-Primas'!$A$5:$A$45,0)),0)) -> 0 | M11: =IF(A11="",0,C11*IFERROR(INDEX('Matérias-Primas'!$N$5:$N$45,MATCH(A11,'Matérias-Primas'!$A$5:$A$45,0)),0)) -> 0 | N11: =IF(A11="",0,C11*IFERROR(INDEX('Matérias-Primas'!$O$5:$O$45,MATCH(A11,'Matérias-Primas'!$A$5:$A$45,0)),0)) -> 0 | O11: =IF(A11="",0,C11*IFERROR(INDEX('Matérias-Primas'!$P$5:$P$45,MATCH(A11,'Matérias-Primas'!$A$5:$A$45,0)),0)) -> 0 | P11: =IF(A11="",0,C11*IFERROR(INDEX('Matérias-Primas'!$Q$5:$Q$45,MATCH(A11,'Matérias-Primas'!$A$5:$A$45,0)),0)) -> 0 | Q11: =IF(A11="",0,C11*IFERROR(INDEX('Matérias-Primas'!$R$5:$R$45,MATCH(A11,'Matérias-Primas'!$A$5:$A$45,0)),0)) -> 0
C12: =IF(B12="","",B12/SUM($B$5:$B$14)) | D12: =IF(A12="","",IFERROR(INDEX('Matérias-Primas'!$D$5:$D$45,MATCH(A12,'Matérias-Primas'!$A$5:$A$45,0)),0)) | E12: =IF(A12="",0,C12*IFERROR(INDEX('Matérias-Primas'!$F$5:$F$45,MATCH(A12,'Matérias-Primas'!$A$5:$A$45,0)),0)) -> 0 | F12: =IF(A12="",0,C12*IFERROR(INDEX('Matérias-Primas'!$G$5:$G$45,MATCH(A12,'Matérias-Primas'!$A$5:$A$45,0)),0)) -> 0 | G12: =IF(A12="",0,C12*IFERROR(INDEX('Matérias-Primas'!$H$5:$H$45,MATCH(A12,'Matérias-Primas'!$A$5:$A$45,0)),0)) -> 0 | H12: =IF(A12="",0,C12*IFERROR(INDEX('Matérias-Primas'!$I$5:$I$45,MATCH(A12,'Matérias-Primas'!$A$5:$A$45,0)),0)) -> 0 | I12: =IF(A12="",0,C12*IFERROR(INDEX('Matérias-Primas'!$J$5:$J$45,MATCH(A12,'Matérias-Primas'!$A$5:$A$45,0)),0)) -> 0 | J12: =IF(A12="",0,C12*IFERROR(INDEX('Matérias-Primas'!$K$5:$K$45,MATCH(A12,'Matérias-Primas'!$A$5:$A$45,0)),0)) -> 0 | K12: =IF(A12="",0,C12*IFERROR(INDEX('Matérias-Primas'!$L$5:$L$45,MATCH(A12,'Matérias-Primas'!$A$5:$A$45,0)),0)) -> 0 | L12: =IF(A12="",0,C12*IFERROR(INDEX('Matérias-Primas'!$M$5:$M$45,MATCH(A12,'Matérias-Primas'!$A$5:$A$45,0)),0)) -> 0 | M12: =IF(A12="",0,C12*IFERROR(INDEX('Matérias-Primas'!$N$5:$N$45,MATCH(A12,'Matérias-Primas'!$A$5:$A$45,0)),0)) -> 0 | N12: =IF(A12="",0,C12*IFERROR(INDEX('Matérias-Primas'!$O$5:$O$45,MATCH(A12,'Matérias-Primas'!$A$5:$A$45,0)),0)) -> 0 | O12: =IF(A12="",0,C12*IFERROR(INDEX('Matérias-Primas'!$P$5:$P$45,MATCH(A12,'Matérias-Primas'!$A$5:$A$45,0)),0)) -> 0 | P12: =IF(A12="",0,C12*IFERROR(INDEX('Matérias-Primas'!$Q$5:$Q$45,MATCH(A12,'Matérias-Primas'!$A$5:$A$45,0)),0)) -> 0 | Q12: =IF(A12="",0,C12*IFERROR(INDEX('Matérias-Primas'!$R$5:$R$45,MATCH(A12,'Matérias-Primas'!$A$5:$A$45,0)),0)) -> 0
C13: =IF(B13="","",B13/SUM($B$5:$B$14)) | D13: =IF(A13="","",IFERROR(INDEX('Matérias-Primas'!$D$5:$D$45,MATCH(A13,'Matérias-Primas'!$A$5:$A$45,0)),0)) | E13: =IF(A13="",0,C13*IFERROR(INDEX('Matérias-Primas'!$F$5:$F$45,MATCH(A13,'Matérias-Primas'!$A$5:$A$45,0)),0)) -> 0 | F13: =IF(A13="",0,C13*IFERROR(INDEX('Matérias-Primas'!$G$5:$G$45,MATCH(A13,'Matérias-Primas'!$A$5:$A$45,0)),0)) -> 0 | G13: =IF(A13="",0,C13*IFERROR(INDEX('Matérias-Primas'!$H$5:$H$45,MATCH(A13,'Matérias-Primas'!$A$5:$A$45,0)),0)) -> 0 | H13: =IF(A13="",0,C13*IFERROR(INDEX('Matérias-Primas'!$I$5:$I$45,MATCH(A13,'Matérias-Primas'!$A$5:$A$45,0)),0)) -> 0 | I13: =IF(A13="",0,C13*IFERROR(INDEX('Matérias-Primas'!$J$5:$J$45,MATCH(A13,'Matérias-Primas'!$A$5:$A$45,0)),0)) -> 0 | J13: =IF(A13="",0,C13*IFERROR(INDEX('Matérias-Primas'!$K$5:$K$45,MATCH(A13,'Matérias-Primas'!$A$5:$A$45,0)),0)) -> 0 | K13: =IF(A13="",0,C13*IFERROR(INDEX('Matérias-Primas'!$L$5:$L$45,MATCH(A13,'Matérias-Primas'!$A$5:$A$45,0)),0)) -> 0 | L13: =IF(A13="",0,C13*IFERROR(INDEX('Matérias-Primas'!$M$5:$M$45,MATCH(A13,'Matérias-Primas'!$A$5:$A$45,0)),0)) -> 0 | M13: =IF(A13="",0,C13*IFERROR(INDEX('Matérias-Primas'!$N$5:$N$45,MATCH(A13,'Matérias-Primas'!$A$5:$A$45,0)),0)) -> 0 | N13: =IF(A13="",0,C13*IFERROR(INDEX('Matérias-Primas'!$O$5:$O$45,MATCH(A13,'Matérias-Primas'!$A$5:$A$45,0)),0)) -> 0 | O13: =IF(A13="",0,C13*IFERROR(INDEX('Matérias-Primas'!$P$5:$P$45,MATCH(A13,'Matérias-Primas'!$A$5:$A$45,0)),0)) -> 0 | P13: =IF(A13="",0,C13*IFERROR(INDEX('Matérias-Primas'!$Q$5:$Q$45,MATCH(A13,'Matérias-Primas'!$A$5:$A$45,0)),0)) -> 0 | Q13: =IF(A13="",0,C13*IFERROR(INDEX('Matérias-Primas'!$R$5:$R$45,MATCH(A13,'Matérias-Primas'!$A$5:$A$45,0)),0)) -> 0
C14: =IF(B14="","",B14/SUM($B$5:$B$14)) | D14: =IF(A14="","",IFERROR(INDEX('Matérias-Primas'!$D$5:$D$45,MATCH(A14,'Matérias-Primas'!$A$5:$A$45,0)),0)) | E14: =IF(A14="",0,C14*IFERROR(INDEX('Matérias-Primas'!$F$5:$F$45,MATCH(A14,'Matérias-Primas'!$A$5:$A$45,0)),0)) -> 0 | F14: =IF(A14="",0,C14*IFERROR(INDEX('Matérias-Primas'!$G$5:$G$45,MATCH(A14,'Matérias-Primas'!$A$5:$A$45,0)),0)) -> 0 | G14: =IF(A14="",0,C14*IFERROR(INDEX('Matérias-Primas'!$H$5:$H$45,MATCH(A14,'Matérias-Primas'!$A$5:$A$45,0)),0)) -> 0 | H14: =IF(A14="",0,C14*IFERROR(INDEX('Matérias-Primas'!$I$5:$I$45,MATCH(A14,'Matérias-Primas'!$A$5:$A$45,0)),0)) -> 0 | I14: =IF(A14="",0,C14*IFERROR(INDEX('Matérias-Primas'!$J$5:$J$45,MATCH(A14,'Matérias-Primas'!$A$5:$A$45,0)),0)) -> 0 | J14: =IF(A14="",0,C14*IFERROR(INDEX('Matérias-Primas'!$K$5:$K$45,MATCH(A14,'Matérias-Primas'!$A$5:$A$45,0)),0)) -> 0 | K14: =IF(A14="",0,C14*IFERROR(INDEX('Matérias-Primas'!$L$5:$L$45,MATCH(A14,'Matérias-Primas'!$A$5:$A$45,0)),0)) -> 0 | L14: =IF(A14="",0,C14*IFERROR(INDEX('Matérias-Primas'!$M$5:$M$45,MATCH(A14,'Matérias-Primas'!$A$5:$A$45,0)),0)) -> 0 | M14: =IF(A14="",0,C14*IFERROR(INDEX('Matérias-Primas'!$N$5:$N$45,MATCH(A14,'Matérias-Primas'!$A$5:$A$45,0)),0)) -> 0 | N14: =IF(A14="",0,C14*IFERROR(INDEX('Matérias-Primas'!$O$5:$O$45,MATCH(A14,'Matérias-Primas'!$A$5:$A$45,0)),0)) -> 0 | O14: =IF(A14="",0,C14*IFERROR(INDEX('Matérias-Primas'!$P$5:$P$45,MATCH(A14,'Matérias-Primas'!$A$5:$A$45,0)),0)) -> 0 | P14: =IF(A14="",0,C14*IFERROR(INDEX('Matérias-Primas'!$Q$5:$Q$45,MATCH(A14,'Matérias-Primas'!$A$5:$A$45,0)),0)) -> 0 | Q14: =IF(A14="",0,C14*IFERROR(INDEX('Matérias-Primas'!$R$5:$R$45,MATCH(A14,'Matérias-Primas'!$A$5:$A$45,0)),0)) -> 0
A15: Total | B15: =SUM(B5:B14) -> 100 | C15: =SUM(C5:C14) -> 1 | E15: =SUM(E5:E14) -> 59.265 | F15: =SUM(F5:F14) -> 10.55 | G15: =SUM(G5:G14) -> 4.158 | H15: =SUM(H5:H14) -> 2.604 | I15: =SUM(I5:I14) -> 2.75 | J15: =SUM(J5:J14) -> 0 | K15: =SUM(K5:K14) -> 8.498 | L15: =SUM(L5:L14) -> 0 | ... Q15: =SUM(Q5:Q14) -> 0
A16: Massa molar | E16: ='Matérias-Primas'!F3 -> 60.08 | F16: ='Matérias-Primas'!G3 -> 101.96 | G16: ='Matérias-Primas'!H3 -> 69.62 | H16: ='Matérias-Primas'!I3 -> 61.98 | I16: ='Matérias-Primas'!J3 -> 94.2 | J16: ='Matérias-Primas'!K3 -> 29.88 | K16: ='Matérias-Primas'!L3 -> 56.08 | L16: ='Matérias-Primas'!M3 -> 40.3 | ... Q16: ='Matérias-Primas'!R3 -> 79.87
A17: Mols | C17: Soma fundentes: | D17: =H17+I17+J17+K17+L17+M17+N17 -> 0.29048782 | E17: =E15/E16 -> 0.98643475 | F17: =F15/F16 -> 0.10347195 | G17: =G15/G16 -> 0.059724217 | H17: =H15/H16 -> 0.042013553 | I17: =I15/I16 -> 0.029193206 | J17: =J15/J16 -> 0 | K17: =K15/K16 -> 0.15153352 | L17: =L15/L16 -> 0 | ... Q17: =Q15/Q16 -> 0
A18: UMF (fundentes = 1) | E18: =IF($D$17=0,0,E17/$D$17) -> 3.395787 | F18: =IF($D$17=0,0,F17/$D$17) -> 0.35620065 | G18: =IF($D$17=0,0,G17/$D$17) -> 0.20559973 | H18: =IF($D$17=0,0,H17/$D$17) -> 0.14463103 | I18: =IF($D$17=0,0,I17/$D$17) -> 0.10049718 | J18: =IF($D$17=0,0,J17/$D$17) -> 0 | K18: =IF($D$17=0,0,K17/$D$17) -> 0.5216519 | L18: =IF($D$17=0,0,L17/$D$17) -> 0 | ... Q18: =IF($D$17=0,0,Q17/$D$17) -> 0
A20: Checagem contra faixas-alvo
A21: Indicador | B21: Valor | C21: Mín | D21: Máx | E21: Status
A22: SiO₂ (UMF) | B22: =E18 -> 3.395787 | C22: 3 | D22: 4 | E22: =IF(AND(B22>=C22,B22<=D22),"OK","Ajustar") -> OK
A23: Al₂O₃ (UMF) | B23: =F18 -> 0.35620065 | C23: 0.3 | D23: 0.4 | E23: =IF(AND(B23>=C23,B23<=D23),"OK","Ajustar") -> OK
A24: B₂O₃ (UMF) | B24: =G18 -> 0.20559973 | C24: 0.1 | D24: 0.3 | E24: =IF(AND(B24>=C24,B24<=D24),"OK","Ajustar") -> OK
A25: Razão SiO₂:Al₂O₃ | B25: =IF(F18=0,0,E18/F18) -> 9.5333543 | C25: 8 | D25: 10 | E25: =IF(AND(B25>=C25,B25<=D25),"OK","Ajustar") -> OK
A27: Custo matéria-prima da base (R$/kg) | B27: =SUMPRODUCT(C5:C14,D5:D14) -> 8.69
A28: Faixas-alvo são referências de literatura para cone 6 estável; ajuste-as conforme seus testes. Fórmula-alvo calculada sobre óxidos; colorantes entram na aba Cores.

Sheet Base D
A1: Base D — Reativa fluida (rutilo / azul flutuante)
A2: Mais boro, mais fluida. Melhor com resfriamento lento. Atenção ao escorrimento.
E3: Contribuição em massa de cada óxido (g por 100 g de esmalte queimado não normalizado) →
A4: Material | B4: Quantidade (g) | C4: % normalizado | D4: Preço (R$/kg) | E4: SiO2 | F4: Al2O3 | G4: B2O3 | H4: Na2O | I4: K2O | J4: Li2O | K4: CaO | L4: MgO | M4: SrO | N4: ZnO | O4: ZrO2 | P4: Fe2O3 | Q4: TiO2
A5: Frita borácica | B5: 30 | C5: =IF(B5="","",B5/SUM($B$5:$B$14)) -> 0.3 | D5: =IF(A5="","",IFERROR(INDEX('Matérias-Primas'!$D$5:$D$45,MATCH(A5,'Matérias-Primas'!$A$5:$A$45,0)),0)) -> 15 | E5: =IF(A5="",0,C5*IFERROR(INDEX('Matérias-Primas'!$F$5:$F$45,MATCH(A5,'Matérias-Primas'!$A$5:$A$45,0)),0)) -> 13.95 | F5: =IF(A5="",0,C5*IFERROR(INDEX('Matérias-Primas'!$G$5:$G$45,MATCH(A5,'Matérias-Primas'!$A$5:$A$45,0)),0)) -> 0 | G5: =IF(A5="",0,C5*IFERROR(INDEX('Matérias-Primas'!$H$5:$H$45,MATCH(A5,'Matérias-Primas'!$A$5:$A$45,0)),0)) -> 6.93 | H5: =IF(A5="",0,C5*IFERROR(INDEX('Matérias-Primas'!$I$5:$I$45,MATCH(A5,'Matérias-Primas'!$A$5:$A$45,0)),0)) -> 3.09 | I5: =IF(A5="",0,C5*IFERROR(INDEX('Matérias-Primas'!$J$5:$J$45,MATCH(A5,'Matérias-Primas'!$A$5:$A$45,0)),0)) -> 0 | J5: =IF(A5="",0,C5*IFERROR(INDEX('Matérias-Primas'!$K$5:$K$45,MATCH(A5,'Matérias-Primas'!$A$5:$A$45,0)),0)) -> 0 | K5: =IF(A5="",0,C5*IFERROR(INDEX('Matérias-Primas'!$L$5:$L$45,MATCH(A5,'Matérias-Primas'!$A$5:$A$45,0)),0)) -> 6.03 | L5: =IF(A5="",0,C5*IFERROR(INDEX('Matérias-Primas'!$M$5:$M$45,MATCH(A5,'Matérias-Primas'!$A$5:$A$45,0)),0)) -> 0 | M5: =IF(A5="",0,C5*IFERROR(INDEX('Matérias-Primas'!$N$5:$N$45,MATCH(A5,'Matérias-Primas'!$A$5:$A$45,0)),0)) -> 0 | N5: =IF(A5="",0,C5*IFERROR(INDEX('Matérias-Primas'!$O$5:$O$45,MATCH(A5,'Matérias-Primas'!$A$5:$A$45,0)),0)) -> 0 | O5: =IF(A5="",0,C5*IFERROR(INDEX('Matérias-Primas'!$P$5:$P$45,MATCH(A5,'Matérias-Primas'!$A$5:$A$45,0)),0)) -> 0 | P5: =IF(A5="",0,C5*IFERROR(INDEX('Matérias-Primas'!$Q$5:$Q$45,MATCH(A5,'Matérias-Primas'!$A$5:$A$45,0)),0)) -> 0 | Q5: =IF(A5="",0,C5*IFERROR(INDEX('Matérias-Primas'!$R$5:$R$45,MATCH(A5,'Matérias-Primas'!$A$5:$A$45,0)),0)) -> 0
A6: Feldspato potássico | B6: 20 | C6: =IF(B6="","",B6/SUM($B$5:$B$14)) -> 0.2 | D6: =IF(A6="","",IFERROR(INDEX('Matérias-Primas'!$D$5:$D$45,MATCH(A6,'Matérias-Primas'!$A$5:$A$45,0)),0)) -> 3.5 | E6: =IF(A6="",0,C6*IFERROR(INDEX('Matérias-Primas'!$F$5:$F$45,MATCH(A6,'Matérias-Primas'!$A$5:$A$45,0)),0)) -> 13.4 | F6: =IF(A6="",0,C6*IFERROR(INDEX('Matérias-Primas'!$G$5:$G$45,MATCH(A6,'Matérias-Primas'!$A$5:$A$45,0)),0)) -> 3.7 | G6: =IF(A6="",0,C6*IFERROR(INDEX('Matérias-Primas'!$H$5:$H$45,MATCH(A6,'Matérias-Primas'!$A$5:$A$45,0)),0)) -> 0 | H6: =IF(A6="",0,C6*IFERROR(INDEX('Matérias-Primas'!$I$5:$I$45,MATCH(A6,'Matérias-Primas'!$A$5:$A$45,0)),0)) -> 0.6 | I6: =IF(A6="",0,C6*IFERROR(INDEX('Matérias-Primas'!$J$5:$J$45,MATCH(A6,'Matérias-Primas'!$A$5:$A$45,0)),0)) -> 2.2 | J6: =IF(A6="",0,C6*IFERROR(INDEX('Matérias-Primas'!$K$5:$K$45,MATCH(A6,'Matérias-Primas'!$A$5:$A$45,0)),0)) -> 0 | K6: =IF(A6="",0,C6*IFERROR(INDEX('Matérias-Primas'!$L$5:$L$45,MATCH(A6,'Matérias-Primas'!$A$5:$A$45,0)),0)) -> 0.04 | L6: =IF(A6="",0,C6*IFERROR(INDEX('Matérias-Primas'!$M$5:$M$45,MATCH(A6,'Matérias-Primas'!$A$5:$A$45,0)),0)) -> 0 | M6: =IF(A6="",0,C6*IFERROR(INDEX('Matérias-Primas'!$N$5:$N$45,MATCH(A6,'Matérias-Primas'!$A$5:$A$45,0)),0)) -> 0 | N6: =IF(A6="",0,C6*IFERROR(INDEX('Matérias-Primas'!$O$5:$O$45,MATCH(A6,'Matérias-Primas'!$A$5:$A$45,0)),0)) -> 0 | O6: =IF(A6="",0,C6*IFERROR(INDEX('Matérias-Primas'!$P$5:$P$45,MATCH(A6,'Matérias-Primas'!$A$5:$A$45,0)),0)) -> 0 | P6: =IF(A6="",0,C6*IFERROR(INDEX('Matérias-Primas'!$Q$5:$Q$45,MATCH(A6,'Matérias-Primas'!$A$5:$A$45,0)),0)) -> 0.02 | Q6: =IF(A6="",0,C6*IFERROR(INDEX('Matérias-Primas'!$R$5:$R$45,MATCH(A6,'Matérias-Primas'!$A$5:$A$45,0)),0)) -> 0
A7: Carbonato de estrôncio | B7: 8 | C7: =IF(B7="","",B7/SUM($B$5:$B$14)) -> 0.08 | D7: =IF(A7="","",IFERROR(INDEX('Matérias-Primas'!$D$5:$D$45,MATCH(A7,'Matérias-Primas'!$A$5:$A$45,0)),0)) -> 35 | E7: =IF(A7="",0,C7*IFERROR(INDEX('Matérias-Primas'!$F$5:$F$45,MATCH(A7,'Matérias-Primas'!$A$5:$A$45,0)),0)) -> 0 | F7: =IF(A7="",0,C7*IFERROR(INDEX('Matérias-Primas'!$G$5:$G$45,MATCH(A7,'Matérias-Primas'!$A$5:$A$45,0)),0)) -> 0 | G7: =IF(A7="",0,C7*IFERROR(INDEX('Matérias-Primas'!$H$5:$H$45,MATCH(A7,'Matérias-Primas'!$A$5:$A$45,0)),0)) -> 0 | H7: =IF(A7="",0,C7*IFERROR(INDEX('Matérias-Primas'!$I$5:$I$45,MATCH(A7,'Matérias-Primas'!$A$5:$A$45,0)),0)) -> 0 | I7: =IF(A7="",0,C7*IFERROR(INDEX('Matérias-Primas'!$J$5:$J$45,MATCH(A7,'Matérias-Primas'!$A$5:$A$45,0)),0)) -> 0 | J7: =IF(A7="",0,C7*IFERROR(INDEX('Matérias-Primas'!$K$5:$K$45,MATCH(A7,'Matérias-Primas'!$A$5:$A$45,0)),0)) -> 0 | K7: =IF(A7="",0,C7*IFERROR(INDEX('Matérias-Primas'!$L$5:$L$45,MATCH(A7,'Matérias-Primas'!$A$5:$A$45,0)),0)) -> 0 | L7: =IF(A7="",0,C7*IFERROR(INDEX('Matérias-Primas'!$M$5:$M$45,MATCH(A7,'Matérias-Primas'!$A$5:$A$45,0)),0)) -> 0 | M7: =IF(A7="",0,C7*IFERROR(INDEX('Matérias-Primas'!$N$5:$N$45,MATCH(A7,'Matérias-Primas'!$A$5:$A$45,0)),0)) -> 5.616 | N7: =IF(A7="",0,C7*IFERROR(INDEX('Matérias-Primas'!$O$5:$O$45,MATCH(A7,'Matérias-Primas'!$A$5:$A$45,0)),0)) -> 0 | O7: =IF(A7="",0,C7*IFERROR(INDEX('Matérias-Primas'!$P$5:$P$45,MATCH(A7,'Matérias-Primas'!$A$5:$A$45,0)),0)) -> 0 | P7: =IF(A7="",0,C7*IFERROR(INDEX('Matérias-Primas'!$Q$5:$Q$45,MATCH(A7,'Matérias-Primas'!$A$5:$A$45,0)),0)) -> 0 | Q7: =IF(A7="",0,C7*IFERROR(INDEX('Matérias-Primas'!$R$5:$R$45,MATCH(A7,'Matérias-Primas'!$A$5:$A$45,0)),0)) -> 0
A8: Wollastonita | B8: 7 | C8: =IF(B8="","",B8/SUM($B$5:$B$14)) -> 0.07 | D8: =IF(A8="","",IFERROR(INDEX('Matérias-Primas'!$D$5:$D$45,MATCH(A8,'Matérias-Primas'!$A$5:$A$45,0)),0)) -> 8 | E8: =IF(A8="",0,C8*IFERROR(INDEX('Matérias-Primas'!$F$5:$F$45,MATCH(A8,'Matérias-Primas'!$A$5:$A$45,0)),0)) -> 3.619 | F8: =IF(A8="",0,C8*IFERROR(INDEX('Matérias-Primas'!$G$5:$G$45,MATCH(A8,'Matérias-Primas'!$A$5:$A$45,0)),0)) -> 0 | G8: =IF(A8="",0,C8*IFERROR(INDEX('Matérias-Primas'!$H$5:$H$45,MATCH(A8,'Matérias-Primas'!$A$5:$A$45,0)),0)) -> 0 | H8: =IF(A8="",0,C8*IFERROR(INDEX('Matérias-Primas'!$I$5:$I$45,MATCH(A8,'Matérias-Primas'!$A$5:$A$45,0)),0)) -> 0 | I8: =IF(A8="",0,C8*IFERROR(INDEX('Matérias-Primas'!$J$5:$J$45,MATCH(A8,'Matérias-Primas'!$A$5:$A$45,0)),0)) -> 0 | J8: =IF(A8="",0,C8*IFERROR(INDEX('Matérias-Primas'!$K$5:$K$45,MATCH(A8,'Matérias-Primas'!$A$5:$A$45,0)),0)) -> 0 | K8: =IF(A8="",0,C8*IFERROR(INDEX('Matérias-Primas'!$L$5:$L$45,MATCH(A8,'Matérias-Primas'!$A$5:$A$45,0)),0)) -> 3.381 | L8: =IF(A8="",0,C8*IFERROR(INDEX('Matérias-Primas'!$M$5:$M$45,MATCH(A8,'Matérias-Primas'!$A$5:$A$45,0)),0)) -> 0 | M8: =IF(A8="",0,C8*IFERROR(INDEX('Matérias-Primas'!$N$5:$N$45,MATCH(A8,'Matérias-Primas'!$A$5:$A$45,0)),0)) -> 0 | N8: =IF(A8="",0,C8*IFERROR(INDEX('Matérias-Primas'!$O$5:$O$45,MATCH(A8,'Matérias-Primas'!$A$5:$A$45,0)),0)) -> 0 | O8: =IF(A8="",0,C8*IFERROR(INDEX('Matérias-Primas'!$P$5:$P$45,MATCH(A8,'Matérias-Primas'!$A$5:$A$45,0)),0)) -> 0 | P8: =IF(A8="",0,C8*IFERROR(INDEX('Matérias-Primas'!$Q$5:$Q$45,MATCH(A8,'Matérias-Primas'!$A$5:$A$45,0)),0)) -> 0 | Q8: =IF(A8="",0,C8*IFERROR(INDEX('Matérias-Primas'!$R$5:$R$45,MATCH(A8,'Matérias-Primas'!$A$5:$A$45,0)),0)) -> 0
A9: Caulim | B9: 15 | C9: =IF(B9="","",B9/SUM($B$5:$B$14)) -> 0.15 | D9: =IF(A9="","",IFERROR(INDEX('Matérias-Primas'!$D$5:$D$45,MATCH(A9,'Matérias-Primas'!$A$5:$A$45,0)),0)) -> 2.5 | E9: =IF(A9="",0,C9*IFERROR(INDEX('Matérias-Primas'!$F$5:$F$45,MATCH(A9,'Matérias-Primas'!$A$5:$A$45,0)),0)) -> 6.975 | F9: =IF(A9="",0,C9*IFERROR(INDEX('Matérias-Primas'!$G$5:$G$45,MATCH(A9,'Matérias-Primas'!$A$5:$A$45,0)),0)) -> 5.925 | G9: =IF(A9="",0,C9*IFERROR(INDEX('Matérias-Primas'!$H$5:$H$45,MATCH(A9,'Matérias-Primas'!$A$5:$A$45,0)),0)) -> 0 | H9: =IF(A9="",0,C9*IFERROR(INDEX('Matérias-Primas'!$I$5:$I$45,MATCH(A9,'Matérias-Primas'!$A$5:$A$45,0)),0)) -> 0 | I9: =IF(A9="",0,C9*IFERROR(INDEX('Matérias-Primas'!$J$5:$J$45,MATCH(A9,'Matérias-Primas'!$A$5:$A$45,0)),0)) -> 0 | J9: =IF(A9="",0,C9*IFERROR(INDEX('Matérias-Primas'!$K$5:$K$45,MATCH(A9,'Matérias-Primas'!$A$5:$A$45,0)),0)) -> 0 | K9: =IF(A9="",0,C9*IFERROR(INDEX('Matérias-Primas'!$L$5:$L$45,MATCH(A9,'Matérias-Primas'!$A$5:$A$45,0)),0)) -> 0 | L9: =IF(A9="",0,C9*IFERROR(INDEX('Matérias-Primas'!$M$5:$M$45,MATCH(A9,'Matérias-Primas'!$A$5:$A$45,0)),0)) -> 0 | M9: =IF(A9="",0,C9*IFERROR(INDEX('Matérias-Primas'!$N$5:$N$45,MATCH(A9,'Matérias-Primas'!$A$5:$A$45,0)),0)) -> 0 | N9: =IF(A9="",0,C9*IFERROR(INDEX('Matérias-Primas'!$O$5:$O$45,MATCH(A9,'Matérias-Primas'!$A$5:$A$45,0)),0)) -> 0 | O9: =IF(A9="",0,C9*IFERROR(INDEX('Matérias-Primas'!$P$5:$P$45,MATCH(A9,'Matérias-Primas'!$A$5:$A$45,0)),0)) -> 0 | P9: =IF(A9="",0,C9*IFERROR(INDEX('Matérias-Primas'!$Q$5:$Q$45,MATCH(A9,'Matérias-Primas'!$A$5:$A$45,0)),0)) -> 0.015 | Q9: =IF(A9="",0,C9*IFERROR(INDEX('Matérias-Primas'!$R$5:$R$45,MATCH(A9,'Matérias-Primas'!$A$5:$A$45,0)),0)) -> 0
A10: Quartzo (sílica 325#) | B10: 20 | C10: =IF(B10="","",B10/SUM($B$5:$B$14)) -> 0.2 | D10: =IF(A10="","",IFERROR(INDEX('Matérias-Primas'!$D$5:$D$45,MATCH(A10,'Matérias-Primas'!$A$5:$A$45,0)),0)) -> 2 | E10: =IF(A10="",0,C10*IFERROR(INDEX('Matérias-Primas'!$F$5:$F$45,MATCH(A10,'Matérias-Primas'!$A$5:$A$45,0)),0)) -> 20 | F10: =IF(A10="",0,C10*IFERROR(INDEX('Matérias-Primas'!$G$5:$G$45,MATCH(A10,'Matérias-Primas'!$A$5:$A$45,0)),0)) -> 0 | G10: =IF(A10="",0,C10*IFERROR(INDEX('Matérias-Primas'!$H$5:$H$45,MATCH(A10,'Matérias-Primas'!$A$5:$A$45,0)),0)) -> 0 | H10: =IF(A10="",0,C10*IFERROR(INDEX('Matérias-Primas'!$I$5:$I$45,MATCH(A10,'Matérias-Primas'!$A$5:$A$45,0)),0)) -> 0 | I10: =IF(A10="",0,C10*IFERROR(INDEX('Matérias-Primas'!$J$5:$J$45,MATCH(A10,'Matérias-Primas'!$A$5:$A$45,0)),0)) -> 0 | J10: =IF(A10="",0,C10*IFERROR(INDEX('Matérias-Primas'!$K$5:$K$45,MATCH(A10,'Matérias-Primas'!$A$5:$A$45,0)),0)) -> 0 | K10: =IF(A10="",0,C10*IFERROR(INDEX('Matérias-Primas'!$L$5:$L$45,MATCH(A10,'Matérias-Primas'!$A$5:$A$45,0)),0)) -> 0 | L10: =IF(A10="",0,C10*IFERROR(INDEX('Matérias-Primas'!$M$5:$M$45,MATCH(A10,'Matérias-Primas'!$A$5:$A$45,0)),0)) -> 0 | M10: =IF(A10="",0,C10*IFERROR(INDEX('Matérias-Primas'!$N$5:$N$45,MATCH(A10,'Matérias-Primas'!$A$5:$A$45,0)),0)) -> 0 | N10: =IF(A10="",0,C10*IFERROR(INDEX('Matérias-Primas'!$O$5:$O$45,MATCH(A10,'Matérias-Primas'!$A$5:$A$45,0)),0)) -> 0 | O10: =IF(A10="",0,C10*IFERROR(INDEX('Matérias-Primas'!$P$5:$P$45,MATCH(A10,'Matérias-Primas'!$A$5:$A$45,0)),0)) -> 0 | P10: =IF(A10="",0,C10*IFERROR(INDEX('Matérias-Primas'!$Q$5:$Q$45,MATCH(A10,'Matérias-Primas'!$A$5:$A$45,0)),0)) -> 0 | Q10: =IF(A10="",0,C10*IFERROR(INDEX('Matérias-Primas'!$R$5:$R$45,MATCH(A10,'Matérias-Primas'!$A$5:$A$45,0)),0)) -> 0
C11: =IF(B11="","",B11/SUM($B$5:$B$14)) | D11: =IF(A11="","",IFERROR(INDEX('Matérias-Primas'!$D$5:$D$45,MATCH(A11,'Matérias-Primas'!$A$5:$A$45,0)),0)) | E11: =IF(A11="",0,C11*IFERROR(INDEX('Matérias-Primas'!$F$5:$F$45,MATCH(A11,'Matérias-Primas'!$A$5:$A$45,0)),0)) -> 0 | F11: =IF(A11="",0,C11*IFERROR(INDEX('Matérias-Primas'!$G$5:$G$45,MATCH(A11,'Matérias-Primas'!$A$5:$A$45,0)),0)) -> 0 | G11: =IF(A11="",0,C11*IFERROR(INDEX('Matérias-Primas'!$H$5:$H$45,MATCH(A11,'Matérias-Primas'!$A$5:$A$45,0)),0)) -> 0 | H11: =IF(A11="",0,C11*IFERROR(INDEX('Matérias-Primas'!$I$5:$I$45,MATCH(A11,'Matérias-Primas'!$A$5:$A$45,0)),0)) -> 0 | I11: =IF(A11="",0,C11*IFERROR(INDEX('Matérias-Primas'!$J$5:$J$45,MATCH(A11,'Matérias-Primas'!$A$5:$A$45,0)),0)) -> 0 | J11: =IF(A11="",0,C11*IFERROR(INDEX('Matérias-Primas'!$K$5:$K$45,MATCH(A11,'Matérias-Primas'!$A$5:$A$45,0)),0)) -> 0 | K11: =IF(A11="",0,C11*IFERROR(INDEX('Matérias-Primas'!$L$5:$L$45,MATCH(A11,'Matérias-Primas'!$A$5:$A$45,0)),0)) -> 0 | L11: =IF(A11="",0,C11*IFERROR(INDEX('Matérias-Primas'!$M$5:$M$45,MATCH(A11,'Matérias-Primas'!$A$5:$A$45,0)),0)) -> 0 | M11: =IF(A11="",0,C11*IFERROR(INDEX('Matérias-Primas'!$N$5:$N$45,MATCH(A11,'Matérias-Primas'!$A$5:$A$45,0)),0)) -> 0 | N11: =IF(A11="",0,C11*IFERROR(INDEX('Matérias-Primas'!$O$5:$O$45,MATCH(A11,'Matérias-Primas'!$A$5:$A$45,0)),0)) -> 0 | O11: =IF(A11="",0,C11*IFERROR(INDEX('Matérias-Primas'!$P$5:$P$45,MATCH(A11,'Matérias-Primas'!$A$5:$A$45,0)),0)) -> 0 | P11: =IF(A11="",0,C11*IFERROR(INDEX('Matérias-Primas'!$Q$5:$Q$45,MATCH(A11,'Matérias-Primas'!$A$5:$A$45,0)),0)) -> 0 | Q11: =IF(A11="",0,C11*IFERROR(INDEX('Matérias-Primas'!$R$5:$R$45,MATCH(A11,'Matérias-Primas'!$A$5:$A$45,0)),0)) -> 0
C12: =IF(B12="","",B12/SUM($B$5:$B$14)) | D12: =IF(A12="","",IFERROR(INDEX('Matérias-Primas'!$D$5:$D$45,MATCH(A12,'Matérias-Primas'!$A$5:$A$45,0)),0)) | E12: =IF(A12="",0,C12*IFERROR(INDEX('Matérias-Primas'!$F$5:$F$45,MATCH(A12,'Matérias-Primas'!$A$5:$A$45,0)),0)) -> 0 | F12: =IF(A12="",0,C12*IFERROR(INDEX('Matérias-Primas'!$G$5:$G$45,MATCH(A12,'Matérias-Primas'!$A$5:$A$45,0)),0)) -> 0 | G12: =IF(A12="",0,C12*IFERROR(INDEX('Matérias-Primas'!$H$5:$H$45,MATCH(A12,'Matérias-Primas'!$A$5:$A$45,0)),0)) -> 0 | H12: =IF(A12="",0,C12*IFERROR(INDEX('Matérias-Primas'!$I$5:$I$45,MATCH(A12,'Matérias-Primas'!$A$5:$A$45,0)),0)) -> 0 | I12: =IF(A12="",0,C12*IFERROR(INDEX('Matérias-Primas'!$J$5:$J$45,MATCH(A12,'Matérias-Primas'!$A$5:$A$45,0)),0)) -> 0 | J12: =IF(A12="",0,C12*IFERROR(INDEX('Matérias-Primas'!$K$5:$K$45,MATCH(A12,'Matérias-Primas'!$A$5:$A$45,0)),0)) -> 0 | K12: =IF(A12="",0,C12*IFERROR(INDEX('Matérias-Primas'!$L$5:$L$45,MATCH(A12,'Matérias-Primas'!$A$5:$A$45,0)),0)) -> 0 | L12: =IF(A12="",0,C12*IFERROR(INDEX('Matérias-Primas'!$M$5:$M$45,MATCH(A12,'Matérias-Primas'!$A$5:$A$45,0)),0)) -> 0 | M12: =IF(A12="",0,C12*IFERROR(INDEX('Matérias-Primas'!$N$5:$N$45,MATCH(A12,'Matérias-Primas'!$A$5:$A$45,0)),0)) -> 0 | N12: =IF(A12="",0,C12*IFERROR(INDEX('Matérias-Primas'!$O$5:$O$45,MATCH(A12,'Matérias-Primas'!$A$5:$A$45,0)),0)) -> 0 | O12: =IF(A12="",0,C12*IFERROR(INDEX('Matérias-Primas'!$P$5:$P$45,MATCH(A12,'Matérias-Primas'!$A$5:$A$45,0)),0)) -> 0 | P12: =IF(A12="",0,C12*IFERROR(INDEX('Matérias-Primas'!$Q$5:$Q$45,MATCH(A12,'Matérias-Primas'!$A$5:$A$45,0)),0)) -> 0 | Q12: =IF(A12="",0,C12*IFERROR(INDEX('Matérias-Primas'!$R$5:$R$45,MATCH(A12,'Matérias-Primas'!$A$5:$A$45,0)),0)) -> 0
C13: =IF(B13="","",B13/SUM($B$5:$B$14)) | D13: =IF(A13="","",IFERROR(INDEX('Matérias-Primas'!$D$5:$D$45,MATCH(A13,'Matérias-Primas'!$A$5:$A$45,0)),0)) | E13: =IF(A13="",0,C13*IFERROR(INDEX('Matérias-Primas'!$F$5:$F$45,MATCH(A13,'Matérias-Primas'!$A$5:$A$45,0)),0)) -> 0 | F13: =IF(A13="",0,C13*IFERROR(INDEX('Matérias-Primas'!$G$5:$G$45,MATCH(A13,'Matérias-Primas'!$A$5:$A$45,0)),0)) -> 0 | G13: =IF(A13="",0,C13*IFERROR(INDEX('Matérias-Primas'!$H$5:$H$45,MATCH(A13,'Matérias-Primas'!$A$5:$A$45,0)),0)) -> 0 | H13: =IF(A13="",0,C13*IFERROR(INDEX('Matérias-Primas'!$I$5:$I$45,MATCH(A13,'Matérias-Primas'!$A$5:$A$45,0)),0)) -> 0 | I13: =IF(A13="",0,C13*IFERROR(INDEX('Matérias-Primas'!$J$5:$J$45,MATCH(A13,'Matérias-Primas'!$A$5:$A$45,0)),0)) -> 0 | J13: =IF(A13="",0,C13*IFERROR(INDEX('Matérias-Primas'!$K$5:$K$45,MATCH(A13,'Matérias-Primas'!$A$5:$A$45,0)),0)) -> 0 | K13: =IF(A13="",0,C13*IFERROR(INDEX('Matérias-Primas'!$L$5:$L$45,MATCH(A13,'Matérias-Primas'!$A$5:$A$45,0)),0)) -> 0 | L13: =IF(A13="",0,C13*IFERROR(INDEX('Matérias-Primas'!$M$5:$M$45,MATCH(A13,'Matérias-Primas'!$A$5:$A$45,0)),0)) -> 0 | M13: =IF(A13="",0,C13*IFERROR(INDEX('Matérias-Primas'!$N$5:$N$45,MATCH(A13,'Matérias-Primas'!$A$5:$A$45,0)),0)) -> 0 | N13: =IF(A13="",0,C13*IFERROR(INDEX('Matérias-Primas'!$O$5:$O$45,MATCH(A13,'Matérias-Primas'!$A$5:$A$45,0)),0)) -> 0 | O13: =IF(A13="",0,C13*IFERROR(INDEX('Matérias-Primas'!$P$5:$P$45,MATCH(A13,'Matérias-Primas'!$A$5:$A$45,0)),0)) -> 0 | P13: =IF(A13="",0,C13*IFERROR(INDEX('Matérias-Primas'!$Q$5:$Q$45,MATCH(A13,'Matérias-Primas'!$A$5:$A$45,0)),0)) -> 0 | Q13: =IF(A13="",0,C13*IFERROR(INDEX('Matérias-Primas'!$R$5:$R$45,MATCH(A13,'Matérias-Primas'!$A$5:$A$45,0)),0)) -> 0
C14: =IF(B14="","",B14/SUM($B$5:$B$14)) | D14: =IF(A14="","",IFERROR(INDEX('Matérias-Primas'!$D$5:$D$45,MATCH(A14,'Matérias-Primas'!$A$5:$A$45,0)),0)) | E14: =IF(A14="",0,C14*IFERROR(INDEX('Matérias-Primas'!$F$5:$F$45,MATCH(A14,'Matérias-Primas'!$A$5:$A$45,0)),0)) -> 0 | F14: =IF(A14="",0,C14*IFERROR(INDEX('Matérias-Primas'!$G$5:$G$45,MATCH(A14,'Matérias-Primas'!$A$5:$A$45,0)),0)) -> 0 | G14: =IF(A14="",0,C14*IFERROR(INDEX('Matérias-Primas'!$H$5:$H$45,MATCH(A14,'Matérias-Primas'!$A$5:$A$45,0)),0)) -> 0 | H14: =IF(A14="",0,C14*IFERROR(INDEX('Matérias-Primas'!$I$5:$I$45,MATCH(A14,'Matérias-Primas'!$A$5:$A$45,0)),0)) -> 0 | I14: =IF(A14="",0,C14*IFERROR(INDEX('Matérias-Primas'!$J$5:$J$45,MATCH(A14,'Matérias-Primas'!$A$5:$A$45,0)),0)) -> 0 | J14: =IF(A14="",0,C14*IFERROR(INDEX('Matérias-Primas'!$K$5:$K$45,MATCH(A14,'Matérias-Primas'!$A$5:$A$45,0)),0)) -> 0 | K14: =IF(A14="",0,C14*IFERROR(INDEX('Matérias-Primas'!$L$5:$L$45,MATCH(A14,'Matérias-Primas'!$A$5:$A$45,0)),0)) -> 0 | L14: =IF(A14="",0,C14*IFERROR(INDEX('Matérias-Primas'!$M$5:$M$45,MATCH(A14,'Matérias-Primas'!$A$5:$A$45,0)),0)) -> 0 | M14: =IF(A14="",0,C14*IFERROR(INDEX('Matérias-Primas'!$N$5:$N$45,MATCH(A14,'Matérias-Primas'!$A$5:$A$45,0)),0)) -> 0 | N14: =IF(A14="",0,C14*IFERROR(INDEX('Matérias-Primas'!$O$5:$O$45,MATCH(A14,'Matérias-Primas'!$A$5:$A$45,0)),0)) -> 0 | O14: =IF(A14="",0,C14*IFERROR(INDEX('Matérias-Primas'!$P$5:$P$45,MATCH(A14,'Matérias-Primas'!$A$5:$A$45,0)),0)) -> 0 | P14: =IF(A14="",0,C14*IFERROR(INDEX('Matérias-Primas'!$Q$5:$Q$45,MATCH(A14,'Matérias-Primas'!$A$5:$A$45,0)),0)) -> 0 | Q14: =IF(A14="",0,C14*IFERROR(INDEX('Matérias-Primas'!$R$5:$R$45,MATCH(A14,'Matérias-Primas'!$A$5:$A$45,0)),0)) -> 0
A15: Total | B15: =SUM(B5:B14) -> 100 | C15: =SUM(C5:C14) -> 1 | E15: =SUM(E5:E14) -> 57.944 | F15: =SUM(F5:F14) -> 9.625 | G15: =SUM(G5:G14) -> 6.93 | H15: =SUM(H5:H14) -> 3.69 | I15: =SUM(I5:I14) -> 2.2 | J15: =SUM(J5:J14) -> 0 | K15: =SUM(K5:K14) -> 9.451 | L15: =SUM(L5:L14) -> 0 | ... Q15: =SUM(Q5:Q14) -> 0
A16: Massa molar | E16: ='Matérias-Primas'!F3 -> 60.08 | F16: ='Matérias-Primas'!G3 -> 101.96 | G16: ='Matérias-Primas'!H3 -> 69.62 | H16: ='Matérias-Primas'!I3 -> 61.98 | I16: ='Matérias-Primas'!J3 -> 94.2 | J16: ='Matérias-Primas'!K3 -> 29.88 | K16: ='Matérias-Primas'!L3 -> 56.08 | L16: ='Matérias-Primas'!M3 -> 40.3 | ... Q16: ='Matérias-Primas'!R3 -> 79.87
A17: Mols | C17: Soma fundentes: | D17: =H17+I17+J17+K17+L17+M17+N17 -> 0.30561503 | E17: =E15/E16 -> 0.9644474 | F17: =F15/F16 -> 0.094399765 | G17: =G15/G16 -> 0.099540362 | H17: =H15/H16 -> 0.059535334 | I17: =I15/I16 -> 0.023354565 | J17: =J15/J16 -> 0 | K17: =K15/K16 -> 0.1685271 | L17: =L15/L16 -> 0 | ... Q17: =Q15/Q16 -> 0
A18: UMF (fundentes = 1) | E18: =IF($D$17=0,0,E17/$D$17) -> 3.155759 | F18: =IF($D$17=0,0,F17/$D$17) -> 0.30888456 | G18: =IF($D$17=0,0,G17/$D$17) -> 0.32570506 | H18: =IF($D$17=0,0,H17/$D$17) -> 0.19480499 | I18: =IF($D$17=0,0,I17/$D$17) -> 0.076418246 | J18: =IF($D$17=0,0,J17/$D$17) -> 0 | K18: =IF($D$17=0,0,K17/$D$17) -> 0.55143591 | L18: =IF($D$17=0,0,L17/$D$17) -> 0 | ... Q18: =IF($D$17=0,0,Q17/$D$17) -> 0
A20: Checagem contra faixas-alvo
A21: Indicador | B21: Valor | C21: Mín | D21: Máx | E21: Status
A22: SiO₂ (UMF) | B22: =E18 -> 3.155759 | C22: 2.8 | D22: 3.6 | E22: =IF(AND(B22>=C22,B22<=D22),"OK","Ajustar") -> OK
A23: Al₂O₃ (UMF) | B23: =F18 -> 0.30888456 | C23: 0.25 | D23: 0.35 | E23: =IF(AND(B23>=C23,B23<=D23),"OK","Ajustar") -> OK
A24: B₂O₃ (UMF) | B24: =G18 -> 0.32570506 | C24: 0.2 | D24: 0.4 | E24: =IF(AND(B24>=C24,B24<=D24),"OK","Ajustar") -> OK
A25: Razão SiO₂:Al₂O₃ | B25: =IF(F18=0,0,E18/F18) -> 10.216629 | C25: 8 | D25: 11 | E25: =IF(AND(B25>=C25,B25<=D25),"OK","Ajustar") -> OK
A27: Custo matéria-prima da base (R$/kg) | B27: =SUMPRODUCT(C5:C14,D5:D14) -> 9.335
A28: Faixas-alvo são referências de literatura para cone 6 estável; ajuste-as conforme seus testes. Fórmula-alvo calculada sobre óxidos; colorantes entram na aba Cores.

Sheet Base E
A1: Base E — Para óxido de ferro (tenmoku / ferrugem)
A2: Recebe 6–12% de Fe2O3.
E3: Contribuição em massa de cada óxido (g por 100 g de esmalte queimado não normalizado) →
A4: Material | B4: Quantidade (g) | C4: % normalizado | D4: Preço (R$/kg) | E4: SiO2 | F4: Al2O3 | G4: B2O3 | H4: Na2O | I4: K2O | J4: Li2O | K4: CaO | L4: MgO | M4: SrO | N4: ZnO | O4: ZrO2 | P4: Fe2O3 | Q4: TiO2
A5: Feldspato potássico | B5: 35 | C5: =IF(B5="","",B5/SUM($B$5:$B$14)) -> 0.35 | D5: =IF(A5="","",IFERROR(INDEX('Matérias-Primas'!$D$5:$D$45,MATCH(A5,'Matérias-Primas'!$A$5:$A$45,0)),0)) -> 3.5 | E5: =IF(A5="",0,C5*IFERROR(INDEX('Matérias-Primas'!$F$5:$F$45,MATCH(A5,'Matérias-Primas'!$A$5:$A$45,0)),0)) -> 23.45 | F5: =IF(A5="",0,C5*IFERROR(INDEX('Matérias-Primas'!$G$5:$G$45,MATCH(A5,'Matérias-Primas'!$A$5:$A$45,0)),0)) -> 6.475 | G5: =IF(A5="",0,C5*IFERROR(INDEX('Matérias-Primas'!$H$5:$H$45,MATCH(A5,'Matérias-Primas'!$A$5:$A$45,0)),0)) -> 0 | H5: =IF(A5="",0,C5*IFERROR(INDEX('Matérias-Primas'!$I$5:$I$45,MATCH(A5,'Matérias-Primas'!$A$5:$A$45,0)),0)) -> 1.05 | I5: =IF(A5="",0,C5*IFERROR(INDEX('Matérias-Primas'!$J$5:$J$45,MATCH(A5,'Matérias-Primas'!$A$5:$A$45,0)),0)) -> 3.85 | J5: =IF(A5="",0,C5*IFERROR(INDEX('Matérias-Primas'!$K$5:$K$45,MATCH(A5,'Matérias-Primas'!$A$5:$A$45,0)),0)) -> 0 | K5: =IF(A5="",0,C5*IFERROR(INDEX('Matérias-Primas'!$L$5:$L$45,MATCH(A5,'Matérias-Primas'!$A$5:$A$45,0)),0)) -> 0.07 | L5: =IF(A5="",0,C5*IFERROR(INDEX('Matérias-Primas'!$M$5:$M$45,MATCH(A5,'Matérias-Primas'!$A$5:$A$45,0)),0)) -> 0 | M5: =IF(A5="",0,C5*IFERROR(INDEX('Matérias-Primas'!$N$5:$N$45,MATCH(A5,'Matérias-Primas'!$A$5:$A$45,0)),0)) -> 0 | N5: =IF(A5="",0,C5*IFERROR(INDEX('Matérias-Primas'!$O$5:$O$45,MATCH(A5,'Matérias-Primas'!$A$5:$A$45,0)),0)) -> 0 | O5: =IF(A5="",0,C5*IFERROR(INDEX('Matérias-Primas'!$P$5:$P$45,MATCH(A5,'Matérias-Primas'!$A$5:$A$45,0)),0)) -> 0 | P5: =IF(A5="",0,C5*IFERROR(INDEX('Matérias-Primas'!$Q$5:$Q$45,MATCH(A5,'Matérias-Primas'!$A$5:$A$45,0)),0)) -> 0.035 | Q5: =IF(A5="",0,C5*IFERROR(INDEX('Matérias-Primas'!$R$5:$R$45,MATCH(A5,'Matérias-Primas'!$A$5:$A$45,0)),0)) -> 0
A6: Frita borácica | B6: 12 | C6: =IF(B6="","",B6/SUM($B$5:$B$14)) -> 0.12 | D6: =IF(A6="","",IFERROR(INDEX('Matérias-Primas'!$D$5:$D$45,MATCH(A6,'Matérias-Primas'!$A$5:$A$45,0)),0)) -> 15 | E6: =IF(A6="",0,C6*IFERROR(INDEX('Matérias-Primas'!$F$5:$F$45,MATCH(A6,'Matérias-Primas'!$A$5:$A$45,0)),0)) -> 5.58 | F6: =IF(A6="",0,C6*IFERROR(INDEX('Matérias-Primas'!$G$5:$G$45,MATCH(A6,'Matérias-Primas'!$A$5:$A$45,0)),0)) -> 0 | G6: =IF(A6="",0,C6*IFERROR(INDEX('Matérias-Primas'!$H$5:$H$45,MATCH(A6,'Matérias-Primas'!$A$5:$A$45,0)),0)) -> 2.772 | H6: =IF(A6="",0,C6*IFERROR(INDEX('Matérias-Primas'!$I$5:$I$45,MATCH(A6,'Matérias-Primas'!$A$5:$A$45,0)),0)) -> 1.236 | I6: =IF(A6="",0,C6*IFERROR(INDEX('Matérias-Primas'!$J$5:$J$45,MATCH(A6,'Matérias-Primas'!$A$5:$A$45,0)),0)) -> 0 | J6: =IF(A6="",0,C6*IFERROR(INDEX('Matérias-Primas'!$K$5:$K$45,MATCH(A6,'Matérias-Primas'!$A$5:$A$45,0)),0)) -> 0 | K6: =IF(A6="",0,C6*IFERROR(INDEX('Matérias-Primas'!$L$5:$L$45,MATCH(A6,'Matérias-Primas'!$A$5:$A$45,0)),0)) -> 2.412 | L6: =IF(A6="",0,C6*IFERROR(INDEX('Matérias-Primas'!$M$5:$M$45,MATCH(A6,'Matérias-Primas'!$A$5:$A$45,0)),0)) -> 0 | M6: =IF(A6="",0,C6*IFERROR(INDEX('Matérias-Primas'!$N$5:$N$45,MATCH(A6,'Matérias-Primas'!$A$5:$A$45,0)),0)) -> 0 | N6: =IF(A6="",0,C6*IFERROR(INDEX('Matérias-Primas'!$O$5:$O$45,MATCH(A6,'Matérias-Primas'!$A$5:$A$45,0)),0)) -> 0 | O6: =IF(A6="",0,C6*IFERROR(INDEX('Matérias-Primas'!$P$5:$P$45,MATCH(A6,'Matérias-Primas'!$A$5:$A$45,0)),0)) -> 0 | P6: =IF(A6="",0,C6*IFERROR(INDEX('Matérias-Primas'!$Q$5:$Q$45,MATCH(A6,'Matérias-Primas'!$A$5:$A$45,0)),0)) -> 0 | Q6: =IF(A6="",0,C6*IFERROR(INDEX('Matérias-Primas'!$R$5:$R$45,MATCH(A6,'Matérias-Primas'!$A$5:$A$45,0)),0)) -> 0
A7: Wollastonita | B7: 18 | C7: =IF(B7="","",B7/SUM($B$5:$B$14)) -> 0.18 | D7: =IF(A7="","",IFERROR(INDEX('Matérias-Primas'!$D$5:$D$45,MATCH(A7,'Matérias-Primas'!$A$5:$A$45,0)),0)) -> 8 | E7: =IF(A7="",0,C7*IFERROR(INDEX('Matérias-Primas'!$F$5:$F$45,MATCH(A7,'Matérias-Primas'!$A$5:$A$45,0)),0)) -> 9.306 | F7: =IF(A7="",0,C7*IFERROR(INDEX('Matérias-Primas'!$G$5:$G$45,MATCH(A7,'Matérias-Primas'!$A$5:$A$45,0)),0)) -> 0 | G7: =IF(A7="",0,C7*IFERROR(INDEX('Matérias-Primas'!$H$5:$H$45,MATCH(A7,'Matérias-Primas'!$A$5:$A$45,0)),0)) -> 0 | H7: =IF(A7="",0,C7*IFERROR(INDEX('Matérias-Primas'!$I$5:$I$45,MATCH(A7,'Matérias-Primas'!$A$5:$A$45,0)),0)) -> 0 | I7: =IF(A7="",0,C7*IFERROR(INDEX('Matérias-Primas'!$J$5:$J$45,MATCH(A7,'Matérias-Primas'!$A$5:$A$45,0)),0)) -> 0 | J7: =IF(A7="",0,C7*IFERROR(INDEX('Matérias-Primas'!$K$5:$K$45,MATCH(A7,'Matérias-Primas'!$A$5:$A$45,0)),0)) -> 0 | K7: =IF(A7="",0,C7*IFERROR(INDEX('Matérias-Primas'!$L$5:$L$45,MATCH(A7,'Matérias-Primas'!$A$5:$A$45,0)),0)) -> 8.694 | L7: =IF(A7="",0,C7*IFERROR(INDEX('Matérias-Primas'!$M$5:$M$45,MATCH(A7,'Matérias-Primas'!$A$5:$A$45,0)),0)) -> 0 | M7: =IF(A7="",0,C7*IFERROR(INDEX('Matérias-Primas'!$N$5:$N$45,MATCH(A7,'Matérias-Primas'!$A$5:$A$45,0)),0)) -> 0 | N7: =IF(A7="",0,C7*IFERROR(INDEX('Matérias-Primas'!$O$5:$O$45,MATCH(A7,'Matérias-Primas'!$A$5:$A$45,0)),0)) -> 0 | O7: =IF(A7="",0,C7*IFERROR(INDEX('Matérias-Primas'!$P$5:$P$45,MATCH(A7,'Matérias-Primas'!$A$5:$A$45,0)),0)) -> 0 | P7: =IF(A7="",0,C7*IFERROR(INDEX('Matérias-Primas'!$Q$5:$Q$45,MATCH(A7,'Matérias-Primas'!$A$5:$A$45,0)),0)) -> 0 | Q7: =IF(A7="",0,C7*IFERROR(INDEX('Matérias-Primas'!$R$5:$R$45,MATCH(A7,'Matérias-Primas'!$A$5:$A$45,0)),0)) -> 0
A8: Talco | B8: 5 | C8: =IF(B8="","",B8/SUM($B$5:$B$14)) -> 0.05 | D8: =IF(A8="","",IFERROR(INDEX('Matérias-Primas'!$D$5:$D$45,MATCH(A8,'Matérias-Primas'!$A$5:$A$45,0)),0)) -> 4 | E8: =IF(A8="",0,C8*IFERROR(INDEX('Matérias-Primas'!$F$5:$F$45,MATCH(A8,'Matérias-Primas'!$A$5:$A$45,0)),0)) -> 3.175 | F8: =IF(A8="",0,C8*IFERROR(INDEX('Matérias-Primas'!$G$5:$G$45,MATCH(A8,'Matérias-Primas'!$A$5:$A$45,0)),0)) -> 0 | G8: =IF(A8="",0,C8*IFERROR(INDEX('Matérias-Primas'!$H$5:$H$45,MATCH(A8,'Matérias-Primas'!$A$5:$A$45,0)),0)) -> 0 | H8: =IF(A8="",0,C8*IFERROR(INDEX('Matérias-Primas'!$I$5:$I$45,MATCH(A8,'Matérias-Primas'!$A$5:$A$45,0)),0)) -> 0 | I8: =IF(A8="",0,C8*IFERROR(INDEX('Matérias-Primas'!$J$5:$J$45,MATCH(A8,'Matérias-Primas'!$A$5:$A$45,0)),0)) -> 0 | J8: =IF(A8="",0,C8*IFERROR(INDEX('Matérias-Primas'!$K$5:$K$45,MATCH(A8,'Matérias-Primas'!$A$5:$A$45,0)),0)) -> 0 | K8: =IF(A8="",0,C8*IFERROR(INDEX('Matérias-Primas'!$L$5:$L$45,MATCH(A8,'Matérias-Primas'!$A$5:$A$45,0)),0)) -> 0 | L8: =IF(A8="",0,C8*IFERROR(INDEX('Matérias-Primas'!$M$5:$M$45,MATCH(A8,'Matérias-Primas'!$A$5:$A$45,0)),0)) -> 1.595 | M8: =IF(A8="",0,C8*IFERROR(INDEX('Matérias-Primas'!$N$5:$N$45,MATCH(A8,'Matérias-Primas'!$A$5:$A$45,0)),0)) -> 0 | N8: =IF(A8="",0,C8*IFERROR(INDEX('Matérias-Primas'!$O$5:$O$45,MATCH(A8,'Matérias-Primas'!$A$5:$A$45,0)),0)) -> 0 | O8: =IF(A8="",0,C8*IFERROR(INDEX('Matérias-Primas'!$P$5:$P$45,MATCH(A8,'Matérias-Primas'!$A$5:$A$45,0)),0)) -> 0 | P8: =IF(A8="",0,C8*IFERROR(INDEX('Matérias-Primas'!$Q$5:$Q$45,MATCH(A8,'Matérias-Primas'!$A$5:$A$45,0)),0)) -> 0 | Q8: =IF(A8="",0,C8*IFERROR(INDEX('Matérias-Primas'!$R$5:$R$45,MATCH(A8,'Matérias-Primas'!$A$5:$A$45,0)),0)) -> 0
A9: Caulim | B9: 10 | C9: =IF(B9="","",B9/SUM($B$5:$B$14)) -> 0.1 | D9: =IF(A9="","",IFERROR(INDEX('Matérias-Primas'!$D$5:$D$45,MATCH(A9,'Matérias-Primas'!$A$5:$A$45,0)),0)) -> 2.5 | E9: =IF(A9="",0,C9*IFERROR(INDEX('Matérias-Primas'!$F$5:$F$45,MATCH(A9,'Matérias-Primas'!$A$5:$A$45,0)),0)) -> 4.65 | F9: =IF(A9="",0,C9*IFERROR(INDEX('Matérias-Primas'!$G$5:$G$45,MATCH(A9,'Matérias-Primas'!$A$5:$A$45,0)),0)) -> 3.95 | G9: =IF(A9="",0,C9*IFERROR(INDEX('Matérias-Primas'!$H$5:$H$45,MATCH(A9,'Matérias-Primas'!$A$5:$A$45,0)),0)) -> 0 | H9: =IF(A9="",0,C9*IFERROR(INDEX('Matérias-Primas'!$I$5:$I$45,MATCH(A9,'Matérias-Primas'!$A$5:$A$45,0)),0)) -> 0 | I9: =IF(A9="",0,C9*IFERROR(INDEX('Matérias-Primas'!$J$5:$J$45,MATCH(A9,'Matérias-Primas'!$A$5:$A$45,0)),0)) -> 0 | J9: =IF(A9="",0,C9*IFERROR(INDEX('Matérias-Primas'!$K$5:$K$45,MATCH(A9,'Matérias-Primas'!$A$5:$A$45,0)),0)) -> 0 | K9: =IF(A9="",0,C9*IFERROR(INDEX('Matérias-Primas'!$L$5:$L$45,MATCH(A9,'Matérias-Primas'!$A$5:$A$45,0)),0)) -> 0 | L9: =IF(A9="",0,C9*IFERROR(INDEX('Matérias-Primas'!$M$5:$M$45,MATCH(A9,'Matérias-Primas'!$A$5:$A$45,0)),0)) -> 0 | M9: =IF(A9="",0,C9*IFERROR(INDEX('Matérias-Primas'!$N$5:$N$45,MATCH(A9,'Matérias-Primas'!$A$5:$A$45,0)),0)) -> 0 | N9: =IF(A9="",0,C9*IFERROR(INDEX('Matérias-Primas'!$O$5:$O$45,MATCH(A9,'Matérias-Primas'!$A$5:$A$45,0)),0)) -> 0 | O9: =IF(A9="",0,C9*IFERROR(INDEX('Matérias-Primas'!$P$5:$P$45,MATCH(A9,'Matérias-Primas'!$A$5:$A$45,0)),0)) -> 0 | P9: =IF(A9="",0,C9*IFERROR(INDEX('Matérias-Primas'!$Q$5:$Q$45,MATCH(A9,'Matérias-Primas'!$A$5:$A$45,0)),0)) -> 0.01 | Q9: =IF(A9="",0,C9*IFERROR(INDEX('Matérias-Primas'!$R$5:$R$45,MATCH(A9,'Matérias-Primas'!$A$5:$A$45,0)),0)) -> 0
A10: Quartzo (sílica 325#) | B10: 20 | C10: =IF(B10="","",B10/SUM($B$5:$B$14)) -> 0.2 | D10: =IF(A10="","",IFERROR(INDEX('Matérias-Primas'!$D$5:$D$45,MATCH(A10,'Matérias-Primas'!$A$5:$A$45,0)),0)) -> 2 | E10: =IF(A10="",0,C10*IFERROR(INDEX('Matérias-Primas'!$F$5:$F$45,MATCH(A10,'Matérias-Primas'!$A$5:$A$45,0)),0)) -> 20 | F10: =IF(A10="",0,C10*IFERROR(INDEX('Matérias-Primas'!$G$5:$G$45,MATCH(A10,'Matérias-Primas'!$A$5:$A$45,0)),0)) -> 0 | G10: =IF(A10="",0,C10*IFERROR(INDEX('Matérias-Primas'!$H$5:$H$45,MATCH(A10,'Matérias-Primas'!$A$5:$A$45,0)),0)) -> 0 | H10: =IF(A10="",0,C10*IFERROR(INDEX('Matérias-Primas'!$I$5:$I$45,MATCH(A10,'Matérias-Primas'!$A$5:$A$45,0)),0)) -> 0 | I10: =IF(A10="",0,C10*IFERROR(INDEX('Matérias-Primas'!$J$5:$J$45,MATCH(A10,'Matérias-Primas'!$A$5:$A$45,0)),0)) -> 0 | J10: =IF(A10="",0,C10*IFERROR(INDEX('Matérias-Primas'!$K$5:$K$45,MATCH(A10,'Matérias-Primas'!$A$5:$A$45,0)),0)) -> 0 | K10: =IF(A10="",0,C10*IFERROR(INDEX('Matérias-Primas'!$L$5:$L$45,MATCH(A10,'Matérias-Primas'!$A$5:$A$45,0)),0)) -> 0 | L10: =IF(A10="",0,C10*IFERROR(INDEX('Matérias-Primas'!$M$5:$M$45,MATCH(A10,'Matérias-Primas'!$A$5:$A$45,0)),0)) -> 0 | M10: =IF(A10="",0,C10*IFERROR(INDEX('Matérias-Primas'!$N$5:$N$45,MATCH(A10,'Matérias-Primas'!$A$5:$A$45,0)),0)) -> 0 | N10: =IF(A10="",0,C10*IFERROR(INDEX('Matérias-Primas'!$O$5:$O$45,MATCH(A10,'Matérias-Primas'!$A$5:$A$45,0)),0)) -> 0 | O10: =IF(A10="",0,C10*IFERROR(INDEX('Matérias-Primas'!$P$5:$P$45,MATCH(A10,'Matérias-Primas'!$A$5:$A$45,0)),0)) -> 0 | P10: =IF(A10="",0,C10*IFERROR(INDEX('Matérias-Primas'!$Q$5:$Q$45,MATCH(A10,'Matérias-Primas'!$A$5:$A$45,0)),0)) -> 0 | Q10: =IF(A10="",0,C10*IFERROR(INDEX('Matérias-Primas'!$R$5:$R$45,MATCH(A10,'Matérias-Primas'!$A$5:$A$45,0)),0)) -> 0
C11: =IF(B11="","",B11/SUM($B$5:$B$14)) | D11: =IF(A11="","",IFERROR(INDEX('Matérias-Primas'!$D$5:$D$45,MATCH(A11,'Matérias-Primas'!$A$5:$A$45,0)),0)) | E11: =IF(A11="",0,C11*IFERROR(INDEX('Matérias-Primas'!$F$5:$F$45,MATCH(A11,'Matérias-Primas'!$A$5:$A$45,0)),0)) -> 0 | F11: =IF(A11="",0,C11*IFERROR(INDEX('Matérias-Primas'!$G$5:$G$45,MATCH(A11,'Matérias-Primas'!$A$5:$A$45,0)),0)) -> 0 | G11: =IF(A11="",0,C11*IFERROR(INDEX('Matérias-Primas'!$H$5:$H$45,MATCH(A11,'Matérias-Primas'!$A$5:$A$45,0)),0)) -> 0 | H11: =IF(A11="",0,C11*IFERROR(INDEX('Matérias-Primas'!$I$5:$I$45,MATCH(A11,'Matérias-Primas'!$A$5:$A$45,0)),0)) -> 0 | I11: =IF(A11="",0,C11*IFERROR(INDEX('Matérias-Primas'!$J$5:$J$45,MATCH(A11,'Matérias-Primas'!$A$5:$A$45,0)),0)) -> 0 | J11: =IF(A11="",0,C11*IFERROR(INDEX('Matérias-Primas'!$K$5:$K$45,MATCH(A11,'Matérias-Primas'!$A$5:$A$45,0)),0)) -> 0 | K11: =IF(A11="",0,C11*IFERROR(INDEX('Matérias-Primas'!$L$5:$L$45,MATCH(A11,'Matérias-Primas'!$A$5:$A$45,0)),0)) -> 0 | L11: =IF(A11="",0,C11*IFERROR(INDEX('Matérias-Primas'!$M$5:$M$45,MATCH(A11,'Matérias-Primas'!$A$5:$A$45,0)),0)) -> 0 | M11: =IF(A11="",0,C11*IFERROR(INDEX('Matérias-Primas'!$N$5:$N$45,MATCH(A11,'Matérias-Primas'!$A$5:$A$45,0)),0)) -> 0 | N11: =IF(A11="",0,C11*IFERROR(INDEX('Matérias-Primas'!$O$5:$O$45,MATCH(A11,'Matérias-Primas'!$A$5:$A$45,0)),0)) -> 0 | O11: =IF(A11="",0,C11*IFERROR(INDEX('Matérias-Primas'!$P$5:$P$45,MATCH(A11,'Matérias-Primas'!$A$5:$A$45,0)),0)) -> 0 | P11: =IF(A11="",0,C11*IFERROR(INDEX('Matérias-Primas'!$Q$5:$Q$45,MATCH(A11,'Matérias-Primas'!$A$5:$A$45,0)),0)) -> 0 | Q11: =IF(A11="",0,C11*IFERROR(INDEX('Matérias-Primas'!$R$5:$R$45,MATCH(A11,'Matérias-Primas'!$A$5:$A$45,0)),0)) -> 0
C12: =IF(B12="","",B12/SUM($B$5:$B$14)) | D12: =IF(A12="","",IFERROR(INDEX('Matérias-Primas'!$D$5:$D$45,MATCH(A12,'Matérias-Primas'!$A$5:$A$45,0)),0)) | E12: =IF(A12="",0,C12*IFERROR(INDEX('Matérias-Primas'!$F$5:$F$45,MATCH(A12,'Matérias-Primas'!$A$5:$A$45,0)),0)) -> 0 | F12: =IF(A12="",0,C12*IFERROR(INDEX('Matérias-Primas'!$G$5:$G$45,MATCH(A12,'Matérias-Primas'!$A$5:$A$45,0)),0)) -> 0 | G12: =IF(A12="",0,C12*IFERROR(INDEX('Matérias-Primas'!$H$5:$H$45,MATCH(A12,'Matérias-Primas'!$A$5:$A$45,0)),0)) -> 0 | H12: =IF(A12="",0,C12*IFERROR(INDEX('Matérias-Primas'!$I$5:$I$45,MATCH(A12,'Matérias-Primas'!$A$5:$A$45,0)),0)) -> 0 | I12: =IF(A12="",0,C12*IFERROR(INDEX('Matérias-Primas'!$J$5:$J$45,MATCH(A12,'Matérias-Primas'!$A$5:$A$45,0)),0)) -> 0 | J12: =IF(A12="",0,C12*IFERROR(INDEX('Matérias-Primas'!$K$5:$K$45,MATCH(A12,'Matérias-Primas'!$A$5:$A$45,0)),0)) -> 0 | K12: =IF(A12="",0,C12*IFERROR(INDEX('Matérias-Primas'!$L$5:$L$45,MATCH(A12,'Matérias-Primas'!$A$5:$A$45,0)),0)) -> 0 | L12: =IF(A12="",0,C12*IFERROR(INDEX('Matérias-Primas'!$M$5:$M$45,MATCH(A12,'Matérias-Primas'!$A$5:$A$45,0)),0)) -> 0 | M12: =IF(A12="",0,C12*IFERROR(INDEX('Matérias-Primas'!$N$5:$N$45,MATCH(A12,'Matérias-Primas'!$A$5:$A$45,0)),0)) -> 0 | N12: =IF(A12="",0,C12*IFERROR(INDEX('Matérias-Primas'!$O$5:$O$45,MATCH(A12,'Matérias-Primas'!$A$5:$A$45,0)),0)) -> 0 | O12: =IF(A12="",0,C12*IFERROR(INDEX('Matérias-Primas'!$P$5:$P$45,MATCH(A12,'Matérias-Primas'!$A$5:$A$45,0)),0)) -> 0 | P12: =IF(A12="",0,C12*IFERROR(INDEX('Matérias-Primas'!$Q$5:$Q$45,MATCH(A12,'Matérias-Primas'!$A$5:$A$45,0)),0)) -> 0 | Q12: =IF(A12="",0,C12*IFERROR(INDEX('Matérias-Primas'!$R$5:$R$45,MATCH(A12,'Matérias-Primas'!$A$5:$A$45,0)),0)) -> 0
C13: =IF(B13="","",B13/SUM($B$5:$B$14)) | D13: =IF(A13="","",IFERROR(INDEX('Matérias-Primas'!$D$5:$D$45,MATCH(A13,'Matérias-Primas'!$A$5:$A$45,0)),0)) | E13: =IF(A13="",0,C13*IFERROR(INDEX('Matérias-Primas'!$F$5:$F$45,MATCH(A13,'Matérias-Primas'!$A$5:$A$45,0)),0)) -> 0 | F13: =IF(A13="",0,C13*IFERROR(INDEX('Matérias-Primas'!$G$5:$G$45,MATCH(A13,'Matérias-Primas'!$A$5:$A$45,0)),0)) -> 0 | G13: =IF(A13="",0,C13*IFERROR(INDEX('Matérias-Primas'!$H$5:$H$45,MATCH(A13,'Matérias-Primas'!$A$5:$A$45,0)),0)) -> 0 | H13: =IF(A13="",0,C13*IFERROR(INDEX('Matérias-Primas'!$I$5:$I$45,MATCH(A13,'Matérias-Primas'!$A$5:$A$45,0)),0)) -> 0 | I13: =IF(A13="",0,C13*IFERROR(INDEX('Matérias-Primas'!$J$5:$J$45,MATCH(A13,'Matérias-Primas'!$A$5:$A$45,0)),0)) -> 0 | J13: =IF(A13="",0,C13*IFERROR(INDEX('Matérias-Primas'!$K$5:$K$45,MATCH(A13,'Matérias-Primas'!$A$5:$A$45,0)),0)) -> 0 | K13: =IF(A13="",0,C13*IFERROR(INDEX('Matérias-Primas'!$L$5:$L$45,MATCH(A13,'Matérias-Primas'!$A$5:$A$45,0)),0)) -> 0 | L13: =IF(A13="",0,C13*IFERROR(INDEX('Matérias-Primas'!$M$5:$M$45,MATCH(A13,'Matérias-Primas'!$A$5:$A$45,0)),0)) -> 0 | M13: =IF(A13="",0,C13*IFERROR(INDEX('Matérias-Primas'!$N$5:$N$45,MATCH(A13,'Matérias-Primas'!$A$5:$A$45,0)),0)) -> 0 | N13: =IF(A13="",0,C13*IFERROR(INDEX('Matérias-Primas'!$O$5:$O$45,MATCH(A13,'Matérias-Primas'!$A$5:$A$45,0)),0)) -> 0 | O13: =IF(A13="",0,C13*IFERROR(INDEX('Matérias-Primas'!$P$5:$P$45,MATCH(A13,'Matérias-Primas'!$A$5:$A$45,0)),0)) -> 0 | P13: =IF(A13="",0,C13*IFERROR(INDEX('Matérias-Primas'!$Q$5:$Q$45,MATCH(A13,'Matérias-Primas'!$A$5:$A$45,0)),0)) -> 0 | Q13: =IF(A13="",0,C13*IFERROR(INDEX('Matérias-Primas'!$R$5:$R$45,MATCH(A13,'Matérias-Primas'!$A$5:$A$45,0)),0)) -> 0
C14: =IF(B14="","",B14/SUM($B$5:$B$14)) | D14: =IF(A14="","",IFERROR(INDEX('Matérias-Primas'!$D$5:$D$45,MATCH(A14,'Matérias-Primas'!$A$5:$A$45,0)),0)) | E14: =IF(A14="",0,C14*IFERROR(INDEX('Matérias-Primas'!$F$5:$F$45,MATCH(A14,'Matérias-Primas'!$A$5:$A$45,0)),0)) -> 0 | F14: =IF(A14="",0,C14*IFERROR(INDEX('Matérias-Primas'!$G$5:$G$45,MATCH(A14,'Matérias-Primas'!$A$5:$A$45,0)),0)) -> 0 | G14: =IF(A14="",0,C14*IFERROR(INDEX('Matérias-Primas'!$H$5:$H$45,MATCH(A14,'Matérias-Primas'!$A$5:$A$45,0)),0)) -> 0 | H14: =IF(A14="",0,C14*IFERROR(INDEX('Matérias-Primas'!$I$5:$I$45,MATCH(A14,'Matérias-Primas'!$A$5:$A$45,0)),0)) -> 0 | I14: =IF(A14="",0,C14*IFERROR(INDEX('Matérias-Primas'!$J$5:$J$45,MATCH(A14,'Matérias-Primas'!$A$5:$A$45,0)),0)) -> 0 | J14: =IF(A14="",0,C14*IFERROR(INDEX('Matérias-Primas'!$K$5:$K$45,MATCH(A14,'Matérias-Primas'!$A$5:$A$45,0)),0)) -> 0 | K14: =IF(A14="",0,C14*IFERROR(INDEX('Matérias-Primas'!$L$5:$L$45,MATCH(A14,'Matérias-Primas'!$A$5:$A$45,0)),0)) -> 0 | L14: =IF(A14="",0,C14*IFERROR(INDEX('Matérias-Primas'!$M$5:$M$45,MATCH(A14,'Matérias-Primas'!$A$5:$A$45,0)),0)) -> 0 | M14: =IF(A14="",0,C14*IFERROR(INDEX('Matérias-Primas'!$N$5:$N$45,MATCH(A14,'Matérias-Primas'!$A$5:$A$45,0)),0)) -> 0 | N14: =IF(A14="",0,C14*IFERROR(INDEX('Matérias-Primas'!$O$5:$O$45,MATCH(A14,'Matérias-Primas'!$A$5:$A$45,0)),0)) -> 0 | O14: =IF(A14="",0,C14*IFERROR(INDEX('Matérias-Primas'!$P$5:$P$45,MATCH(A14,'Matérias-Primas'!$A$5:$A$45,0)),0)) -> 0 | P14: =IF(A14="",0,C14*IFERROR(INDEX('Matérias-Primas'!$Q$5:$Q$45,MATCH(A14,'Matérias-Primas'!$A$5:$A$45,0)),0)) -> 0 | Q14: =IF(A14="",0,C14*IFERROR(INDEX('Matérias-Primas'!$R$5:$R$45,MATCH(A14,'Matérias-Primas'!$A$5:$A$45,0)),0)) -> 0
A15: Total | B15: =SUM(B5:B14) -> 100 | C15: =SUM(C5:C14) -> 1 | E15: =SUM(E5:E14) -> 66.161 | F15: =SUM(F5:F14) -> 10.425 | G15: =SUM(G5:G14) -> 2.772 | H15: =SUM(H5:H14) -> 2.286 | I15: =SUM(I5:I14) -> 3.85 | J15: =SUM(J5:J14) -> 0 | K15: =SUM(K5:K14) -> 11.176 | L15: =SUM(L5:L14) -> 1.595 | ... Q15: =SUM(Q5:Q14) -> 0
A16: Massa molar | E16: ='Matérias-Primas'!F3 -> 60.08 | F16: ='Matérias-Primas'!G3 -> 101.96 | G16: ='Matérias-Primas'!H3 -> 69.62 | H16: ='Matérias-Primas'!I3 -> 61.98 | I16: ='Matérias-Primas'!J3 -> 94.2 | J16: ='Matérias-Primas'!K3 -> 29.88 | K16: ='Matérias-Primas'!L3 -> 56.08 | L16: ='Matérias-Primas'!M3 -> 40.3 | ... Q16: ='Matérias-Primas'!R3 -> 79.87
A17: Mols | C17: Soma fundentes: | D17: =H17+I17+J17+K17+L17+M17+N17 -> 0.31661825 | E17: =E15/E16 -> 1.101215 | F17: =F15/F16 -> 0.10224598 | G17: =G15/G16 -> 0.039816145 | H17: =H15/H16 -> 0.036882865 | I17: =I15/I16 -> 0.040870488 | J17: =J15/J16 -> 0 | K17: =K15/K16 -> 0.19928673 | L17: =L15/L16 -> 0.039578164 | ... Q17: =Q15/Q16 -> 0
A18: UMF (fundentes = 1) | E18: =IF($D$17=0,0,E17/$D$17) -> 3.478053 | F18: =IF($D$17=0,0,F17/$D$17) -> 0.32293141 | G18: =IF($D$17=0,0,G17/$D$17) -> 0.12575442 | H18: =IF($D$17=0,0,H17/$D$17) -> 0.11649002 | I18: =IF($D$17=0,0,I17/$D$17) -> 0.12908444 | J18: =IF($D$17=0,0,J17/$D$17) -> 0 | K18: =IF($D$17=0,0,K17/$D$17) -> 0.62942276 | L18: =IF($D$17=0,0,L17/$D$17) -> 0.12500279 | ... Q18: =IF($D$17=0,0,Q17/$D$17) -> 0
A20: Checagem contra faixas-alvo
A21: Indicador | B21: Valor | C21: Mín | D21: Máx | E21: Status
A22: SiO₂ (UMF) | B22: =E18 -> 3.478053 | C22: 3 | D22: 4 | E22: =IF(AND(B22>=C22,B22<=D22),"OK","Ajustar") -> OK
A23: Al₂O₃ (UMF) | B23: =F18 -> 0.32293141 | C23: 0.28 | D23: 0.38 | E23: =IF(AND(B23>=C23,B23<=D23),"OK","Ajustar") -> OK
A24: B₂O₃ (UMF) | B24: =G18 -> 0.12575442 | C24: 0.1 | D24: 0.25 | E24: =IF(AND(B24>=C24,B24<=D24),"OK","Ajustar") -> OK
A25: Razão SiO₂:Al₂O₃ | B25: =IF(F18=0,0,E18/F18) -> 10.770253 | C25: 8 | D25: 11 | E25: =IF(AND(B25>=C25,B25<=D25),"OK","Ajustar") -> OK
A27: Custo matéria-prima da base (R$/kg) | B27: =SUMPRODUCT(C5:C14,D5:D14) -> 5.315
A28: Faixas-alvo são referências de literatura para cone 6 estável; ajuste-as conforme seus testes. Fórmula-alvo calculada sobre óxidos; colorantes entram na aba Cores.

Sheet Cores
A1: Linha de 17 cores — cone 6 oxidação
A2: Colorantes em % adicionados sobre 100% da base seca. Valores = ponto de partida para teste.
A4: Nº | B4: Nome | C4: Base | D4: Colorante 1 | E4: % 1 | F4: Colorante 2 | G4: % 2 | H4: Colorante 3 | I4: % 3 | J4: Resfr. lento? | K4: Alimentos? | L4: Custo base (R$/kg) | M4: Custo colorantes (R$ por 100 g base) | N4: Custo MP (R$/kg esmalte) | O4: Observações
A5: 1 | B5: Transparente brilhante | C5: A | J5: Não necessário | K5: Pendente lixiviação | L5: =IFERROR(CHOOSE(MATCH(C5,{"A","B","C","D","E"},0),'Base A'!$B$27,'Base B'!$B$27,'Base C'!$B$27,'Base D'!$B$27,'Base E'!$B$27),0) -> 6.2 | M5: =IF(D5="",0,N(E5)/100*IFERROR(INDEX('Matérias-Primas'!$D$5:$D$45,MATCH(D5,'Matérias-Primas'!$A$5:$A$45,0)),0))+IF(F5="",0,N(G5)/100*IFERROR(INDEX('Matérias-Primas'!$D$5:$D$45,MATCH(F5,'Matérias-Primas'!$A$5:$A$45,0)),0))+IF(H5="",0,N(I5)/100*IFERROR(INDEX('Matérias-Primas'!$D$5:$D$45,MATCH(H5,'Matérias-Primas'!$A$5:$A$45,0)),0)) -> 0 | N5: =(L5+M5)/(1+(N(E5)+N(G5)+N(I5))/100) -> 6.2 | O5: Base de referência
A6: 2 | B6: Transparente mate | C6: B | J6: Recomendado | K6: Pendente lixiviação | L6: =IFERROR(CHOOSE(MATCH(C6,{"A","B","C","D","E"},0),'Base A'!$B$27,'Base B'!$B$27,'Base C'!$B$27,'Base D'!$B$27,'Base E'!$B$27),0) -> 5.455 | M6: =IF(D6="",0,N(E6)/100*IFERROR(INDEX('Matérias-Primas'!$D$5:$D$45,MATCH(D6,'Matérias-Primas'!$A$5:$A$45,0)),0))+IF(F6="",0,N(G6)/100*IFERROR(INDEX('Matérias-Primas'!$D$5:$D$45,MATCH(F6,'Matérias-Primas'!$A$5:$A$45,0)),0))+IF(H6="",0,N(I6)/100*IFERROR(INDEX('Matérias-Primas'!$D$5:$D$45,MATCH(H6,'Matérias-Primas'!$A$5:$A$45,0)),0)) -> 0 | N6: =(L6+M6)/(1+(N(E6)+N(G6)+N(I6))/100) -> 5.455 | O6: Mate cálcico
A7: 3 | B7: Branco brilhante | C7: C | D7: Silicato de zircônio | E7: 10 | J7: Não necessário | K7: Pendente lixiviação | L7: =IFERROR(CHOOSE(MATCH(C7,{"A","B","C","D","E"},0),'Base A'!$B$27,'Base B'!$B$27,'Base C'!$B$27,'Base D'!$B$27,'Base E'!$B$27),0) -> 8.69 | M7: =IF(D7="",0,N(E7)/100*IFERROR(INDEX('Matérias-Primas'!$D$5:$D$45,MATCH(D7,'Matérias-Primas'!$A$5:$A$45,0)),0))+IF(F7="",0,N(G7)/100*IFERROR(INDEX('Matérias-Primas'!$D$5:$D$45,MATCH(F7,'Matérias-Primas'!$A$5:$A$45,0)),0))+IF(H7="",0,N(I7)/100*IFERROR(INDEX('Matérias-Primas'!$D$5:$D$45,MATCH(H7,'Matérias-Primas'!$A$5:$A$45,0)),0)) -> 2.5 | N7: =(L7+M7)/(1+(N(E7)+N(G7)+N(I7))/100) -> 10.172727
A8: 4 | B8: Branco acetinado | C8: B | D8: Silicato de zircônio | E8: 8 | J8: Recomendado | K8: Pendente lixiviação | L8: =IFERROR(CHOOSE(MATCH(C8,{"A","B","C","D","E"},0),'Base A'!$B$27,'Base B'!$B$27,'Base C'!$B$27,'Base D'!$B$27,'Base E'!$B$27),0) -> 5.455 | M8: =IF(D8="",0,N(E8)/100*IFERROR(INDEX('Matérias-Primas'!$D$5:$D$45,MATCH(D8,'Matérias-Primas'!$A$5:$A$45,0)),0))+IF(F8="",0,N(G8)/100*IFERROR(INDEX('Matérias-Primas'!$D$5:$D$45,MATCH(F8,'Matérias-Primas'!$A$5:$A$45,0)),0))+IF(H8="",0,N(I8)/100*IFERROR(INDEX('Matérias-Primas'!$D$5:$D$45,MATCH(H8,'Matérias-Primas'!$A$5:$A$45,0)),0)) -> 2 | N8: =(L8+M8)/(1+(N(E8)+N(G8)+N(I8))/100) -> 6.9027778
A9: 5 | B9: Preto brilhante | C9: A | D9: Pigmento preto | E9: 7 | J9: Não necessário | K9: Pendente lixiviação | L9: =IFERROR(CHOOSE(MATCH(C9,{"A","B","C","D","E"},0),'Base A'!$B$27,'Base B'!$B$27,'Base C'!$B$27,'Base D'!$B$27,'Base E'!$B$27),0) -> 6.2 | M9: =IF(D9="",0,N(E9)/100*IFERROR(INDEX('Matérias-Primas'!$D$5:$D$45,MATCH(D9,'Matérias-Primas'!$A$5:$A$45,0)),0))+IF(F9="",0,N(G9)/100*IFERROR(INDEX('Matérias-Primas'!$D$5:$D$45,MATCH(F9,'Matérias-Primas'!$A$5:$A$45,0)),0))+IF(H9="",0,N(I9)/100*IFERROR(INDEX('Matérias-Primas'!$D$5:$D$45,MATCH(H9,'Matérias-Primas'!$A$5:$A$45,0)),0)) -> 17.5 | N9: =(L9+M9)/(1+(N(E9)+N(G9)+N(I9))/100) -> 22.149533 | O9: Alternativa: Fe + Co + Mn
A10: 6 | B10: Tenmoku | C10: E | D10: Óxido de ferro vermelho | E10: 10 | J10: Recomendado | K10: Pendente lixiviação | L10: =IFERROR(CHOOSE(MATCH(C10,{"A","B","C","D","E"},0),'Base A'!$B$27,'Base B'!$B$27,'Base C'!$B$27,'Base D'!$B$27,'Base E'!$B$27),0) -> 5.315 | M10: =IF(D10="",0,N(E10)/100*IFERROR(INDEX('Matérias-Primas'!$D$5:$D$45,MATCH(D10,'Matérias-Primas'!$A$5:$A$45,0)),0))+IF(F10="",0,N(G10)/100*IFERROR(INDEX('Matérias-Primas'!$D$5:$D$45,MATCH(F10,'Matérias-Primas'!$A$5:$A$45,0)),0))+IF(H10="",0,N(I10)/100*IFERROR(INDEX('Matérias-Primas'!$D$5:$D$45,MATCH(H10,'Matérias-Primas'!$A$5:$A$45,0)),0)) -> 2 | N10: =(L10+M10)/(1+(N(E10)+N(G10)+N(I10))/100) -> 6.65 | O10: Quebra marrom nas bordas
A11: 7 | B11: Celadon verde | C11: A | D11: Óxido de ferro vermelho | E11: 1.5 | J11: Não necessário | K11: Pendente lixiviação | L11: =IFERROR(CHOOSE(MATCH(C11,{"A","B","C","D","E"},0),'Base A'!$B$27,'Base B'!$B$27,'Base C'!$B$27,'Base D'!$B$27,'Base E'!$B$27),0) -> 6.2 | M11: =IF(D11="",0,N(E11)/100*IFERROR(INDEX('Matérias-Primas'!$D$5:$D$45,MATCH(D11,'Matérias-Primas'!$A$5:$A$45,0)),0))+IF(F11="",0,N(G11)/100*IFERROR(INDEX('Matérias-Primas'!$D$5:$D$45,MATCH(F11,'Matérias-Primas'!$A$5:$A$45,0)),0))+IF(H11="",0,N(I11)/100*IFERROR(INDEX('Matérias-Primas'!$D$5:$D$45,MATCH(H11,'Matérias-Primas'!$A$5:$A$45,0)),0)) -> 0.3 | N11: =(L11+M11)/(1+(N(E11)+N(G11)+N(I11))/100) -> 6.4039409 | O11: Em oxidação fica verde-amarelado; teste 1–2%
A12: 8 | B12: Celadon azul | C12: A | D12: Óxido de ferro vermelho | E12: 1 | F12: Carbonato de cobalto | G12: 0.1 | J12: Não necessário | K12: Pendente lixiviação | L12: =IFERROR(CHOOSE(MATCH(C12,{"A","B","C","D","E"},0),'Base A'!$B$27,'Base B'!$B$27,'Base C'!$B$27,'Base D'!$B$27,'Base E'!$B$27),0) -> 6.2 | M12: =IF(D12="",0,N(E12)/100*IFERROR(INDEX('Matérias-Primas'!$D$5:$D$45,MATCH(D12,'Matérias-Primas'!$A$5:$A$45,0)),0))+IF(F12="",0,N(G12)/100*IFERROR(INDEX('Matérias-Primas'!$D$5:$D$45,MATCH(F12,'Matérias-Primas'!$A$5:$A$45,0)),0))+IF(H12="",0,N(I12)/100*IFERROR(INDEX('Matérias-Primas'!$D$5:$D$45,MATCH(H12,'Matérias-Primas'!$A$5:$A$45,0)),0)) -> 1.1 | N12: =(L12+M12)/(1+(N(E12)+N(G12)+N(I12))/100) -> 7.2205737
A13: 9 | B13: Rutilo mel | C13: D | D13: Rutilo | E13: 6 | F13: Óxido de ferro vermelho | G13: 2 | J13: Sim | K13: Pendente lixiviação | L13: =IFERROR(CHOOSE(MATCH(C13,{"A","B","C","D","E"},0),'Base A'!$B$27,'Base B'!$B$27,'Base C'!$B$27,'Base D'!$B$27,'Base E'!$B$27),0) -> 9.335 | M13: =IF(D13="",0,N(E13)/100*IFERROR(INDEX('Matérias-Primas'!$D$5:$D$45,MATCH(D13,'Matérias-Primas'!$A$5:$A$45,0)),0))+IF(F13="",0,N(G13)/100*IFERROR(INDEX('Matérias-Primas'!$D$5:$D$45,MATCH(F13,'Matérias-Primas'!$A$5:$A$45,0)),0))+IF(H13="",0,N(I13)/100*IFERROR(INDEX('Matérias-Primas'!$D$5:$D$45,MATCH(H13,'Matérias-Primas'!$A$5:$A$45,0)),0)) -> 5.2 | N13: =(L13+M13)/(1+(N(E13)+N(G13)+N(I13))/100) -> 13.458333 | O13: Variegação depende da espessura
A14: 10 | B14: Creme pintalgado | C14: D | D14: Silicato de zircônio | E14: 4 | F14: Rutilo | G14: 2 | H14: Ilmenita granular | I14: 0.75 | J14: Sim | K14: Pendente lixiviação | L14: =IFERROR(CHOOSE(MATCH(C14,{"A","B","C","D","E"},0),'Base A'!$B$27,'Base B'!$B$27,'Base C'!$B$27,'Base D'!$B$27,'Base E'!$B$27),0) -> 9.335 | M14: =IF(D14="",0,N(E14)/100*IFERROR(INDEX('Matérias-Primas'!$D$5:$D$45,MATCH(D14,'Matérias-Primas'!$A$5:$A$45,0)),0))+IF(F14="",0,N(G14)/100*IFERROR(INDEX('Matérias-Primas'!$D$5:$D$45,MATCH(F14,'Matérias-Primas'!$A$5:$A$45,0)),0))+IF(H14="",0,N(I14)/100*IFERROR(INDEX('Matérias-Primas'!$D$5:$D$45,MATCH(H14,'Matérias-Primas'!$A$5:$A$45,0)),0)) -> 3.05 | N14: =(L14+M14)/(1+(N(E14)+N(G14)+N(I14))/100) -> 11.601874 | O14: Substitui o shino (que exige redução)
A15: 11 | B15: Azul cobalto | C15: A | D15: Carbonato de cobalto | E15: 1 | J15: Não necessário | K15: Pendente lixiviação | L15: =IFERROR(CHOOSE(MATCH(C15,{"A","B","C","D","E"},0),'Base A'!$B$27,'Base B'!$B$27,'Base C'!$B$27,'Base D'!$B$27,'Base E'!$B$27),0) -> 6.2 | M15: =IF(D15="",0,N(E15)/100*IFERROR(INDEX('Matérias-Primas'!$D$5:$D$45,MATCH(D15,'Matérias-Primas'!$A$5:$A$45,0)),0))+IF(F15="",0,N(G15)/100*IFERROR(INDEX('Matérias-Primas'!$D$5:$D$45,MATCH(F15,'Matérias-Primas'!$A$5:$A$45,0)),0))+IF(H15="",0,N(I15)/100*IFERROR(INDEX('Matérias-Primas'!$D$5:$D$45,MATCH(H15,'Matérias-Primas'!$A$5:$A$45,0)),0)) -> 9 | N15: =(L15+M15)/(1+(N(E15)+N(G15)+N(I15))/100) -> 15.049505
A16: 12 | B16: Turquesa | C16: C | D16: Carbonato de cobre | E16: 2.5 | J16: Não necessário | K16: Pendente lixiviação | L16: =IFERROR(CHOOSE(MATCH(C16,{"A","B","C","D","E"},0),'Base A'!$B$27,'Base B'!$B$27,'Base C'!$B$27,'Base D'!$B$27,'Base E'!$B$27),0) -> 8.69 | M16: =IF(D16="",0,N(E16)/100*IFERROR(INDEX('Matérias-Primas'!$D$5:$D$45,MATCH(D16,'Matérias-Primas'!$A$5:$A$45,0)),0))+IF(F16="",0,N(G16)/100*IFERROR(INDEX('Matérias-Primas'!$D$5:$D$45,MATCH(F16,'Matérias-Primas'!$A$5:$A$45,0)),0))+IF(H16="",0,N(I16)/100*IFERROR(INDEX('Matérias-Primas'!$D$5:$D$45,MATCH(H16,'Matérias-Primas'!$A$5:$A$45,0)),0)) -> 3.75 | N16: =(L16+M16)/(1+(N(E16)+N(G16)+N(I16))/100) -> 12.136585 | O16: Cobre: maior risco de lixiviação — testar antes de vender para louça
A17: 13 | B17: Amarelo | C17: A | D17: Pigmento amarelo Zr-Pr | E17: 8 | J17: Não necessário | K17: Pendente lixiviação | L17: =IFERROR(CHOOSE(MATCH(C17,{"A","B","C","D","E"},0),'Base A'!$B$27,'Base B'!$B$27,'Base C'!$B$27,'Base D'!$B$27,'Base E'!$B$27),0) -> 6.2 | M17: =IF(D17="",0,N(E17)/100*IFERROR(INDEX('Matérias-Primas'!$D$5:$D$45,MATCH(D17,'Matérias-Primas'!$A$5:$A$45,0)),0))+IF(F17="",0,N(G17)/100*IFERROR(INDEX('Matérias-Primas'!$D$5:$D$45,MATCH(F17,'Matérias-Primas'!$A$5:$A$45,0)),0))+IF(H17="",0,N(I17)/100*IFERROR(INDEX('Matérias-Primas'!$D$5:$D$45,MATCH(H17,'Matérias-Primas'!$A$5:$A$45,0)),0)) -> 20 | N17: =(L17+M17)/(1+(N(E17)+N(G17)+N(I17))/100) -> 24.259259
A18: 14 | B18: Rosa coral | C18: B | D18: Pigmento rosa Cr-Sn | E18: 6 | J18: Recomendado | K18: Pendente lixiviação | L18: =IFERROR(CHOOSE(MATCH(C18,{"A","B","C","D","E"},0),'Base A'!$B$27,'Base B'!$B$27,'Base C'!$B$27,'Base D'!$B$27,'Base E'!$B$27),0) -> 5.455 | M18: =IF(D18="",0,N(E18)/100*IFERROR(INDEX('Matérias-Primas'!$D$5:$D$45,MATCH(D18,'Matérias-Primas'!$A$5:$A$45,0)),0))+IF(F18="",0,N(G18)/100*IFERROR(INDEX('Matérias-Primas'!$D$5:$D$45,MATCH(F18,'Matérias-Primas'!$A$5:$A$45,0)),0))+IF(H18="",0,N(I18)/100*IFERROR(INDEX('Matérias-Primas'!$D$5:$D$45,MATCH(H18,'Matérias-Primas'!$A$5:$A$45,0)),0)) -> 21 | N18: =(L18+M18)/(1+(N(E18)+N(G18)+N(I18))/100) -> 24.957547 | O18: Base precisa de cálcio e ZERO zinco
A19: 15 | B19: Ferrugem | C19: E | D19: Óxido de ferro vermelho | E19: 7 | J19: Sim | K19: Pendente lixiviação | L19: =IFERROR(CHOOSE(MATCH(C19,{"A","B","C","D","E"},0),'Base A'!$B$27,'Base B'!$B$27,'Base C'!$B$27,'Base D'!$B$27,'Base E'!$B$27),0) -> 5.315 | M19: =IF(D19="",0,N(E19)/100*IFERROR(INDEX('Matérias-Primas'!$D$5:$D$45,MATCH(D19,'Matérias-Primas'!$A$5:$A$45,0)),0))+IF(F19="",0,N(G19)/100*IFERROR(INDEX('Matérias-Primas'!$D$5:$D$45,MATCH(F19,'Matérias-Primas'!$A$5:$A$45,0)),0))+IF(H19="",0,N(I19)/100*IFERROR(INDEX('Matérias-Primas'!$D$5:$D$45,MATCH(H19,'Matérias-Primas'!$A$5:$A$45,0)),0)) -> 1.4 | N19: =(L19+M19)/(1+(N(E19)+N(G19)+N(I19))/100) -> 6.2757009 | O19: Superfície saturada de ferro
A20: 16 | B20: Azul flutuante | C20: D | D20: Rutilo | E20: 4 | F20: Óxido de ferro vermelho | G20: 2 | H20: Carbonato de cobalto | I20: 1 | J20: Sim | K20: Pendente lixiviação | L20: =IFERROR(CHOOSE(MATCH(C20,{"A","B","C","D","E"},0),'Base A'!$B$27,'Base B'!$B$27,'Base C'!$B$27,'Base D'!$B$27,'Base E'!$B$27),0) -> 9.335 | M20: =IF(D20="",0,N(E20)/100*IFERROR(INDEX('Matérias-Primas'!$D$5:$D$45,MATCH(D20,'Matérias-Primas'!$A$5:$A$45,0)),0))+IF(F20="",0,N(G20)/100*IFERROR(INDEX('Matérias-Primas'!$D$5:$D$45,MATCH(F20,'Matérias-Primas'!$A$5:$A$45,0)),0))+IF(H20="",0,N(I20)/100*IFERROR(INDEX('Matérias-Primas'!$D$5:$D$45,MATCH(H20,'Matérias-Primas'!$A$5:$A$45,0)),0)) -> 12.6 | N20: =(L20+M20)/(1+(N(E20)+N(G20)+N(I20))/100) -> 20.5 | O20: Floating blue; escorre se grosso
A21: 17 | B21: Imitação de cinza | C21: D | D21: Rutilo | E21: 3 | F21: Óxido de ferro vermelho | G21: 1.5 | H21: Silicato de zircônio | I21: 2 | J21: Sim | K21: Pendente lixiviação | L21: =IFERROR(CHOOSE(MATCH(C21,{"A","B","C","D","E"},0),'Base A'!$B$27,'Base B'!$B$27,'Base C'!$B$27,'Base D'!$B$27,'Base E'!$B$27),0) -> 9.335 | M21: =IF(D21="",0,N(E21)/100*IFERROR(INDEX('Matérias-Primas'!$D$5:$D$45,MATCH(D21,'Matérias-Primas'!$A$5:$A$45,0)),0))+IF(F21="",0,N(G21)/100*IFERROR(INDEX('Matérias-Primas'!$D$5:$D$45,MATCH(F21,'Matérias-Primas'!$A$5:$A$45,0)),0))+IF(H21="",0,N(I21)/100*IFERROR(INDEX('Matérias-Primas'!$D$5:$D$45,MATCH(H21,'Matérias-Primas'!$A$5:$A$45,0)),0)) -> 3.2 | N21: =(L21+M21)/(1+(N(E21)+N(G21)+N(I21))/100) -> 11.769953 | O21: Efeito ash sem cinza real
A23: Custo colorantes = Σ (% colorante/100 × preço R$/kg), em R$ por kg de base. Custo MP por kg de esmalte = (custo base + custo colorantes) ÷ (1 + Σ%/100).

Sheet Pincel
A1: Fase 1 — Esmalte líquido para pincel
A2: Receita de suspensão aplicada a qualquer cor: esmalte seco + água + aditivos. Valores de partida — ajuste nos testes.
A4: Parâmetro | B4: Valor | C4: Observação
A5: Densidade alvo do líquido (g/ml) | B5: 1.55 | C5: Pincel: 1,50–1,65. Meça com proveta de 100 ml e balança.
A6: Densidade do esmalte seco (g/cm³) | B6: 2.6 | C6: Típico de esmaltes; mantenha 2,6 se não medir.
A7: Teor de sólidos (% em massa) | B7: =(1-1/B5)/(1-1/B6) -> 0.5766129 | C7: Calculado a partir das densidades
A8: Esmalte seco por litro (kg/L) | B8: =B5*B7 -> 0.89375 | C8: Quanto pó vai em cada litro
A11: Aditivo | B11: % sobre esmalte seco | C11: Preço (R$/kg) | D11: Custo (R$/kg de esmalte seco) | E11: Função
A12: Goma CMC | B12: 1 | C12: =IFERROR(INDEX('Matérias-Primas'!$D$5:$D$45,MATCH(A12,'Matérias-Primas'!$A$5:$A$45,0)),0) -> 60 | D12: =N(B12)/100*C12 -> 0.6 | E12: Ligante: pincelada lisa, adere sem esfarelar; dá "corpo"
A13: Bentonita | B13: 1.5 | C13: =IFERROR(INDEX('Matérias-Primas'!$D$5:$D$45,MATCH(A13,'Matérias-Primas'!$A$5:$A$45,0)),0) -> 8 | D13: =N(B13)/100*C13 -> 0.12 | E13: Suspensão: evita sedimento duro no pote
A14: Glicerina | B14: 3 | C14: =IFERROR(INDEX('Matérias-Primas'!$D$5:$D$45,MATCH(A14,'Matérias-Primas'!$A$5:$A$45,0)),0) -> 20 | D14: =N(B14)/100*C14 -> 0.6 | E14: Retarda a secagem: pincelada sem marcas
A15: Silicato de sódio | B15: 0.1 | C15: =IFERROR(INDEX('Matérias-Primas'!$D$5:$D$45,MATCH(A15,'Matérias-Primas'!$A$5:$A$45,0)),0) -> 10 | D15: =N(B15)/100*C15 -> 0.01 | E15: Defloculante: permite densidade alta com fluidez
A16: Conservante (isotiazolinona) | B16: 0.2 | C16: =IFERROR(INDEX('Matérias-Primas'!$D$5:$D$45,MATCH(A16,'Matérias-Primas'!$A$5:$A$45,0)),0) -> 80 | D16: =N(B16)/100*C16 -> 0.16 | E16: Evita mofo/odor da CMC no pote
A17: Total aditivos | D17: =SUM(D12:D16) -> 1.49
A19: Preparo sugerido (por lote)
A20: 1. Hidrate a CMC em parte da água quente na véspera (gel sem grumos) e misture o conservante.
A21: 2. Disperse a bentonita na água restante, com misturador de alta rotação.
A22: 3. Adicione o esmalte seco (base + colorantes) aos poucos; passe na peneira 120 mesh.
A23: 4. Junte o gel de CMC e a glicerina; corrija a densidade com água até o valor-alvo.
A24: 5. Descanse 24 h, meça densidade de novo e envase. Guarde um pote de cada lote como contraprova.
A25: Rótulo: "Aplicar 3 demãos cruzadas, secando entre elas. Cone 6 (1220–1240 °C)." Leve a FDS dos aditivos para a FDS do produto.

Sheet Custos e Preço
A1: Custo total e preço — Fase 1 (pincel) e Fase 2 (pó para mergulho)
A2: Todas as premissas em amarelo são estimativas ilustrativas — substitua pelas suas.
A4: Premissa | B4: Valor
A5: FASE 1 — Pincel
A6: Volume do pote pequeno (ml) | B6: 100
A7: Volume do pote grande (ml) | B7: 250
A8: Embalagem pote pequeno (pote + tampa + rótulo + lacre) — R$/un | B8: 3.5
A9: Embalagem pote grande — R$/un | B9: 5
A10: Mão de obra (preparo + envase) — R$/L | B10: 10
A11: Energia, QC e rateio de testes — R$/L | B11: 4
A12: Preço de venda praticado — pote pequeno (pesquise o mercado) | B12: 34.9
A13: Preço de venda praticado — pote grande (pesquise o mercado) | B13: 69.9
A14: FASE 2 — Pó para mergulho
A15: Embalagem 500 g — R$/un | B15: 4.5
A16: Embalagem 1 kg — R$/un | B16: 6.5
A17: Mão de obra pó — R$/kg | B17: 8
A18: Energia, QC e rateio de testes pó — R$/kg | B18: 3
A19: COMUNS
A20: Perdas de processo (% sobre MP) | B20: 0.1
A21: Impostos sobre venda (Simples Nacional, %) | B21: 0.06
A22: Taxa do canal (marketplace/cartão, %) | B22: 0.15
A23: Margem de lucro desejada (% sobre preço) | B23: 0.3
A24: Preço mínimo = custo ÷ (1 − impostos − taxa − margem desejada). Margem real = (preço praticado × (1 − impostos − taxa) − custo) ÷ preço praticado. Vermelho = abaixo da margem desejada.
A25: FASE 1 — Esmalte líquido para pincel
A26: Nº | B26: Cor | C26: MP (R$/kg seco) | D26: Custo por litro (R$/L) | E26: Custo pote pequeno | F26: Preço mínimo pote pequeno | G26: Margem real pote pequeno | H26: Custo pote grande | I26: Preço mínimo pote grande | J26: Margem real pote grande
A27: =Cores!A5 -> 1 | B27: =Cores!B5 -> Transparente brilhante | C27: =Cores!N5 -> 6.2 | D27: =Pincel!$B$8*(C27*(1+$B$20)+Pincel!$D$17)+$B$10+$B$11 -> 21.427063 | E27: =D27*$B$6/1000+$B$8 -> 5.6427062 | F27: =IF((1-$B$21-$B$22-$B$23)<=0,"inviável",E27/(1-$B$21-$B$22-$B$23)) -> 11.515727 | G27: =IF($B$12=0,0,($B$12*(1-$B$21-$B$22)-E27)/$B$12) -> 0.62831787 | H27: =D27*$B$7/1000+$B$9 -> 10.356766 | I27: =IF((1-$B$21-$B$22-$B$23)<=0,"inviável",H27/(1-$B$21-$B$22-$B$23)) -> 21.136256 | J27: =IF($B$13=0,0,($B$13*(1-$B$21-$B$22)-H27)/$B$13) -> 0.64183454
A28: =Cores!A6 -> 2 | B28: =Cores!B6 -> Transparente mate | C28: =Cores!N6 -> 5.455 | D28: =Pincel!$B$8*(C28*(1+$B$20)+Pincel!$D$17)+$B$10+$B$11 -> 20.694634 | E28: =D28*$B$6/1000+$B$8 -> 5.5694634 | F28: =IF((1-$B$21-$B$22-$B$23)<=0,"inviável",E28/(1-$B$21-$B$22-$B$23)) -> 11.366252 | G28: =IF($B$12=0,0,($B$12*(1-$B$21-$B$22)-E28)/$B$12) -> 0.63041652 | H28: =D28*$B$7/1000+$B$9 -> 10.173659 | I28: =IF((1-$B$21-$B$22-$B$23)<=0,"inviável",H28/(1-$B$21-$B$22-$B$23)) -> 20.762569 | J28: =IF($B$13=0,0,($B$13*(1-$B$21-$B$22)-H28)/$B$13) -> 0.6444541
A29: =Cores!A7 -> 3 | B29: =Cores!B7 -> Branco brilhante | C29: =Cores!N7 -> 10.172727 | D29: =Pincel!$B$8*(C29*(1+$B$20)+Pincel!$D$17)+$B$10+$B$11 -> 25.33275 | E29: =D29*$B$6/1000+$B$8 -> 6.033275 | F29: =IF((1-$B$21-$B$22-$B$23)<=0,"inviável",E29/(1-$B$21-$B$22-$B$23)) -> 12.312806 | G29: =IF($B$12=0,0,($B$12*(1-$B$21-$B$22)-E29)/$B$12) -> 0.61712679 | H29: =D29*$B$7/1000+$B$9 -> 11.333187 | I29: =IF((1-$B$21-$B$22-$B$23)<=0,"inviável",H29/(1-$B$21-$B$22-$B$23)) -> 23.128954 | J29: =IF($B$13=0,0,($B$13*(1-$B$21-$B$22)-H29)/$B$13) -> 0.6278657
A30: =Cores!A8 -> 4 | B30: =Cores!B8 -> Branco acetinado | C30: =Cores!N8 -> 6.9027778 | D30: =Pincel!$B$8*(C30*(1+$B$20)+Pincel!$D$17)+$B$10+$B$11 -> 22.117981 | E30: =D30*$B$6/1000+$B$8 -> 5.7117981 | F30: =IF((1-$B$21-$B$22-$B$23)<=0,"inviável",E30/(1-$B$21-$B$22-$B$23)) -> 11.656731 | G30: =IF($B$12=0,0,($B$12*(1-$B$21-$B$22)-E30)/$B$12) -> 0.62633816 | H30: =D30*$B$7/1000+$B$9 -> 10.529495 | I30: =IF((1-$B$21-$B$22-$B$23)<=0,"inviável",H30/(1-$B$21-$B$22-$B$23)) -> 21.488766 | J30: =IF($B$13=0,0,($B$13*(1-$B$21-$B$22)-H30)/$B$13) -> 0.63936344
A31: =Cores!A9 -> 5 | B31: =Cores!B9 -> Preto brilhante | C31: =Cores!N9 -> 22.149533 | D31: =Pincel!$B$8*(C31*(1+$B$20)+Pincel!$D$17)+$B$10+$B$11 -> 37.107447 | E31: =D31*$B$6/1000+$B$8 -> 7.2107447 | F31: =IF((1-$B$21-$B$22-$B$23)<=0,"inviável",E31/(1-$B$21-$B$22-$B$23)) -> 14.715805 | G31: =IF($B$12=0,0,($B$12*(1-$B$21-$B$22)-E31)/$B$12) -> 0.5833884 | H31: =D31*$B$7/1000+$B$9 -> 14.276862 | I31: =IF((1-$B$21-$B$22-$B$23)<=0,"inviável",H31/(1-$B$21-$B$22-$B$23)) -> 29.136452 | J31: =IF($B$13=0,0,($B$13*(1-$B$21-$B$22)-H31)/$B$13) -> 0.58575305
A32: =Cores!A10 -> 6 | B32: =Cores!B10 -> Tenmoku | C32: =Cores!N10 -> 6.65 | D32: =Pincel!$B$8*(C32*(1+$B$20)+Pincel!$D$17)+$B$10+$B$11 -> 21.869469 | E32: =D32*$B$6/1000+$B$8 -> 5.6869469 | F32: =IF((1-$B$21-$B$22-$B$23)<=0,"inviável",E32/(1-$B$21-$B$22-$B$23)) -> 11.606014 | G32: =IF($B$12=0,0,($B$12*(1-$B$21-$B$22)-E32)/$B$12) -> 0.62705023 | H32: =D32*$B$7/1000+$B$9 -> 10.467367 | I32: =IF((1-$B$21-$B$22-$B$23)<=0,"inviável",H32/(1-$B$21-$B$22-$B$23)) -> 21.361974 | J32: =IF($B$13=0,0,($B$13*(1-$B$21-$B$22)-H32)/$B$13) -> 0.64025226
A33: =Cores!A11 -> 7 | B33: =Cores!B11 -> Celadon verde | C33: =Cores!N11 -> 6.4039409 | D33: =Pincel!$B$8*(C33*(1+$B$20)+Pincel!$D$17)+$B$10+$B$11 -> 21.627562 | E33: =D33*$B$6/1000+$B$8 -> 5.6627562 | F33: =IF((1-$B$21-$B$22-$B$23)<=0,"inviável",E33/(1-$B$21-$B$22-$B$23)) -> 11.556645 | G33: =IF($B$12=0,0,($B$12*(1-$B$21-$B$22)-E33)/$B$12) -> 0.62774338 | H33: =D33*$B$7/1000+$B$9 -> 10.40689 | I33: =IF((1-$B$21-$B$22-$B$23)<=0,"inviável",H33/(1-$B$21-$B$22-$B$23)) -> 21.238552 | J33: =IF($B$13=0,0,($B$13*(1-$B$21-$B$22)-H33)/$B$13) -> 0.64111745
A34: =Cores!A12 -> 8 | B34: =Cores!B12 -> Celadon azul | C34: =Cores!N12 -> 7.2205737 | D34: =Pincel!$B$8*(C34*(1+$B$20)+Pincel!$D$17)+$B$10+$B$11 -> 22.430414 | E34: =D34*$B$6/1000+$B$8 -> 5.7430414 | F34: =IF((1-$B$21-$B$22-$B$23)<=0,"inviável",E34/(1-$B$21-$B$22-$B$23)) -> 11.720493 | G34: =IF($B$12=0,0,($B$12*(1-$B$21-$B$22)-E34)/$B$12) -> 0.62544294 | H34: =D34*$B$7/1000+$B$9 -> 10.607604 | I34: =IF((1-$B$21-$B$22-$B$23)<=0,"inviável",H34/(1-$B$21-$B$22-$B$23)) -> 21.64817 | J34: =IF($B$13=0,0,($B$13*(1-$B$21-$B$22)-H34)/$B$13) -> 0.63824602
A35: =Cores!A13 -> 9 | B35: =Cores!B13 -> Rutilo mel | C35: =Cores!N13 -> 13.458333 | D35: =Pincel!$B$8*(C35*(1+$B$20)+Pincel!$D$17)+$B$10+$B$11 -> 28.562911 | E35: =D35*$B$6/1000+$B$8 -> 6.3562911 | F35: =IF((1-$B$21-$B$22-$B$23)<=0,"inviável",E35/(1-$B$21-$B$22-$B$23)) -> 12.972023 | G35: =IF($B$12=0,0,($B$12*(1-$B$21-$B$22)-E35)/$B$12) -> 0.60787131 | H35: =D35*$B$7/1000+$B$9 -> 12.140728 | I35: =IF((1-$B$21-$B$22-$B$23)<=0,"inviável",H35/(1-$B$21-$B$22-$B$23)) -> 24.776996 | J35: =IF($B$13=0,0,($B$13*(1-$B$21-$B$22)-H35)/$B$13) -> 0.61631291
A36: =Cores!A14 -> 10 | B36: =Cores!B14 -> Creme pintalgado | C36: =Cores!N14 -> 11.601874 | D36: =Pincel!$B$8*(C36*(1+$B$20)+Pincel!$D$17)+$B$10+$B$11 -> 26.737779 | E36: =D36*$B$6/1000+$B$8 -> 6.1737779 | F36: =IF((1-$B$21-$B$22-$B$23)<=0,"inviável",E36/(1-$B$21-$B$22-$B$23)) -> 12.599547 | G36: =IF($B$12=0,0,($B$12*(1-$B$21-$B$22)-E36)/$B$12) -> 0.61310092 | H36: =D36*$B$7/1000+$B$9 -> 11.684445 | I36: =IF((1-$B$21-$B$22-$B$23)<=0,"inviável",H36/(1-$B$21-$B$22-$B$23)) -> 23.845806 | J36: =IF($B$13=0,0,($B$13*(1-$B$21-$B$22)-H36)/$B$13) -> 0.62284056
A37: =Cores!A15 -> 11 | B37: =Cores!B15 -> Azul cobalto | C37: =Cores!N15 -> 15.049505 | D37: =Pincel!$B$8*(C37*(1+$B$20)+Pincel!$D$17)+$B$10+$B$11 -> 30.127232 | E37: =D37*$B$6/1000+$B$8 -> 6.5127232 | F37: =IF((1-$B$21-$B$22-$B$23)<=0,"inviável",E37/(1-$B$21-$B$22-$B$23)) -> 13.291272 | G37: =IF($B$12=0,0,($B$12*(1-$B$21-$B$22)-E37)/$B$12) -> 0.60338902 | H37: =D37*$B$7/1000+$B$9 -> 12.531808 | I37: =IF((1-$B$21-$B$22-$B$23)<=0,"inviável",H37/(1-$B$21-$B$22-$B$23)) -> 25.575118 | J37: =IF($B$13=0,0,($B$13*(1-$B$21-$B$22)-H37)/$B$13) -> 0.61071805
A38: =Cores!A16 -> 12 | B38: =Cores!B16 -> Turquesa | C38: =Cores!N16 -> 12.136585 | D38: =Pincel!$B$8*(C38*(1+$B$20)+Pincel!$D$17)+$B$10+$B$11 -> 27.263468 | E38: =D38*$B$6/1000+$B$8 -> 6.2263468 | F38: =IF((1-$B$21-$B$22-$B$23)<=0,"inviável",E38/(1-$B$21-$B$22-$B$23)) -> 12.70683 | G38: =IF($B$12=0,0,($B$12*(1-$B$21-$B$22)-E38)/$B$12) -> 0.61159465 | H38: =D38*$B$7/1000+$B$9 -> 11.815867 | I38: =IF((1-$B$21-$B$22-$B$23)<=0,"inviável",H38/(1-$B$21-$B$22-$B$23)) -> 24.114014 | J38: =IF($B$13=0,0,($B$13*(1-$B$21-$B$22)-H38)/$B$13) -> 0.62096041
... A43: =Cores!A21 -> 17 | B43: =Cores!B21 -> Imitação de cinza | C43: =Cores!N21 -> 11.769953 | D43: =Pincel!$B$8*(C43*(1+$B$20)+Pincel!$D$17)+$B$10+$B$11 -> 26.903023 | E43: =D43*$B$6/1000+$B$8 -> 6.1903023 | F43: =IF((1-$B$21-$B$22-$B$23)<=0,"inviável",E43/(1-$B$21-$B$22-$B$23)) -> 12.63327 | G43: =IF($B$12=0,0,($B$12*(1-$B$21-$B$22)-E43)/$B$12) -> 0.61262744 | H43: =D43*$B$7/1000+$B$9 -> 11.725756 | I43: =IF((1-$B$21-$B$22-$B$23)<=0,"inviável",H43/(1-$B$21-$B$22-$B$23)) -> 23.930114 | J43: =IF($B$13=0,0,($B$13*(1-$B$21-$B$22)-H43)/$B$13) -> 0.62224956
B44: Média | C44: =AVERAGE(C27:C43) -> 12.421371 | D44: =AVERAGE(D27:D43) -> 27.543448 | E44: =AVERAGE(E27:E43) -> 6.2543448 | F44: =AVERAGE(F27:F43) -> 12.763969 | G44: =AVERAGE(G27:G43) -> 0.61079241 | H44: =AVERAGE(H27:H43) -> 11.885862 | I44: =AVERAGE(I27:I43) -> 24.256861 | J44: =AVERAGE(J27:J43) -> 0.61995906
A46: FASE 2 — Pó para o ceramista preparar (mergulho/banho)
A47: Nº | B47: Cor | C47: MP (R$/kg) | D47: MP + perdas (R$/kg) | E47: Custo produção (R$/kg) | F47: Custo 500 g (R$) | G47: Preço mínimo 500 g | H47: Custo 1 kg (R$) | I47: Preço mínimo 1 kg | J47: Lucro 1 kg (R$)
A48: =Cores!A5 -> 1 | B48: =Cores!B5 -> Transparente brilhante | C48: =Cores!N5 -> 6.2 | D48: =C48*(1+$B$20) -> 6.82 | E48: =D48+$B$17+$B$18 -> 17.82 | F48: =E48*0.5+$B$15 -> 13.41 | G48: =IF((1-$B$21-$B$22-$B$23)<=0,"inviável",F48/(1-$B$21-$B$22-$B$23)) -> 27.367347 | H48: =E48+$B$16 -> 24.32 | I48: =IF((1-$B$21-$B$22-$B$23)<=0,"inviável",H48/(1-$B$21-$B$22-$B$23)) -> 49.632653 | J48: =IF(ISNUMBER(I48),I48*$B$23,0) -> 14.889796
A49: =Cores!A6 -> 2 | B49: =Cores!B6 -> Transparente mate | C49: =Cores!N6 -> 5.455 | D49: =C49*(1+$B$20) -> 6.0005 | E49: =D49+$B$17+$B$18 -> 17.0005 | F49: =E49*0.5+$B$15 -> 13.00025 | G49: =IF((1-$B$21-$B$22-$B$23)<=0,"inviável",F49/(1-$B$21-$B$22-$B$23)) -> 26.531122 | H49: =E49+$B$16 -> 23.5005 | I49: =IF((1-$B$21-$B$22-$B$23)<=0,"inviável",H49/(1-$B$21-$B$22-$B$23)) -> 47.960204 | J49: =IF(ISNUMBER(I49),I49*$B$23,0) -> 14.388061
A50: =Cores!A7 -> 3 | B50: =Cores!B7 -> Branco brilhante | C50: =Cores!N7 -> 10.172727 | D50: =C50*(1+$B$20) -> 11.19 | E50: =D50+$B$17+$B$18 -> 22.19 | F50: =E50*0.5+$B$15 -> 15.595 | G50: =IF((1-$B$21-$B$22-$B$23)<=0,"inviável",F50/(1-$B$21-$B$22-$B$23)) -> 31.826531 | H50: =E50+$B$16 -> 28.69 | I50: =IF((1-$B$21-$B$22-$B$23)<=0,"inviável",H50/(1-$B$21-$B$22-$B$23)) -> 58.55102 | J50: =IF(ISNUMBER(I50),I50*$B$23,0) -> 17.565306
A51: =Cores!A8 -> 4 | B51: =Cores!B8 -> Branco acetinado | C51: =Cores!N8 -> 6.9027778 | D51: =C51*(1+$B$20) -> 7.5930556 | E51: =D51+$B$17+$B$18 -> 18.593056 | F51: =E51*0.5+$B$15 -> 13.796528 | G51: =IF((1-$B$21-$B$22-$B$23)<=0,"inviável",F51/(1-$B$21-$B$22-$B$23)) -> 28.156179 | H51: =E51+$B$16 -> 25.093056 | I51: =IF((1-$B$21-$B$22-$B$23)<=0,"inviável",H51/(1-$B$21-$B$22-$B$23)) -> 51.210317 | J51: =IF(ISNUMBER(I51),I51*$B$23,0) -> 15.363095
A52: =Cores!A9 -> 5 | B52: =Cores!B9 -> Preto brilhante | C52: =Cores!N9 -> 22.149533 | D52: =C52*(1+$B$20) -> 24.364486 | E52: =D52+$B$17+$B$18 -> 35.364486 | F52: =E52*0.5+$B$15 -> 22.182243 | G52: =IF((1-$B$21-$B$22-$B$23)<=0,"inviável",F52/(1-$B$21-$B$22-$B$23)) -> 45.269884 | H52: =E52+$B$16 -> 41.864486 | I52: =IF((1-$B$21-$B$22-$B$23)<=0,"inviável",H52/(1-$B$21-$B$22-$B$23)) -> 85.437726 | J52: =IF(ISNUMBER(I52),I52*$B$23,0) -> 25.631318
A53: =Cores!A10 -> 6 | B53: =Cores!B10 -> Tenmoku | C53: =Cores!N10 -> 6.65 | D53: =C53*(1+$B$20) -> 7.315 | E53: =D53+$B$17+$B$18 -> 18.315 | F53: =E53*0.5+$B$15 -> 13.6575 | G53: =IF((1-$B$21-$B$22-$B$23)<=0,"inviável",F53/(1-$B$21-$B$22-$B$23)) -> 27.872449 | H53: =E53+$B$16 -> 24.815 | I53: =IF((1-$B$21-$B$22-$B$23)<=0,"inviável",H53/(1-$B$21-$B$22-$B$23)) -> 50.642857 | J53: =IF(ISNUMBER(I53),I53*$B$23,0) -> 15.192857
A54: =Cores!A11 -> 7 | B54: =Cores!B11 -> Celadon verde | C54: =Cores!N11 -> 6.4039409 | D54: =C54*(1+$B$20) -> 7.044335 | E54: =D54+$B$17+$B$18 -> 18.044335 | F54: =E54*0.5+$B$15 -> 13.522167 | G54: =IF((1-$B$21-$B$22-$B$23)<=0,"inviável",F54/(1-$B$21-$B$22-$B$23)) -> 27.59626 | H54: =E54+$B$16 -> 24.544335 | I54: =IF((1-$B$21-$B$22-$B$23)<=0,"inviável",H54/(1-$B$21-$B$22-$B$23)) -> 50.09048 | J54: =IF(ISNUMBER(I54),I54*$B$23,0) -> 15.027144
A55: =Cores!A12 -> 8 | B55: =Cores!B12 -> Celadon azul | C55: =Cores!N12 -> 7.2205737 | D55: =C55*(1+$B$20) -> 7.9426311 | E55: =D55+$B$17+$B$18 -> 18.942631 | F55: =E55*0.5+$B$15 -> 13.971316 | G55: =IF((1-$B$21-$B$22-$B$23)<=0,"inviável",F55/(1-$B$21-$B$22-$B$23)) -> 28.512889 | H55: =E55+$B$16 -> 25.442631 | I55: =IF((1-$B$21-$B$22-$B$23)<=0,"inviável",H55/(1-$B$21-$B$22-$B$23)) -> 51.923737 | J55: =IF(ISNUMBER(I55),I55*$B$23,0) -> 15.577121
A56: =Cores!A13 -> 9 | B56: =Cores!B13 -> Rutilo mel | C56: =Cores!N13 -> 13.458333 | D56: =C56*(1+$B$20) -> 14.804167 | E56: =D56+$B$17+$B$18 -> 25.804167 | F56: =E56*0.5+$B$15 -> 17.402083 | G56: =IF((1-$B$21-$B$22-$B$23)<=0,"inviável",F56/(1-$B$21-$B$22-$B$23)) -> 35.514456 | H56: =E56+$B$16 -> 32.304167 | I56: =IF((1-$B$21-$B$22-$B$23)<=0,"inviável",H56/(1-$B$21-$B$22-$B$23)) -> 65.926871 | J56: =IF(ISNUMBER(I56),I56*$B$23,0) -> 19.778061
A57: =Cores!A14 -> 10 | B57: =Cores!B14 -> Creme pintalgado | C57: =Cores!N14 -> 11.601874 | D57: =C57*(1+$B$20) -> 12.762061 | E57: =D57+$B$17+$B$18 -> 23.762061 | F57: =E57*0.5+$B$15 -> 16.38103 | G57: =IF((1-$B$21-$B$22-$B$23)<=0,"inviável",F57/(1-$B$21-$B$22-$B$23)) -> 33.430674 | H57: =E57+$B$16 -> 30.262061 | I57: =IF((1-$B$21-$B$22-$B$23)<=0,"inviável",H57/(1-$B$21-$B$22-$B$23)) -> 61.759308 | J57: =IF(ISNUMBER(I57),I57*$B$23,0) -> 18.527792
A58: =Cores!A15 -> 11 | B58: =Cores!B15 -> Azul cobalto | C58: =Cores!N15 -> 15.049505 | D58: =C58*(1+$B$20) -> 16.554455 | E58: =D58+$B$17+$B$18 -> 27.554455 | F58: =E58*0.5+$B$15 -> 18.277228 | G58: =IF((1-$B$21-$B$22-$B$23)<=0,"inviável",F58/(1-$B$21-$B$22-$B$23)) -> 37.300465 | H58: =E58+$B$16 -> 34.054455 | I58: =IF((1-$B$21-$B$22-$B$23)<=0,"inviável",H58/(1-$B$21-$B$22-$B$23)) -> 69.498889 | J58: =IF(ISNUMBER(I58),I58*$B$23,0) -> 20.849667
A59: =Cores!A16 -> 12 | B59: =Cores!B16 -> Turquesa | C59: =Cores!N16 -> 12.136585 | D59: =C59*(1+$B$20) -> 13.350244 | E59: =D59+$B$17+$B$18 -> 24.350244 | F59: =E59*0.5+$B$15 -> 16.675122 | G59: =IF((1-$B$21-$B$22-$B$23)<=0,"inviável",F59/(1-$B$21-$B$22-$B$23)) -> 34.030861 | H59: =E59+$B$16 -> 30.850244 | I59: =IF((1-$B$21-$B$22-$B$23)<=0,"inviável",H59/(1-$B$21-$B$22-$B$23)) -> 62.959681 | J59: =IF(ISNUMBER(I59),I59*$B$23,0) -> 18.887904
... A64: =Cores!A21 -> 17 | B64: =Cores!B21 -> Imitação de cinza | C64: =Cores!N21 -> 11.769953 | D64: =C64*(1+$B$20) -> 12.946948 | E64: =D64+$B$17+$B$18 -> 23.946948 | F64: =E64*0.5+$B$15 -> 16.473474 | G64: =IF((1-$B$21-$B$22-$B$23)<=0,"inviável",F64/(1-$B$21-$B$22-$B$23)) -> 33.619335 | H64: =E64+$B$16 -> 30.446948 | I64: =IF((1-$B$21-$B$22-$B$23)<=0,"inviável",H64/(1-$B$21-$B$22-$B$23)) -> 62.136629 | J64: =IF(ISNUMBER(I64),I64*$B$23,0) -> 18.640989
B65: Média | C65: =AVERAGE(C48:C64) -> 12.421371 | D65: =AVERAGE(D48:D64) -> 13.663508 | E65: =AVERAGE(E48:E64) -> 24.663508 | F65: =AVERAGE(F48:F64) -> 16.831754 | G65: =AVERAGE(G48:G64) -> 34.350519 | H65: =AVERAGE(H48:H64) -> 31.163508 | I65: =AVERAGE(I48:I64) -> 63.598997 | J65: =AVERAGE(J48:J64) -> 19.079699
A67: Na Fase 2 o pó sai sem aditivos: o ceramista adiciona água (densidade de banho ~1,45–1,50). Inclua no rótulo a proporção sugerida de água.

Sheet Testes
A1: Registro de testes de queima — rodada 1 (pincel)
A2: 17 cores × 2 argilas × 2 e 3 demãos × 2 curvas = 136 placas. A linha 5 é um EXEMPLO preenchido.
A4: ID | B4: Data | C4: Lote | D4: Nº cor | E4: Cor | F4: Argila | G4: Demãos (pincel) | H4: Curva | I4: Cone 6 dobrou? | J4: Temp. máx (°C) | K4: Aparência geral (1–5) | L4: Marcas de pincel | M4: Gretamento | N4: Escorrimento | O4: Limão/vinagre 24h | P4: Choque térmico | Q4: Lixiviação | R4: Foto (link) | S4: Observações
A5: 1 | B5: 2026-11-03 | C5: L001 | D5: 1 | E5: =IFERROR(INDEX(Cores!$B$5:$B$21,MATCH(D5,Cores!$A$5:$A$21,0)),"") -> Transparente brilhante | F5: Clara | G5: 2 demãos | H5: Padrão | I5: Sim | J5: 1225 | K5: 4 | L5: Leve | M5: Nenhum | N5: Nenhum | O5: Nenhum | P5: Nenhum | Q5: Pendente | R5: drive/fotos/L001-01.jpg | S5: EXEMPLO — brilho uniforme, marcas leves de pincel com 2 demãos
A6: 2 | D6: 1 | E6: =IFERROR(INDEX(Cores!$B$5:$B$21,MATCH(D6,Cores!$A$5:$A$21,0)),"") -> Transparente brilhante | F6: Clara | G6: 2 demãos | H6: Resfriamento lento
A7: 3 | D7: 1 | E7: =IFERROR(INDEX(Cores!$B$5:$B$21,MATCH(D7,Cores!$A$5:$A$21,0)),"") -> Transparente brilhante | F7: Clara | G7: 3 demãos | H7: Padrão
A8: 4 | D8: 1 | E8: =IFERROR(INDEX(Cores!$B$5:$B$21,MATCH(D8,Cores!$A$5:$A$21,0)),"") -> Transparente brilhante | F8: Clara | G8: 3 demãos | H8: Resfriamento lento
A9: 5 | D9: 1 | E9: =IFERROR(INDEX(Cores!$B$5:$B$21,MATCH(D9,Cores!$A$5:$A$21,0)),"") -> Transparente brilhante | F9: Escura | G9: 2 demãos | H9: Padrão
A10: 6 | D10: 1 | E10: =IFERROR(INDEX(Cores!$B$5:$B$21,MATCH(D10,Cores!$A$5:$A$21,0)),"") -> Transparente brilhante | F10: Escura | G10: 2 demãos | H10: Resfriamento lento
A11: 7 | D11: 1 | E11: =IFERROR(INDEX(Cores!$B$5:$B$21,MATCH(D11,Cores!$A$5:$A$21,0)),"") -> Transparente brilhante | F11: Escura | G11: 3 demãos | H11: Padrão
A12: 8 | D12: 1 | E12: =IFERROR(INDEX(Cores!$B$5:$B$21,MATCH(D12,Cores!$A$5:$A$21,0)),"") -> Transparente brilhante | F12: Escura | G12: 3 demãos | H12: Resfriamento lento
A13: 9 | D13: 2 | E13: =IFERROR(INDEX(Cores!$B$5:$B$21,MATCH(D13,Cores!$A$5:$A$21,0)),"") -> Transparente mate | F13: Clara | G13: 2 demãos | H13: Padrão
A14: 10 | D14: 2 | E14: =IFERROR(INDEX(Cores!$B$5:$B$21,MATCH(D14,Cores!$A$5:$A$21,0)),"") -> Transparente mate | F14: Clara | G14: 2 demãos | H14: Resfriamento lento
A15: 11 | D15: 2 | E15: =IFERROR(INDEX(Cores!$B$5:$B$21,MATCH(D15,Cores!$A$5:$A$21,0)),"") -> Transparente mate | F15: Clara | G15: 3 demãos | H15: Padrão
A16: 12 | D16: 2 | E16: =IFERROR(INDEX(Cores!$B$5:$B$21,MATCH(D16,Cores!$A$5:$A$21,0)),"") -> Transparente mate | F16: Clara | G16: 3 demãos | H16: Resfriamento lento
A17: 13 | D17: 2 | E17: =IFERROR(INDEX(Cores!$B$5:$B$21,MATCH(D17,Cores!$A$5:$A$21,0)),"") -> Transparente mate | F17: Escura | G17: 2 demãos | H17: Padrão
... A140: 136 | D140: 17 | E140: =IFERROR(INDEX(Cores!$B$5:$B$21,MATCH(D140,Cores!$A$5:$A$21,0)),"") -> Imitação de cinza | F140: Escura | G140: 3 demãos | H140: Resfriamento lento

Sheet Estabilidade
A1: Estabilidade do líquido no pote (validade)
A2: Um pote fechado por cor/lote, guardado em temperatura ambiente. Avalie aos 7, 30 e 90 dias. A linha 5 é um EXEMPLO.
A4: Nº cor | B4: Cor | C4: Lote | D4: Data envase | E4: Densidade no envase (g/ml) | F4: Pincelabilidade (1–5) | G4: Sedimento 7 d | H4: Sedimento 30 d | I4: Sedimento 90 d | J4: Ressuspende com espátula? | K4: Mofo/odor 30 d | L4: Mofo/odor 90 d | M4: Densidade 90 d (g/ml) | N4: Aprovado p/ venda? | O4: Observações
A5: =Cores!A5 -> 1 | B5: =Cores!B5 -> Transparente brilhante | C5: L001 | D5: 2026-11-01 | E5: 1.56 | F5: 4 | G5: Nenhum | H5: Mole | J5: Sim | K5: Não | N5: Não | O5: EXEMPLO — aguardando leitura de 90 dias
A6: =Cores!A6 -> 2 | B6: =Cores!B6 -> Transparente mate
A7: =Cores!A7 -> 3 | B7: =Cores!B7 -> Branco brilhante
A8: =Cores!A8 -> 4 | B8: =Cores!B8 -> Branco acetinado
A9: =Cores!A9 -> 5 | B9: =Cores!B9 -> Preto brilhante
A10: =Cores!A10 -> 6 | B10: =Cores!B10 -> Tenmoku
A11: =Cores!A11 -> 7 | B11: =Cores!B11 -> Celadon verde
A12: =Cores!A12 -> 8 | B12: =Cores!B12 -> Celadon azul
A13: =Cores!A13 -> 9 | B13: =Cores!B13 -> Rutilo mel
A14: =Cores!A14 -> 10 | B14: =Cores!B14 -> Creme pintalgado
A15: =Cores!A15 -> 11 | B15: =Cores!B15 -> Azul cobalto
A16: =Cores!A16 -> 12 | B16: =Cores!B16 -> Turquesa
A17: =Cores!A17 -> 13 | B17: =Cores!B17 -> Amarelo
... A21: =Cores!A21 -> 17 | B21: =Cores!B21 -> Imitação de cinza
A23: Sedimento "Duro" ou mofo = reprovar o lote e revisar bentonita/CMC/conservante na aba Pincel.

Sheet Curva de Queima
A1: Curvas de queima — cone 6, forno elétrico
A2: Use cones pirométricos em toda queima de teste. Cone 6 grande: ~1222 °C a 60 °C/h; ~1243 °C a 150 °C/h (Orton).
A4: Curva | B4: Etapa | C4: Taxa (°C/h) | D4: De (°C) | E4: Até (°C) | F4: Patamar (min) | G4: Duração (h)
A5: Padrão | B5: 1. Aquecimento inicial | C5: 100 | D5: 25 | E5: 600 | F5: 0 | G5: =IF(ISNUMBER(C5),ABS(E5-D5)/C5,0)+F5/60 -> 5.75
A6: Padrão | B6: 2. Aquecimento | C6: 150 | D6: 600 | E6: 1100 | F6: 0 | G6: =IF(ISNUMBER(C6),ABS(E6-D6)/C6,0)+F6/60 -> 3.3333333
A7: Padrão | B7: 3. Final lento | C7: 60 | D7: 1100 | E7: 1225 | F7: 15 | G7: =IF(ISNUMBER(C7),ABS(E7-D7)/C7,0)+F7/60 -> 2.3333333
A8: Resfriamento lento | B8: 1. Aquecimento inicial | C8: 100 | D8: 25 | E8: 600 | F8: 0 | G8: =IF(ISNUMBER(C8),ABS(E8-D8)/C8,0)+F8/60 -> 5.75
A9: Resfriamento lento | B9: 2. Aquecimento | C9: 150 | D9: 600 | E9: 1100 | F9: 0 | G9: =IF(ISNUMBER(C9),ABS(E9-D9)/C9,0)+F9/60 -> 3.3333333
A10: Resfriamento lento | B10: 3. Final lento | C10: 60 | D10: 1100 | E10: 1225 | F10: 15 | G10: =IF(ISNUMBER(C10),ABS(E10-D10)/C10,0)+F10/60 -> 2.3333333
A11: Resfriamento lento | B11: 4. Queda livre (forno desligado) | C11: livre | D11: 1225 | E11: 1100 | F11: 0 | G11: =IF(ISNUMBER(C11),ABS(E11-D11)/C11,0)+F11/60 -> 0
A12: Resfriamento lento | B12: 5. Resfriamento controlado | C12: 80 | D12: 1100 | E12: 800 | F12: 0 | G12: =IF(ISNUMBER(C12),ABS(E12-D12)/C12,0)+F12/60 -> 3.75
A14: Total curva padrão (h) | G14: =SUM(G5:G7) -> 11.416667
A15: Total resfriamento lento, até 800 °C (h) | G15: =SUM(G8:G12) -> 15.166667
A17: Biscoito sugerido: cone 04 (~1060 °C). Esmaltes aplicados sobre biscoito por imersão; densidade de partida 1,45–1,50 g/ml.
